Workbook

Sheet List of documents
A1: Name of the document | B1: Institution | C1: URL | D1: Authors | E1: Affiliates | F1: Sector | G1: Country | H1: Date | I1: Keywords | J1: Exclusion criteria | K1: Status | L1: Label | M1: MapAIE (ours) | N1: Jobin | O1: Fjeld | P1: Tidjon | Q1: Hagendorff | R1: Floridi | S1: Zeng (LAIP) | T1: Attard-Frost | U1: EP | V1: Algorithm watch | W1: CE | X1: Winfield | Y1: EthicalML GitHub | Z1: all sources | AA1: Checked by | AB1: Random
A2: A Unified Framework of Five Principles for AI in Society | B2: . | C2: https://hdsr.mitpress.mit.edu/pub/l0jsh9d1/release/8 | K2: Not included | L2: meta analysis | M2: =IF(LOWER(K2)="included", 1,0) -> 0 | X2: 1 | Z2: =SUM(N2:Y2) -> 1 | AA2: Maria
A3: AI Decolonial Manyfesto | B3: . | C3: https://manyfesto.ai/ | D3: Aarathi Krishnan, Angie Abdilla, A Jung Moon, Carlos Affonso Souza, Chelle Adamson, Eileen M. Lach, Farah Ghazal, Jessica Fjeld, Jennyfer Taylor, John C. Havens, Malavika Jayaram, Monique Morrow, Nagla Rizk, Paola Ricaurte Quijano, R. Buse Çetin, Raja Chatila, Ravit Dotan, Sabelo Mhlambi, Sara Jordan, Sarita Rosenstock | E3: . | F3: civil society | G3: international | H3: 2021 | I3: collective, decolonial, petition | K3: Not included | L3: not cited | M3: =IF(LOWER(K3)="included", 1,0) -> 0 | Z3: =SUM(N3:Y3) -> 0 | AA3: Maria | AB3: Should be included if was cited by anyone
A4: Asimov’s three laws of Robotics | B4: . | K4: Not included | L4: not accessible | M4: =IF(LOWER(K4)="included", 1,0) -> 0 | X4: 1 | Z4: =SUM(N4:Y4) -> 1 | AA4: Maria
A5: AI Index 2022 | B5: University of Stanford, SRI International, MIT, OpenAI, McKinsey Global Institute, Partnership on AI, Harvard University | C5: https://aiindex.stanford.edu/wp-content/uploads/2022/03/2022-AI-Index-Report_Master.pdf | F5: academia, private sector | G5: USA | H5: 2022 | K5: included | L5: SPI | M5: =IF(LOWER(K5)="included", 1,0) -> 1 | W5: 1 | Z5: =SUM(N5:Y5) -> 1 | AA5: Simon | AB5: 0.001920514
A6: 2030 Digital Compass: the European way for the Digital Decade | B6: European Commission | C6: https://eur-lex.europa.eu/legal-content/en/TXT/?uri=CELEX%3A52021DC0118 | F6: international organisation > EU institution | G6: international | H6: 09/03/2021 | K6: Included | L6: SPI | M6: =IF(LOWER(K6)="included", 1,0) -> 1 | W6: 1 | Z6: =SUM(N6:Y6) -> 1 | AA6: Maria | AB6: 0.002177313
A7: Global competition and convergence of AI Law | B7: Vrije Universiteit Brussel | C7: https://osf.io/preprints/socarxiv/j36ke/ | F7: academia | G7: Belgium | H7: 2021 | K7: included | L7: SPI field-specific | M7: =IF(LOWER(K7)="included", 1,0) -> 1 | W7: 1 | Z7: =SUM(N7:Y7) -> 1 | AA7: Simon | AB7: 0.005935097
A8: Six Principles of Artificial Intelligence | B8: . | C8: http://it.people.com.cn/n1/2020/0309/c1009-31622757.html | G8: China | K8: Not included | L8: not in english | M8: =IF(LOWER(K8)="included", 1,0) -> 0 | S8: 1 | Z8: =SUM(N8:Y8) -> 1 | AA8: Maria
A9: The #FreeAI Manifesto | B9: . | C9: https://github.com/freeai-manifesto/manifesto | D9: Maxim Orlovsky, Andrey Sobol | E9: . | F9: civil society | G9: international | H9: 2018 | I9: manifest machine-learning, neural-network, decentralized, manifesto, artificial-intelligence, neural-networks, floss, cognitive-science, decentralization, anarchy, anarchism, skynet, transhumanism, anarcho-capitalism, austrian-school-economics | K9: Not included | L9: not cited | M9: =IF(LOWER(K9)="included", 1,0) -> 0 | Z9: =SUM(N9:Y9) -> 0 | AA9: Maria | AB9: Should be included if was cited by anyone
A10: Technology rules? The advent of new technologies in the justice system | B10: House of Lords, Justice and Home affairs Committee (United Kingdom) | C10: https://publications.parliament.uk/pa/ld5802/ldselect/ldjusthom/180/180.pdf | F10: national authority | G10: UK | H10: 30/03/2022 | K10: Included | L10: SPI | M10: =IF(LOWER(K10)="included", 1,0) -> 1 | W10: 1 | Z10: =SUM(N10:Y10) -> 1 | AA10: Maria | AB10: 0.0075751195
A11: Algorithmic discrimination in Europe: Challenges and opportunities for gender equality and non-discrimination law | B11: European Commission (European network of legal experts in gender equality and non-discrimination) | C11: https://op.europa.eu/en/publication-detail/-/publication/082f1dbc-821d-11eb-9ac9-01aa75ed71a1 | F11: international organisation > EU institution | G11: EU | H11: 10/2020 | K11: Included | L11: SPI, issue-specific | M11: =IF(LOWER(K11)="included", 1,0) -> 1 | W11: 1 | Z11: =SUM(N11:Y11) -> 1 | AA11: Maria | AB11: 0.0076317783
A12: Universal Principles of Data Ethics | B12: Accenture | C12: https://www.accenture.com/t20160629T012639Z__w__/us-en/_acnmedia/PDF-24/Accenture-Universal-Principles-Data-Ethics.pdf new URL https://fr.scribd.com/document/450122018/Accenture-Universal-Principles-Data-Ethics# | G12: USA | K12: not included | L12: not ai ethics | M12: =IF(LOWER(K12)="included", 1,0) -> 0 | V12: 1 | W12: 1 | Z12: =SUM(N12:Y12) -> 2 | AA12: Tiphaine
A13: Responsible AI and robotics. An ethical framework. | B13: Accenture UK | C13: https://www.accenture.com/gb-en/company-responsible-ai-robotics | D13: . | E13: . | F13: private sector | G13: UK | H13: 2018 | K13: Not included | L13: initial url does not work and couldn't find new url | M13: =IF(LOWER(K13)="included", 1,0) -> 0 | N13: 1 | V13: 1 | W13: 1 | Z13: =SUM(N13:Y13) -> 3 | AA13: Maria
A14: AI Index 2019 | B14: University of Stanford, SRI International, MIT, OpenAI, McKinsey Global Institute, Partnership on AI, Harvard University | C14: https://hai.stanford.edu/sites/default/files/ai_index_2019_report.pdf | F14: academia, private sector | G14: USA | H14: 2019 | K14: included | L14: SPI | M14: =IF(LOWER(K14)="included", 1,0) -> 1 | W14: 1 | Z14: =SUM(N14:Y14) -> 1 | AA14: Simon | AB14: 0.010958856
A15: Artificial intelligence and the control of COVID-19 | B15: Council of Europe | C15: https://www.coe.int/en/web/artificial-intelligence/ai-and-control-of-covid-19-coronavirus | F15: international organisation > IGO | G15: EU | H15: 2020 | K15: included | L15: SPI issue-specific | M15: =IF(LOWER(K15)="included", 1,0) -> 1 | W15: 1 | Z15: =SUM(N15:Y15) -> 1 | AA15: Mel | AB15: 0.012365108
A16: Unified Ethical Frame for Big Data Analysis. IAF Big Data Ethics Initiative, Part A | B16: The Information Accountability Foundation | C16: https://bigdata.fpf.org/wp-content/uploads/2015/11/IAF-Unified-Ethical-Frame-for-Big-Data-Analysis.pdf | F16: international organisation > IGO | G16: UK | H16: 03/2015 | K16: included | L16: digital | M16: =IF(LOWER(K16)="included", 1,0) -> 1 | N16: 1 | V16: 1 | W16: 1 | Z16: =SUM(N16:Y16) -> 3 | AA16: Simon | AB16: 0.014377841
A17: Artificial Intelligence | B17: Samsung Research | C17: https://research.samsung.com/artificial-intelligence | F17: private sector | G17: South Korea | K17: included | L17: digital | M17: =IF(LOWER(K17)="included", 1,0) -> 1 | S17: 1 | Z17: =SUM(N17:Y17) -> 1 | AA17: Simon | AB17: 0.015867834
A18: Mapping Regulatory Proposals for AI in Europe | B18: AccessNow | C18: accessnow.org/wp-content/uploads/2018/11/mapping_regulatory_proposals_for_AI_in_EU.pdf | G18: USA | H18: 43405 | K18: not included | L18: meta-analysis | M18: =IF(LOWER(K18)="included", 1,0) -> 0 | W18: 1 | Z18: =SUM(N18:Y18) -> 1 | AA18: Tiphaine
A19: The EURON Roboethics Roadmap | B19: The European Robotics Research Network (EURON) | C19: http://www.roboethics.org/index_file/Roboethics%20Roadmap%20Rel.1.2.pdf | F19: academia | G19: EU | H19: 01/2007 | K19: included | L19: SPI digital | M19: =IF(LOWER(K19)="included", 1,0) -> 1 | U19: 1 | Z19: =SUM(N19:Y19) -> 1 | AA19: Simon | AB19: 0.018161725
A20: Ethics Canvas | B20: Adapt Center | C20: https://www.ethicscanvas.org/index.html | G20: Ireland | K20: not included | L20: not ai ethics | M20: =IF(LOWER(K20)="included", 1,0) -> 0 | P20: 1 | W20: 1 | Z20: =SUM(N20:Y20) -> 2 | AA20: Tiphaine
A21: Algorithm Data Ethics Label | B21: ADEL | C21: http://www.adel-label.com/adel/ | G21: France | K21: not included | L21: not in english | M21: =IF(LOWER(K21)="included", 1,0) -> 0 | V21: 1 | W21: 1 | Z21: =SUM(N21:Y21) -> 2 | AA21: Tiphaine
A22: Understanding Artificial Intelligence and Safety - A guide for the responsible design and implementation of AI systems in the public sector | B22: The Alan Turing Institute | C22: https://www.turing.ac.uk/sites/default/files/2019-06/understanding_artificial_intelligence_ethics_and_safety.pdf | F22: national authority, academia | G22: UK | H22: 2019 | K22: included | M22: =IF(LOWER(K22)="included", 1,0) -> 1 | S22: 1 | T22: 1 | V22: 1 | W22: 1 | Y22: 1 | Z22: =SUM(N22:Y22) -> 5 | AA22: Mel | AB22: 0.024087373
A23: Digital Ethics: A guide for professionals of the Digital Age | B23: CIGREF/Syntec Numérique | C23: https://www.cigref.fr/wp/wp-content/uploads/2019/02/Cigref-Syntec-Digital-Ethics-Guide-for-Professionals-of-Digital-Age-2018-October-EN.pdf | F23: civil society > other | G23: France | H23: 10/2018 | K23: included | L23: SPI digital | M23: =IF(LOWER(K23)="included", 1,0) -> 1 | V23: 1 | W23: 1 | Z23: =SUM(N23:Y23) -> 2 | AA23: Mel | AB23: 0.024125463
A24: Human Rights, Democracy, and the Rule of Law Assurance Framework for AI Systems: A proposal prepared for the Council of Europe’s Ad hoc Committee on Artificial Intelligence | B24: The Alan Turing Institute | C24: https://rm.coe.int/huderaf-coe-final-1-2752-6741-5300-v-1/1680a3f688 | F24: national authority, academia | G24: UK | H24: 2021 | K24: included | L24: SPI issue-specific | M24: =IF(LOWER(K24)="included", 1,0) -> 1 | W24: 1 | Z24: =SUM(N24:Y24) -> 1 | AA24: Simon | AB24: 0.035240019
A25: Study on AI Governance by Human Rights-Centred Design, Deliberation and Oversight | B25: University of Birmingham | C25: https://papers.ssrn.com/sol3/papers.cfm?abstract_id=3435011 | F25: academia | G25: UK | H25: 09/08/2019 | K25: included | L25: SPI digital | M25: =IF(LOWER(K25)="included", 1,0) -> 1 | W25: 1 | Z25: =SUM(N25:Y25) -> 1 | AA25: Simon | AB25: 0.035973615
A26: European ethical Charter on the use of Artificial Intelligence in judicial systems and their environment | B26: Council of Europe: European Commission for the efficiency of Justice (CEPEJ) | C26: https://rm.coe.int/ethical-charter-en-for-publication-4-december-2018/16808f699c | F26: international organisation > IGO | G26: EU | H26: 04/12/2018 | K26: included | L26: field-specific | M26: =IF(LOWER(K26)="included", 1,0) -> 1 | N26: 1 | O26: 1 | T26: 1 | V26: 1 | W26: 1 | X26: 1 | Z26: =SUM(N26:Y26) -> 6 | AA26: Mel | AB26: 0.037653615
A27: The Road to a Human-Centred Digital Society | B27: Centre on AI Technology for Humanking (AiTH) at NUS Business School | C27: https://drive.google.com/uc?export=download&id=1aRyqczni56ONA9PVExt2DrrJ1ATGKSu0 | D27: David De Cremer, Devesh Narayanan, Andreas Deppeler, Mahak Nagpal, Jack McGuire, Jess Zhang | E27: National University of Singapore | F27: academia | G27: Singapore | H27: 12/2021 | K27: included | M27: =IF(LOWER(K27)="included", 1,0) -> 1 | Z27: =SUM(N27:Y27) -> 0 | AA27: Mel | AB27: 0.045590909
A28: AI Roadmap | B28: AI Council (United Kingdom) | C28: https://assets.publishing.service.gov.uk/media/5ff3bc6e8fa8f53b76ccee23/AI_Council_AI_Roadmap.pdf | F28: national authority | G28: UK | H28: 01/2021 | K28: included | L28: SPI | M28: =IF(LOWER(K28)="included", 1,0) -> 1 | W28: 1 | Z28: =SUM(N28:Y28) -> 1 | AA28: Tiphaine | AB28: 0.046481623
A29: Growing the artificial intelligence industry in the UK | B29: Department for Digital, Culture, Media & Sport and Department for Business, Energy & Industrial Strategy (United Kingdom) | C29: https://www.gov.uk/government/publications/growing-the-artificial-intelligence-industry-in-the-uk | F29: national authority | G29: UK | H29: 15/10/2017 | K29: included | M29: =IF(LOWER(K29)="included", 1,0) -> 1 | W29: 1 | Z29: =SUM(N29:Y29) -> 1 | AA29: Tiphaine | AB29: 0.051865015
A30: AI Now 2017 Report | B30: AI Now Institute | C30: https://ainowinstitute.org/wp-content/uploads/2023/04/AI_Now_2017_Report.pdf | F30: civil society > NGO | G30: USA | H30: 2017 | K30: included | L30: SPI | M30: =IF(LOWER(K30)="included", 1,0) -> 1 | N30: 1 | Q30: 1 | Z30: =SUM(N30:Y30) -> 2 | AA30: Tiphaine | AB30: 0.055135916
A31: Algorithms in Decision Making | B31: Parliament Science and Technology Committee (United Kingdom) | C31: https://publications.parliament.uk/pa/cm201719/cmselect/cmsctech/351/351.pdf | F31: national authority | G31: UK | H31: 23/05/2018 | K31: included | L31: SPI | M31: =IF(LOWER(K31)="included", 1,0) -> 1 | W31: 1 | Z31: =SUM(N31:Y31) -> 1 | AA31: Simon | AB31: 0.055506496
A32: Thematic Reviews on 'Social Aspects of Digitalisation' (SPC) and 'Digitalisation and Robotisation of Work' (EMCO) - Endorsement of the joint key messages, 14411/18 | B32: Council of the European Union | C32: http://data.consilium.europa.eu/doc/document/ST-14411-2018-INIT/en/pdf | F32: international organisation > EU institution | G32: EU | H32: 19/11/2018 | K32: included | L32: SPI (study) | M32: =IF(LOWER(K32)="included", 1,0) -> 1 | W32: 1 | Z32: =SUM(N32:Y32) -> 1 | AA32: Tiphaine | AB32: 0.057972697
A33: Standards for AI Governance: International Standards to Enable Global Coordination in AI Research & Development | B33: Future of Humanity Institute, University of Oxford | C33: https://www.fhi.ox.ac.uk/wp-content/uploads/Standards_-FHI-Technical-Report.pdf | F33: academia | G33: international | H33: 04/2019 | K33: included | L33: field-specific | M33: =IF(LOWER(K33)="included", 1,0) -> 1 | W33: 1 | Z33: =SUM(N33:Y33) -> 1 | AA33: Tiphaine | AB33: 0.05949517
A34: Preparing the future of AI | B34: National Science and Technology Council (US) | C34: https://obamawhitehouse.archives.gov/sites/default/files/whitehouse_files/microsites/ostp/NSTC/preparing_for_the_future_of_ai.pdf | F34: national authority | G34: USA | H34: 10/2016 | K34: Included | L34: SPI | M34: =IF(LOWER(K34)="included", 1,0) -> 1 | W34: 1 | Z34: =SUM(N34:Y34) -> 1 | AA34: Maria | AB34: 0.062190447
A35: AI Now Report 2016. The Social and Economic Implications of Artificial Intelligence Technologies in the Near-Term | B35: AI Now Institute | C35: https://assets.ctfassets.net/8wprhhvnpfc0/3JOy5k4f1YSCQOi8MCCmA2/97010d04fbc7892662ce8b2469dc1601/AI_Now_2016_Report.pdf | F35: civil society > NGO | G35: USA | H35: 22/09/2016 | K35: included | L35: SPI | M35: =IF(LOWER(K35)="included", 1,0) -> 1 | N35: 1 | Q35: 1 | Z35: =SUM(N35:Y35) -> 2 | AA35: Tiphaine | AB35: 0.064955985
A36: Overview of National AI-Strategies | B36: AISOMA | C36: https://www.aisoma.de/wp-content/uploads/2021/01/Overview-of-National-AI-Strategies.pdf | G36: Germany | K36: not included | L36: meta-analysis | M36: =IF(LOWER(K36)="included", 1,0) -> 0 | W36: 1 | Z36: =SUM(N36:Y36) -> 1 | AA36: Tiphaine
A37: A toolkit for centering racial equity throughout data integration | B37: AISP | C37: https://aisp.upenn.edu/wp-content/uploads/2022/07/AISP-Toolkit_5.27.20.pdf | G37: USA | K37: not included | L37: tool | M37: =IF(LOWER(K37)="included", 1,0) -> 0 | P37: 1 | Z37: =SUM(N37:Y37) -> 1 | AA37: Tiphaine
A38: G20 AI Principles | B38: Ministry of Internal Affairs and Communications | C38: https://www.mofa.go.jp/policy/economy/g20_summit/osaka19/pdf/documents/en/annex_08.pdf | F38: national authority | G38: Japan | H38: 2019 | K38: included | M38: =IF(LOWER(K38)="included", 1,0) -> 1 | O38: 1 | Z38: =SUM(N38:Y38) -> 1 | AA38: Mel | AB38: 0.068610258
A39: Principles for the Governance of AI | B39: The Future Society Science Law and Society (SLS) Initiative | C39: https://thefuturesociety.org/principles-law-and-society-initiative/ | F39: civil society | G39: USA | H39: 15/07/2017 | K39: included | M39: =IF(LOWER(K39)="included", 1,0) -> 1 | N39: 1 | S39: 1 | U39: 1 | V39: 1 | W39: 1 | X39: 1 | Z39: =SUM(N39:Y39) -> 6 | AA39: Mel | AB39: 0.069249899
A40: 4 Steps to developing Responsible AI | B40: World Economic Forum (WEF) | C40: https://www.weforum.org/agenda/2019/06/4-steps-to-developing-responsible-ai/ | F40: civil society > NGO | G40: international | H40: 20/06/2019 | K40: included | L40: SPI | M40: =IF(LOWER(K40)="included", 1,0) -> 1 | W40: 1 | Z40: =SUM(N40:Y40) -> 1 | AA40: Simon | AB40: 0.070283627
A41: AI and Human Rights | B41: All Tech is Human | C41: https://alltechishuman.org/ai-human-rights-report | G41: USA | K41: not included | L41: not accessible | M41: =IF(LOWER(K41)="included", 1,0) -> 0 | W41: 1 | Z41: =SUM(N41:Y41) -> 1 | AA41: Tiphaine
A42: Opinion on AI - The consequences of artificial intelligence on the (digital) single market, production, consumption, employment and society’ | B42: European Economic and Social Committee (EESC) | C42: https://eur-lex.europa.eu/legal-content/EN/TXT/PDF/?uri=CELEX:52016IE5369&from=EN | F42: international organisation > EU institution | G42: international | H42: 31/08/2017 | K42: included | M42: =IF(LOWER(K42)="included", 1,0) -> 1 | W42: 1 | Z42: =SUM(N42:Y42) -> 1 | AA42: Mel | AB42: 0.071336055
A43: How to regulate AI | B43: Allen Institute for Artificial Intelligence – AI2 (Oren Etzioni, professor of Computer Science) | C43: https://www.nytimes.com/2017/09/01/opinion/artificial-intelligence-regulations-rules.html | G43: USA | K43: not included | L43: not accessible | M43: =IF(LOWER(K43)="included", 1,0) -> 0 | S43: 1 | W43: 1 | Z43: =SUM(N43:Y43) -> 2 | AA43: Tiphaine
A44: Human Rights Impact Assessments for AI: Analysis and Recommendations | B44: AccessNow | C44: https://www.accessnow.org/cms/assets/uploads/2022/11/Access-Now-Version-Human-Rights-Implications-of-Algorithmic-Impact-Assessments_-Priority-Recommendations-to-Guide-Effective-Development-and-Use.pdf | F44: civil society > NGO | G44: USA | H44: 10/2022 | K44: included | L44: SPI | M44: =IF(LOWER(K44)="included", 1,0) -> 1 | W44: 1 | Z44: =SUM(N44:Y44) -> 1 | AA44: Tiphaine | AB44: 0.073121775
A45: Report on Artificial intelligence in health care: medical, legal and ethical challenges ahead | B45: Council of Europe (Parliamentary Assembly) | C45: https://pace.coe.int/files/28737/pdf | F45: international organisation > IGO | G45: EU | H45: 01/10/2020 | K45: included | L45: field-specific | M45: =IF(LOWER(K45)="included", 1,0) -> 1 | W45: 1 | Z45: =SUM(N45:Y45) -> 1 | AA45: Tiphaine | AB45: 0.073720556
A46: Recomendations on the inclusion subSaharan Africa in Global AI Ethics | B46: Research ICT Africa | C46: https://researchictafrica.net/ranitp2019-2-ai-ethics/ | F46: civil society > other | G46: South Africa | H46: 02/2019 | K46: included | L46: issue-specific | M46: =IF(LOWER(K46)="included", 1,0) -> 1 | P46: 1 | Z46: =SUM(N46:Y46) -> 1 | AA46: Simon | AB46: 0.074387829
A47: Our principles | B47: Google | C47: https://blog.google/technology/ai/ai-principles/ | D47: . | E47: . | F47: private sector | G47: USA | H47: 2018 | I47: tech, principles | K47: included | M47: =IF(LOWER(K47)="included", 1,0) -> 1 | N47: 1 | O47: 1 | Q47: 1 | S47: 1 | T47: 1 | V47: 1 | W47: 1 | X47: 1 | Z47: =SUM(N47:Y47) -> 8 | AA47: Mel | AB47: 0.076122277
A48: Unfairness by algorithm: Distilling the Harms of automated decision making | B48: Future of Privacy Forum | C48: https://fpf.org/wp-content/uploads/2017/12/FPF-Automated-Decision-Making-Harms-and-Mitigation-Charts.pdf | F48: civil society > other | G48: USA | H48: 12/2017 | K48: included | L48: SPI issue-specific | M48: =IF(LOWER(K48)="included", 1,0) -> 1 | V48: 1 | Z48: =SUM(N48:Y48) -> 1 | AA48: Mel | AB48: 0.082324586
A49: Automated Decision-Making Under the GDPR: Practical Cases from Courts and Data Protection Authorities | B49: Future of Privacy Forum | C49: https://fpf.org/wp-content/uploads/2022/05/FPF-ADM-Report-R2-singles.pdf | F49: civil society > other | G49: USA | H49: 05/2022 | K49: included | L49: SPI digital issue-specific | M49: =IF(LOWER(K49)="included", 1,0) -> 1 | W49: 1 | Z49: =SUM(N49:Y49) -> 1 | AA49: Mel | AB49: 0.082751483
A50: Guidelines on Automated individual decision-making and Profiling for the purposes of Regulation 2016/679 | B50: Article 29 Working Party | C50: https://ec.europa.eu/newsroom/document.cfm?doc_id=47742 | G50: international | K50: not included | L50: not AI ethics | M50: =IF(LOWER(K50)="included", 1,0) -> 0 | W50: 1 | Z50: =SUM(N50:Y50) -> 1 | AA50: Mel
A51: It’s Time to Do Something: Mitigating the Negative Impacts of Computing Through a Change to the Peer Review Process | B51: Association for Computing Machinery - Future of Computing Machinery | C51: https://perma.cc/K22T-5DFU | G51: USA | K51: not included | L51: not AI ethics | M51: =IF(LOWER(K51)="included", 1,0) -> 0 | V51: 1 | Z51: =SUM(N51:Y51) -> 1 | AA51: Mel
A52: Policy Statement on Mandatory Engineered Law Enforcement Access | B52: Association for Computing Machinery - Future of Computing Machinery | C52: https://www.acm.org/binaries/content/assets/public-policy/usacm/2018-usacm-statement-law-enforcement-access.pdf | G52: USA | K52: not included | L52: not AI ethics | M52: =IF(LOWER(K52)="included", 1,0) -> 0 | U52: 1 | Z52: =SUM(N52:Y52) -> 1 | AA52: Mel
A53: Big Data and AI Principles in Engineering | B53: World Federation of Engineering Organizations (WEFO) | C53: http://www.wfeo.org/big-data-and-ai-principles-in-engineering/ | F53: civil society > NGO | G53: France | H53: 2020 | K53: included | L53: digital | M53: =IF(LOWER(K53)="included", 1,0) -> 1 | W53: 1 | Z53: =SUM(N53:Y53) -> 1 | AA53: Simon | AB53: 0.08365285
A54: RFI for AI Services | B54: TBS Canada | C54: https://buyandsell.gc.ca/cds/public/2018/06/28/05baa93c08b6f2d3000855170f831066/ABES.PROD.PW__EE.B017.E33657.EBSU000.PDF | F54: national authority | G54: Canada | H54: 28/06/2018 | K54: included | L54: SPI field-specific | M54: =IF(LOWER(K54)="included", 1,0) -> 1 | S54: 1 | Z54: =SUM(N54:Y54) -> 1 | AA54: Simon | AB54: 0.088868266
A55: Statement on Internet of Things Privacy and Security | B55: Association for Computing Machinery - Future of Computing Machinery | C55: https://www.acm.org/binaries/content/assets/public-policy/2017_joint_statement_iotprivacysecurity.pdf | G55: USA | K55: not included | L55: not AI ethics | M55: =IF(LOWER(K55)="included", 1,0) -> 0 | U55: 1 | Z55: =SUM(N55:Y55) -> 1 | AA55: Mel
A56: ACM Code of Ethics and Professional Conduct | B56: Association for Computing Machinery (ACM) | C56: https://www.acm.org/code-of-ethics | G56: USA | K56: not included | L56: not AI ethics | M56: =IF(LOWER(K56)="included", 1,0) -> 0 | Y56: 1 | Z56: =SUM(N56:Y56) -> 1 | AA56: Mel
A57: Beyond pilots: sustainable implementation of AI in public services | B57: European Commission (Joint Research Centre, AI Watch) | C57: https://publications.jrc.ec.europa.eu/repository/bitstream/JRC126665/jrc126665_sustainable_implementation_of_ai_in_public_services_technical-report_v2.pdf | F57: international organisation > EU institution | G57: EU | H57: 2021 | K57: included | L57: SPI | M57: =IF(LOWER(K57)="included", 1,0) -> 1 | W57: 1 | Z57: =SUM(N57:Y57) -> 1 | AA57: Tiphaine | AB57: 0.088906356
A58: Addressing Ethical Dilemmas in AI: Listening to Engineers | B58: Association of Nordic Engineers, IEEE, the Data Ethics ThinkDoTank (DataEthics.eu), University of Copenhagen | C58: https://standards.ieee.org/initiatives/autonomous-intelligence-systems/ethical-dilemmas-ai-report/ | G58: USA | K58: not included | L58: not accessible | M58: =IF(LOWER(K58)="included", 1,0) -> 0 | W58: 1 | Z58: =SUM(N58:Y58) -> 1 | AA58: Mel
A59: Open letter: Civil society call for the introduction of red lines in the upcoming European Commission proposal on Artificial Intelligence | B59: European Digital Rights (EDRi) | C59: https://edri.org/wp-content/uploads/2021/01/EDRi-open-letter-AI-red-lines.pdf | F59: civil society > NGO | G59: Belgium | H59: 12/01/2021 | K59: included | L59: SPI | M59: =IF(LOWER(K59)="included", 1,0) -> 1 | W59: 1 | Z59: =SUM(N59:Y59) -> 1 | AA59: Mel | AB59: 0.091418569
A60: Human Rights and Technology | B60: Australian Human Rights Commission | C60: https://tech.humanrights.gov.au/sites/default/files/2021-05/AHRC_RightsTech_2021_Final_Report.pdf | G60: Australia | K60: not included | L60: not accessible | M60: =IF(LOWER(K60)="included", 1,0) -> 0 | W60: 0 | Z60: =SUM(N60:Y60) -> 0 | AA60: Mel
A61: Governance Principles for a New Generation of Artificial Intelligence: Develop Responsible Artificial Intelligence | B61: National New Generation Artificial Intelligence Governance Expert Committee | C61: https://www.newamerica.org/cybersecurity-initiative/digichina/blog/translation-chinese-expert-group-offers-governance-principles-responsible-ai/ | F61: national authority | G61: China | H61: 2019 | K61: Included | L61: press | M61: =IF(LOWER(K61)="included", 1,0) -> 1 | O61: 1 | S61: 1 | V61: 1 | W61: 1 | Z61: =SUM(N61:Y61) -> 4 | AA61: Maria | AB61: 0.092105285
A62: Recommandation on strategy creation process (AIM AT 2030) | B62: Austrian Council For Robotics And Artificial Intelligence | C62: https://www.acrai.at/wp-content/uploads/2019/04/190315_Ratsempfehlung_zum_Strategieprozess_AIM_AT_2030.pdf | G62: Austria | K62: Not included | L62: not accessible | M62: =IF(LOWER(K62)="included", 1,0) -> 0 | W62: 1 | Z62: =SUM(N62:Y62) -> 1 | AA62: Mel
A63: White Paper - Shaping the Future of Austria with Robotics and Artificial Intelligence | B63: Austrian Council For Robotics And Artificial Intelligence | C63: https://www.bmk.gv.at/dam/jcr:8acef058-7167-4335-880e-9fa341b723c8/aimat_ua.pdf | G63: Austria | K63: not included | L63: not english | M63: =IF(LOWER(K63)="included", 1,0) -> 0 | W63: 1 | Z63: =SUM(N63:Y63) -> 1 | AA63: Mel
A64: Principles for Responsible AI | B64: Women leading in AI | C64: https://womenleadinginai.org/wp-content/uploads/2019/02/WLiAI-Report-2019.pdf | D64: Ivana Bartoletti,Allison Gardner,Reema Patel,Emma Gibson,Liz Stocks,Samara Banno,Sanya Sheikh,Rebecca Geach,Holly Rafique | F64: civil society > other | G64: UK | H64: 2019 | K64: included | L64: issue-specific | M64: =IF(LOWER(K64)="included", 1,0) -> 1 | N64: 1 | V64: 1 | W64: 1 | X64: 1 | Z64: =SUM(N64:Y64) -> 4 | AA64: Simon | AB64: 0.093665009
A65: Axon committed to listening and learning so that we can fulfill our mission to protect life together | B65: Axon | C65: https://www.axon.com/news/technology/axon-committed-to-listening-and-learning | G65: USA | K65: Not included | L65: not AI ethics | M65: =IF(LOWER(K65)="included", 1,0) -> 0 | T65: 1 | Z65: =SUM(N65:Y65) -> 1 | AA65: Mel
A66: The Future of Digital Justice | B66: BCG, Bucerius Law School, LegalTech Deutschland | C66: https://web-assets.bcg.com/3a/4a/66275bf64d92b78b8fabeb3fe705/22-05-31-the-future-of-digital-justice-bls-bcg-web.pdf | G66: Germany | K66: Not included | L66: not AI ethics | M66: =IF(LOWER(K66)="included", 1,0) -> 0 | W66: 1 | Z66: =SUM(N66:Y66) -> 1 | AA66: Mel
A67: Principled Artificial Intelligence | B67: Berkman Klein Center (University of Harvard) | C67: https://ssrn.com/abstract=3518482 | G67: USA | K67: Not included | L67: meta-analysis | M67: =IF(LOWER(K67)="included", 1,0) -> 0 | W67: 1 | Z67: =SUM(N67:Y67) -> 1 | AA67: Mel
A68: Report with recommendations to the Commission on a framework of ethical aspects of artificial intelligence, robotics and related technologies | B68: European Parliament | C68: https://www.europarl.europa.eu/doceo/document/A-9-2020-0186_EN.pdf | F68: international organisation > EU institution | G68: EU | H68: 08/10/2020 | K68: Included | L68: SPI, digital | M68: =IF(LOWER(K68)="included", 1,0) -> 1 | W68: 1 | Z68: =SUM(N68:Y68) -> 1 | AA68: Maria | AB68: 0.095904735
A69: Responsible AI Policy Framework | B69: ITechLaw | C69: https://www.itechlaw.org/publication/responsible-ai-2021-update/ | F69: civil society > other | G69: USA | H69: 2021 | K69: Included | L69: SPI | M69: =IF(LOWER(K69)="included", 1,0) -> 1 | S69: 1 | V69: 1 | W69: 1 | Z69: =SUM(N69:Y69) -> 3 | AA69: Maria | AB69: 0.097122461
A70: Four Principles of Explainable Artificial Intelligence | B70: National Institute of Standards and Technology (NIST) (US) | C70: https://nvlpubs.nist.gov/nistpubs/ir/2021/NIST.IR.8312.pdf | F70: national authority | G70: USA | H70: 09/2021 | K70: included | L70: SPI issue-specific | M70: =IF(LOWER(K70)="included", 1,0) -> 1 | W70: 1 | Z70: =SUM(N70:Y70) -> 1 | AA70: Mel | AB70: 0.097428235
A71: Guidelines for Big Data Use - Leitlinien für Big Data Einsatz | B71: Bitkom | C71: https://www.bitkom.org/sites/default/files/file/import/150901-Bitkom-Positionspapier-Big-Data-Leitlinien.pdf | G71: Germany | K71: Not included | L71: not in english | M71: =IF(LOWER(K71)="included", 1,0) -> 0 | W71: 1 | Z71: =SUM(N71:Y71) -> 1 | AA71: Mel
A72: Recommendations for the responsible use of AI and automated decisions - Empfehlungen für den verantwortlichen Einsatz von KI und automatisierten Entscheidungen | B72: Bitkom | C72: https://www.bitkom.org/Bitkom/Publikationen/Empfehlungen-fuer-den-verantwortlichen-Einsatz-von-KI-und-automatisierten-Entscheidungen-Corporate-Digital-Responsibility-and-Decision-Making.html | G72: Germany | K72: Not included | L72: not in english | M72: =IF(LOWER(K72)="included", 1,0) -> 0 | V72: 1 | W72: 1 | Z72: =SUM(N72:Y72) -> 2 | AA72: Mel
A73: The right to privacy in the digital age | B73: United Nations (OHCHR) | C73: https://www.ohchr.org/en/calls-for-input/2021/right-privacy-digital-age-report-2021 | F73: international organisation > IGO | G73: international | H73: 15/09/2021 | K73: included | L73: digital issue-specific | M73: =IF(LOWER(K73)="included", 1,0) -> 1 | W73: 1 | Z73: =SUM(N73:Y73) -> 1 | AA73: Simon | AB73: 0.099665692
A74: Brazilian Strategy for Digital Transformation | B74: Brazil’s Ministry of Science, Technology, Innovations and Communications | C74: https://www.gov.br/mcti/pt-br/centrais-de-conteudo/comunicados-mcti/estrategia-digital-brasileira/digitalstrategy.pdf | G74: Brazil | K74: not included | L74: not AI ethics | M74: =IF(LOWER(K74)="included", 1,0) -> 0 | W74: 1 | Z74: =SUM(N74:Y74) -> 1 | AA74: Mel
A75: Statement on Accessibility, Usability, and Digital Inclusiveness | B75: Association for Computing Machinery - Future of Computing Machinery | C75: https://www.acm.org/binaries/content/assets/public-policy/2017_usacm_statement_accessibility.pdf | F75: civil society > other | G75: USA | H75: 26/09/2017 | K75: included | L75: digital | M75: =IF(LOWER(K75)="included", 1,0) -> 1 | U75: 1 | Z75: =SUM(N75:Y75) -> 1 | AA75: Mel | AB75: 0.10562765
A76: Conclusions from the Conference “Governing the Game Changer" | B76: Council of Europe and Finnish Presidency of the Committee of Ministers | C76: https://rm.coe.int/conclusions-helsinki-conference-26-27-02-2019/168093bfca | F76: international organisation > IGO | G76: EU | H76: 27/02/2019 | K76: included | M76: =IF(LOWER(K76)="included", 1,0) -> 1 | W76: 1 | Z76: =SUM(N76:Y76) -> 1 | AA76: Mel | AB76: 0.10970189
A77: AI Quality Seal - KI Gütesiegel | B77: Bundesverband KI | C77: https://ki-verband.de/ki-guetesiegel-ai-made-in-germany | G77: Germany | K77: Not included | L77: not in english | M77: =IF(LOWER(K77)="included", 1,0) -> 0 | V77: 1 | W77: 1 | Z77: =SUM(N77:Y77) -> 2 | AA77: Mel
A78: Report on Artificial Intellilgence in a digital age | B78: European Parliament | C78: https://www.europarl.europa.eu/doceo/document/TA-9-2022-0140_EN.pdf | F78: international organisation > EU institution | G78: EU | H78: 03/05/2022 | K78: Included | M78: =IF(LOWER(K78)="included", 1,0) -> 1 | W78: 1 | Z78: =SUM(N78:Y78) -> 1 | AA78: Maria | AB78: 0.11366945
A79: Hambach Declaration on Artificial Intelligence – Seven data protection obligations - Hambacher Erklärung zur Künstlichen Intelligenz – Sieben datenschutzrechtliche Anforderungen | B79: Conference of the Independent Federal and State Data Protection Supervisory Authorities - Datenschutzkonferenz (Germany) | C79: https://www.datenschutz.bremen.de/sixcms/media.php/13/Hambacher_Erklaerung_englisch.pdf | F79: civil society > state-dependant | G79: Germany | H79: 03/04/2019 | K79: included | M79: =IF(LOWER(K79)="included", 1,0) -> 1 | W79: 1 | Z79: =SUM(N79:Y79) -> 1 | AA79: Mel | AB79: 0.11529055
A80: National Artificial Intelligence Strategy of the Czech Republic | B80: Ministry of Industry and Trade of Czech Republic | C80: https://www.mpo.cz/assets/en/guidepost/for-the-media/press-releases/2019/5/NAIS_eng_web.pdf. | F80: national authority | G80: Czech Republic | H80: 2019 | K80: included | L80: SPI (strategy) | M80: =IF(LOWER(K80)="included", 1,0) -> 1 | W80: 1 | Z80: =SUM(N80:Y80) -> 1 | AA80: Tiphaine | AB80: 0.1160886
A81: Exploratory study on the use of algoritms by government organisations | B81: CBS (Statistics Netherlands) | C81: https://www.cbs.nl/-/media/_pdf/2018/48/verkennend%20onderzoek%20naar%20het%20gebruik%20van%20algoritmen%20binnen%20overheidsorganisaties.pdf | G81: Netherlands | K81: not included | L81: not in english | M81: =IF(LOWER(K81)="included", 1,0) -> 0 | W81: 1 | Z81: =SUM(N81:Y81) -> 1 | AA81: Mel
A82: Study on the impact of Artificial Intellgience on the infrigement and enforcement of copyrights and designs | B82: European Union Intellectual Property Office (EUIPO) | C82: https://euipo.europa.eu/tunnel-web/secure/webdav/guest/document_library/observatory/documents/reports/2022_Impact_AI_on_the_Infringement_and_Enforcement_CR_Designs/2022_Impact_AI_on_the_Infringement_and_Enforcement_CR_Designs_FullR_en.pdf | F82: international organisation > EU institution | G82: EU | H82: 03/2022 | K82: Included | L82: SPI, field-specific | M82: =IF(LOWER(K82)="included", 1,0) -> 1 | W82: 1 | Z82: =SUM(N82:Y82) -> 1 | AA82: Maria | AB82: 0.11685856
A83: Digital Decisions Tool | B83: Center for Democracy & technology (CDT) | C83: https://www.cdt.info/ddtool/ | D83: 7 | G83: USA | K83: Not included | L83: tool | M83: =IF(LOWER(K83)="included", 1,0) -> 0 | W83: 1 | Z83: =SUM(N83:Y83) -> 1 | AA83: Mel
A84: For technologists | B84: Center for Humane Technology | C84: https://www.humanetech.com/technologists#principles | K84: Not included | L84: not AI ethics | M84: =IF(LOWER(K84)="included", 1,0) -> 0 | T84: 1 | Z84: =SUM(N84:Y84) -> 1 | AA84: Mel
A85: Research Collection: Research Supporting Responsible AI | B85: Microsoft | C85: https://www.microsoft.com/en-us/research/blog/research-collection-research-supporting-responsible-ai/ | F85: private sector | G85: USA | H85: 13/04/2020 | K85: included | M85: =IF(LOWER(K85)="included", 1,0) -> 1 | Z85: =SUM(N85:Y85) -> 0 | AA85: Mel | AB85: 0.11726318
A86: COVID-19 repository and public attitudes retrospective | B86: Centre for Data Ethics and Innovation | C86: https://www.gov.uk/government/publications/covid-19-repository-and-public-attitudes-retrospective | G86: UK | K86: not included | L86: not AI ethics | M86: =IF(LOWER(K86)="included", 1,0) -> 0 | W86: 1 | Z86: =SUM(N86:Y86) -> 1 | AA86: Mel
A87: AI Principles: Recommendations on the Ethical Use of Artificial Intelligence by the Department of Defense | B87: Defense Innovation Board | C87: https://media.defense.gov/2019/Oct/31/2002204458/-1/-1/0/DIB_AI_PRINCIPLES_PRIMARY_DOCUMENT.PDF | F87: civil society > state-dependant | G87: USA | H87: 31/10/2019 | K87: included | L87: field-specific | M87: =IF(LOWER(K87)="included", 1,0) -> 1 | S87: 1 | Z87: =SUM(N87:Y87) -> 1 | AA87: Mel | AB87: 0.12132199
A88: Artificial Intelligence and Data Protection: How the GDPR Regulates AI | B88: Centre for Information Policy Leadership (CIPL) | C88: https://www.huntonprivacyblog.com/wp-content/uploads/sites/28/2020/03/cipl-hunton_andrews_kurth_legal_note_-_how_gdpr_regulates_ai__12_march_2020_-1.pdf | G88: USA | K88: not included | L88: not AI ethics | M88: =IF(LOWER(K88)="included", 1,0) -> 0 | W88: 1 | Z88: =SUM(N88:Y88) -> 1 | AA88: Mel
A89: The Brussels Effect and Artificial Intelligence: How EU regulation will impact the global AI market | B89: Centre for the Governance of AI (GovAI) | C89: https://uploads-ssl.webflow.com/614b70a71b9f71c9c240c7a7/630534b77182a3513398500f_Brussels_Effect_GovAI.pdf | G89: UK | K89: not included | L89: not AI ethics | M89: =IF(LOWER(K89)="included", 1,0) -> 0 | W89: 1 | Z89: =SUM(N89:Y89) -> 1 | AA89: Mel
A90: Special report: Artificial Intelligence - Your questions answered | B90: Australian Strategic Policy Institute (ASPI), University of Adelaide, Australian Institute for Machine Learning | C90: https://ad-aspi.s3.ap-southeast-2.amazonaws.com/2023-01/SR183%20AI%20Your%20questions%20answered.pdf?VersionId=RDGO41fuPaLXTscqQt0SKCfOkLU0G7.6 | F90: civil society > other, academia | G90: Australia | H90: 04/2022 | K90: included | L90: SPI | M90: =IF(LOWER(K90)="included", 1,0) -> 1 | W90: 1 | Z90: =SUM(N90:Y90) -> 1 | AA90: Mel | AB90: 0.13013485
A91: Mapping de l’écosystème de l’IA dans les pays du Maghreb | B91: United Nations Educational Scientific and Cultural Organization (UNESCO) | C91: https://fr.unesco.org/sites/default/files/20210526mappingecosystemeiadsmaghreb.pdf | F91: international organisation > IGO | G91: international | H91: 2020 | K91: included | L91: SPI | M91: =IF(LOWER(K91)="included", 1,0) -> 1 | W91: 1 | Z91: =SUM(N91:Y91) -> 1 | AA91: Simon | AB91: 0.1306392
A92: Artificial Intelligence as a Service: Legal Responsibilities, Liabilities, and Policy Challenges | B92: University of Cambridge | C92: https://papers.ssrn.com/sol3/papers.cfm?abstract_id=3824736 | F92: academia | G92: UK | H92: 29/04/2021 | K92: included | L92: SPI | M92: =IF(LOWER(K92)="included", 1,0) -> 1 | W92: 1 | Z92: =SUM(N92:Y92) -> 1 | AA92: Simon | AB92: 0.13147732
A93: Facial recognition technology: fundamental rights considerations in the context of law enforcement | B93: Fundamental Rights Agency (FRA) | C93: https://fra.europa.eu/sites/default/files/fra_uploads/fra-2019-facial-recognition-technology-focus-paper-1_en.pdf | F93: international organisation > other | G93: EU | H93: 21/11/2019 | K93: included | L93: SPI (study), field-specific | M93: =IF(LOWER(K93)="included", 1,0) -> 1 | W93: 1 | Z93: =SUM(N93:Y93) -> 1 | AA93: Tiphaine | AB93: 0.13232126
A94: Charter of Digital Networking | B94: Charta of digital networking | C94: https://charta-digitale-vernetzung.de/app/uploads/2016/11/Charter-of-Digital-Networking.pdf | G94: Germany | K94: Not included | L94: not AI ethics | M94: =IF(LOWER(K94)="included", 1,0) -> 0 | V94: 1 | Z94: =SUM(N94:Y94) -> 1 | AA94: Mel
A95: Joint Pledge on Artificial Intelligence Industry Self-Discipline | B95: Chinese AI Industry Alliance (AIIA) | C95: https://www.newamerica.org/cybersecurity-initiative/digichina/blog/translation-chinese-ai-alliance-drafts-self-discipline-joint-pledge/ | G95: China | K95: Not included | L95: not in english | M95: =IF(LOWER(K95)="included", 1,0) -> 0 | O95: 1 | S95: 1 | T95: 1 | V95: 1 | W95: 1 | Z95: =SUM(N95:Y95) -> 5 | AA95: Mel
A96: AI Now 2019 Report | B96: AI Now Institute | C96: https://ainowinstitute.org/wp-content/uploads/2023/04/AI_Now_2019_Report.pdf | F96: civil society > NGO | G96: USA | H96: 12/2019 | K96: included | L96: SPI | M96: =IF(LOWER(K96)="included", 1,0) -> 1 | Q96: 1 | T96: 1 | Z96: =SUM(N96:Y96) -> 2 | AA96: Tiphaine | AB96: 0.13412471
A97: Pan-Canadian Artificial Intelligence Strategy | B97: CIFAR | C97: https://www.cifar.ca/ai/pan-canadian-artificial-intelligence-strategy | G97: Canada | K97: not included | L97: not accessible | M97: =IF(LOWER(K97)="included", 1,0) -> 0 | W97: 1 | Z97: =SUM(N97:Y97) -> 1 | AA97: Mel
A98: ADP: Ethics in Artificial Intelligence | B98: Always Designing for People | C98: https://www.adp.com/-/media/adp/redesign2018/pdf/data-privacy/ai-ethics-statement.pdf?rev=f155df771fea4850b310f17ca407f3f1&hash=73364D9FB41931A7C1887B976538BE5C | F98: private sector | G98: USA | H98: 07/03/2022 | K98: included | M98: =IF(LOWER(K98)="included", 1,0) -> 1 | S98: 1 | Z98: =SUM(N98:Y98) -> 1 | AA98: Tiphaine | AB98: 0.13656131
A99: Recommendations for an AI Strategy in Switzerland | B99: Swiss Academy of Technical Sciences (SATW) | C99: https://www.satw.ch/fileadmin/user_upload/documents/02_Themen/08_Kuenstliche-Intelligenz/SATW-Swiss_AI_Strategy.pdf | F99: civil society > other | G99: Switzerland | H99: 2019 | K99: included | L99: SPI digital | M99: =IF(LOWER(K99)="included", 1,0) -> 1 | W99: 1 | Z99: =SUM(N99:Y99) -> 1 | AA99: Simon | AB99: 0.13933301
A100: Declaration of Cities Coalition for Digital Right | B100: Cities Coalition for Digital Rights | C100: https://citiesfordigitalrights.org/assets/Declaration_Cities_for_Digital_Rights.pdf | G100: international | K100: not included | L100: not AI ethics | M100: =IF(LOWER(K100)="included", 1,0) -> 0 | W100: 1 | Z100: =SUM(N100:Y100) -> 1 | AA100: Mel
...

Sheet Tableau croisé dynamique 3

Sheet Matthieu
A1: Title | B1: Institution | C1: URL | G1: Country | H1: Date | I1: Sector | N1: Maria | O1: Aina | P1: Simon
A2: AI Index 2022 | B2: University of Stanford, SRI International, MIT, OpenAI, McKinsey Global Institute, Partnership on AI, Harvard University | C2: https://aiindex.stanford.edu/wp-content/uploads/2022/03/2022-AI-Index-Report_Master.pdf | G2: USA | H2: 2022 | I2: Academia | M2: =IF(ISNUMBER(SEARCH(",",I2)),"multistakeholders",lower(I2)) -> academia | N2: =IF(LOWER(I2)=LOWER(Maria!L2),1,0) -> 1 | O2: =IF(LOWER(I2)=LOWER(Aina!N2),1,0) -> 0 | P2: =IF(LOWER(I2)=LOWER(Kappa!Y4),1,0) -> 0 | R2: Matthieu | T2: COUNTA de Sector | U2: SUM de Maria | V2: SUM de Aina | W2: SUM de Simon | X2: Maria | Y2: Aina | Z2: Simon
A3: 2030 Digital Compass: the European way for the Digital Decade | B3: European Commission | C3: https://eur-lex.europa.eu/legal-content/en/TXT/?uri=CELEX%3A52021DC0118 | G3: international | H3: 09/03/2021 | I3: International organisation | M3: =IF(ISNUMBER(SEARCH(",",I3)),"multistakeholders",lower(I3)) -> international organisation | N3: =IF(LOWER(I3)=LOWER(Maria!L3),1,0) -> 1 | O3: =IF(LOWER(I3)=LOWER(Aina!N3),1,0) -> 1 | P3: =IF(LOWER(I3)=LOWER(Kappa!Y5),1,0) -> 1 | R3: =T3/$T$9 -> 0.18181818 | S3: academia | T3: 8 | U3: 4 | V3: 4 | W3: 4 | X3: =U3/$T3 -> 0.5 | Y3: =V3/$T3 -> 0.5 | Z3: =W3/$T3 -> 0.5
A4: Global competition and convergence of AI Law | B4: Vrije Universiteit Brussel | C4: https://osf.io/preprints/socarxiv/j36ke/ | G4: Belgium | H4: 2021 | I4: Academia | M4: =IF(ISNUMBER(SEARCH(",",I4)),"multistakeholders",lower(I4)) -> academia | N4: =IF(LOWER(I4)=LOWER(Maria!L4),1,0) -> 1 | O4: =IF(LOWER(I4)=LOWER(Aina!N4),1,0) -> 1 | P4: =IF(LOWER(I4)=LOWER(Kappa!Y6),1,0) -> 1 | R4: =T4/$T$9 -> 0.15909091 | S4: civil society | T4: 7 | U4: 5 | V4: 7 | W4: 6 | X4: =U4/$T4 -> 0.71428571 | Y4: =V4/$T4 -> 1 | Z4: =W4/$T4 -> 0.85714286
A5: Technology rules? The advent of new technologies in the justice system | B5: House of Lords, Justice and Home affairs Committee (United Kingdom) | C5: https://publications.parliament.uk/pa/ld5802/ldselect/ldjusthom/180/180.pdf | G5: UK | H5: 30/03/2022 | I5: National authority | M5: =IF(ISNUMBER(SEARCH(",",I5)),"multistakeholders",lower(I5)) -> national authority | N5: =IF(LOWER(I5)=LOWER(Maria!L5),1,0) -> 1 | O5: =IF(LOWER(I5)=LOWER(Aina!N5),1,0) -> 1 | P5: =IF(LOWER(I5)=LOWER(Kappa!Y7),1,0) -> 1 | R5: =T5/$T$9 -> 0.22727273 | S5: international organisation | T5: 10 | U5: 8 | V5: 9 | W5: 10 | X5: =U5/$T5 -> 0.8 | Y5: =V5/$T5 -> 0.9 | Z5: =W5/$T5 -> 1
A6: Algorithmic discrimination in Europe: Challenges and opportunities for gender equality and non-discrimination law | B6: European Commission (European network of legal experts in gender equality and non-discrimination) | C6: https://op.europa.eu/en/publication-detail/-/publication/082f1dbc-821d-11eb-9ac9-01aa75ed71a1 | G6: EU | H6: 10/2020 | I6: International organisation | M6: =IF(ISNUMBER(SEARCH(",",I6)),"multistakeholders",lower(I6)) -> international organisation | N6: =IF(LOWER(I6)=LOWER(Maria!L6),1,0) -> 1 | O6: =IF(LOWER(I6)=LOWER(Aina!N6),1,0) -> 1 | P6: =IF(LOWER(I6)=LOWER(Kappa!Y8),1,0) -> 1 | R6: =T6/$T$9 -> 0.13636364 | S6: multistakeholders | T6: 6 | U6: 0 | V6: 0 | W6: 0 | X6: =U6/$T6 -> 0 | Y6: =V6/$T6 -> 0 | Z6: =W6/$T6 -> 0
A7: AI Index 2019 | B7: University of Stanford, SRI International, MIT, OpenAI, McKinsey Global Institute, Partnership on AI, Harvard University | C7: https://hai.stanford.edu/sites/default/files/ai_index_2019_report.pdf | G7: USA | H7: 2019 | I7: Academia | M7: =IF(ISNUMBER(SEARCH(",",I7)),"multistakeholders",lower(I7)) -> academia | N7: =IF(LOWER(I7)=LOWER(Maria!L7),1,0) -> 0 | O7: =IF(LOWER(I7)=LOWER(Aina!N7),1,0) -> 0 | P7: =IF(LOWER(I7)=LOWER(Kappa!Y9),1,0) -> 0 | R7: =T7/$T$9 -> 0.18181818 | S7: national authority | T7: 8 | U7: 4 | V7: 6 | W7: 8 | X7: =U7/$T7 -> 0.5 | Y7: =V7/$T7 -> 0.75 | Z7: =W7/$T7 -> 1
A8: Artificial intelligence and the control of COVID-19 | B8: Council of Europe | C8: https://www.coe.int/en/web/artificial-intelligence/ai-and-control-of-covid-19-coronavirus | G8: EU | H8: 2020 | I8: International organisation | M8: =IF(ISNUMBER(SEARCH(",",I8)),"multistakeholders",lower(I8)) -> international organisation | N8: =IF(LOWER(I8)=LOWER(Maria!L8),1,0) -> 1 | O8: =IF(LOWER(I8)=LOWER(Aina!N8),1,0) -> 1 | P8: =IF(LOWER(I8)=LOWER(Kappa!Y10),1,0) -> 1 | R8: =T8/$T$9 -> 0.11363636 | S8: private sector | T8: 5 | U8: 2 | V8: 2 | W8: 2 | X8: =U8/$T8 -> 0.4 | Y8: =V8/$T8 -> 0.4 | Z8: =W8/$T8 -> 0.4
A9: Unified Ethical Frame for Big Data Analysis. IAF Big Data Ethics Initiative, Part A | B9: The Information Accountability Foundation | C9: https://bigdata.fpf.org/wp-content/uploads/2015/11/IAF-Unified-Ethical-Frame-for-Big-Data-Analysis.pdf | G9: UK | H9: 03/2015 | I9: Private sector, Civil society | K9: (Funded by the The Information Accountability Foundation, which is a non profit think tank financed by american compagnies) | M9: =IF(ISNUMBER(SEARCH(",",I9)),"multistakeholders",lower(I9)) -> multistakeholders | N9: =IF(LOWER(I9)=LOWER(Maria!L9),1,0) -> 0 | O9: =IF(LOWER(I9)=LOWER(Aina!N9),1,0) -> 0 | P9: =IF(LOWER(I9)=LOWER(Kappa!Y11),1,0) -> 0 | S9: Total général | T9: 44 | U9: 23 | V9: 28 | W9: 30 | X9: =U9/$T9 -> 0.52272727 | Y9: =V9/$T9 -> 0.63636364 | Z9: =W9/$T9 -> 0.68181818
A10: Artificial Intelligence | B10: Samsung Research | C10: https://research.samsung.com/artificial-intelligence | G10: South Korea | I10: Private sector | M10: =IF(ISNUMBER(SEARCH(",",I10)),"multistakeholders",lower(I10)) -> private sector | N10: =IF(LOWER(I10)=LOWER(Maria!L10),1,0) -> 1 | O10: =IF(LOWER(I10)=LOWER(Aina!N10),1,0) -> 1 | P10: =IF(LOWER(I10)=LOWER(Kappa!Y12),1,0) -> 1
A11: The EURON Roboethics Roadmap | B11: The European Robotics Research Network (EURON) | C11: http://www.roboethics.org/index_file/Roboethics%20Roadmap%20Rel.1.2.pdf | G11: EU | H11: 01/2007 | I11: Academia, International organisation | K11: (Fondé/interlocuteur de la commision européenne) | M11: =IF(ISNUMBER(SEARCH(",",I11)),"multistakeholders",lower(I11)) -> multistakeholders | N11: =IF(LOWER(I11)=LOWER(Maria!L11),1,0) -> 0 | O11: =IF(LOWER(I11)=LOWER(Aina!N11),1,0) -> 0 | P11: =IF(LOWER(I11)=LOWER(Kappa!Y13),1,0) -> 0
A12: Understanding Artificial Intelligence and Safety - A guide for the responsible design and implementation of AI systems in the public sector | B12: The Alan Turing Institute | C12: https://www.turing.ac.uk/sites/default/files/2019-06/understanding_artificial_intelligence_ethics_and_safety.pdf | G12: UK | H12: 2019 | I12: Academia | K12: (Only universities, funded by grants/universities) | M12: =IF(ISNUMBER(SEARCH(",",I12)),"multistakeholders",lower(I12)) -> academia | N12: =IF(LOWER(I12)=LOWER(Maria!L12),1,0) -> 0 | O12: =IF(LOWER(I12)=LOWER(Aina!N12),1,0) -> 1 | P12: =IF(LOWER(I12)=LOWER(Kappa!Y14),1,0) -> 0
A13: Digital Ethics: A guide for professionals of the Digital Age | B13: CIGREF/Syntec Numérique | C13: https://www.cigref.fr/wp/wp-content/uploads/2019/02/Cigref-Syntec-Digital-Ethics-Guide-for-Professionals-of-Digital-Age-2018-October-EN.pdf | G13: France | H13: 10/2018 | I13: Private sector | M13: =IF(ISNUMBER(SEARCH(",",I13)),"multistakeholders",lower(I13)) -> private sector | N13: =IF(LOWER(I13)=LOWER(Maria!L13),1,0) -> 0 | O13: =IF(LOWER(I13)=LOWER(Aina!N13),1,0) -> 0 | P13: =IF(LOWER(I13)=LOWER(Kappa!Y15),1,0) -> 0
A14: Human Rights, Democracy, and the Rule of Law Assurance Framework for AI Systems: A proposal prepared for the Council of Europe’s Ad hoc Committee on Artificial Intelligence | B14: The Alan Turing Institute | C14: https://rm.coe.int/huderaf-coe-final-1-2752-6741-5300-v-1/1680a3f688 | G14: UK | H14: 2021 | I14: Academia | M14: =IF(ISNUMBER(SEARCH(",",I14)),"multistakeholders",lower(I14)) -> academia | N14: =IF(LOWER(I14)=LOWER(Maria!L14),1,0) -> 0 | O14: =IF(LOWER(I14)=LOWER(Aina!N14),1,0) -> 0 | P14: =IF(LOWER(I14)=LOWER(Kappa!Y16),1,0) -> 0
A15: Study on AI Governance by Human Rights-Centred Design, Deliberation and Oversight | B15: University of Birmingham | C15: https://papers.ssrn.com/sol3/papers.cfm?abstract_id=3435011 | G15: UK | H15: 09/08/2019 | I15: Academia | M15: =IF(ISNUMBER(SEARCH(",",I15)),"multistakeholders",lower(I15)) -> academia | N15: =IF(LOWER(I15)=LOWER(Maria!L15),1,0) -> 1 | O15: =IF(LOWER(I15)=LOWER(Aina!N15),1,0) -> 1 | P15: =IF(LOWER(I15)=LOWER(Kappa!Y17),1,0) -> 1
A16: European ethical Charter on the use of Artificial Intelligence in judicial systems and their environment | B16: Council of Europe: European Commission for the efficiency of Justice (CEPEJ) | C16: https://rm.coe.int/ethical-charter-en-for-publication-4-december-2018/16808f699c | G16: EU | H16: 04/12/2018 | I16: International organisation | M16: =IF(ISNUMBER(SEARCH(",",I16)),"multistakeholders",lower(I16)) -> international organisation | N16: =IF(LOWER(I16)=LOWER(Maria!L16),1,0) -> 1 | O16: =IF(LOWER(I16)=LOWER(Aina!N16),1,0) -> 1 | P16: =IF(LOWER(I16)=LOWER(Kappa!Y18),1,0) -> 1
A17: The Road to a Human-Centred Digital Society | B17: Centre on AI Technology for Humanking (AiTH) at NUS Business School | C17: https://drive.google.com/uc?export=download&id=1aRyqczni56ONA9PVExt2DrrJ1ATGKSu0 | D17: David De Cremer, Devesh Narayanan, Andreas Deppeler, Mahak Nagpal, Jack McGuire, Jess Zhang | E17: National University of Singapore | G17: Singapore | H17: 12/2021 | I17: Academia | M17: =IF(ISNUMBER(SEARCH(",",I17)),"multistakeholders",lower(I17)) -> academia | N17: =IF(LOWER(I17)=LOWER(Maria!L17),1,0) -> 1 | O17: =IF(LOWER(I17)=LOWER(Aina!N17),1,0) -> 1 | P17: =IF(LOWER(I17)=LOWER(Kappa!Y19),1,0) -> 1
A18: AI Roadmap | B18: AI Council (United Kingdom) | C18: https://assets.publishing.service.gov.uk/media/5ff3bc6e8fa8f53b76ccee23/AI_Council_AI_Roadmap.pdf | G18: UK | H18: 01/2021 | I18: Civil society | M18: =IF(ISNUMBER(SEARCH(",",I18)),"multistakeholders",lower(I18)) -> civil society | N18: =IF(LOWER(I18)=LOWER(Maria!L18),1,0) -> 0 | O18: =IF(LOWER(I18)=LOWER(Aina!N18),1,0) -> 1 | P18: =IF(LOWER(I18)=LOWER(Kappa!Y20),1,0) -> 0
A19: Growing the artificial intelligence industry in the UK | B19: Department for Digital, Culture, Media & Sport and Department for Business, Energy & Industrial Strategy (United Kingdom) | C19: https://www.gov.uk/government/publications/growing-the-artificial-intelligence-industry-in-the-uk | G19: UK | H19: 15/10/2017 | I19: National authority | M19: =IF(ISNUMBER(SEARCH(",",I19)),"multistakeholders",lower(I19)) -> national authority | N19: =IF(LOWER(I19)=LOWER(Maria!L19),1,0) -> 0 | O19: =IF(LOWER(I19)=LOWER(Aina!N19),1,0) -> 0 | P19: =IF(LOWER(I19)=LOWER(Kappa!Y21),1,0) -> 1
A20: AI Now 2017 Report | B20: AI Now Institute | C20: https://ainowinstitute.org/wp-content/uploads/2023/04/AI_Now_2017_Report.pdf | G20: USA | H20: 2017 | I20: Academia, Civil society | K20: (?) | M20: =IF(ISNUMBER(SEARCH(",",I20)),"multistakeholders",lower(I20)) -> multistakeholders | N20: =IF(LOWER(I20)=LOWER(Maria!L20),1,0) -> 0 | O20: =IF(LOWER(I20)=LOWER(Aina!N20),1,0) -> 0 | P20: =IF(LOWER(I20)=LOWER(Kappa!Y22),1,0) -> 0
A21: Algorithms in Decision Making | B21: Parliament Science and Technology Committee (United Kingdom) | C21: https://publications.parliament.uk/pa/cm201719/cmselect/cmsctech/351/351.pdf | G21: UK | H21: 23/05/2018 | I21: National authority | M21: =IF(ISNUMBER(SEARCH(",",I21)),"multistakeholders",lower(I21)) -> national authority | N21: =IF(LOWER(I21)=LOWER(Maria!L21),1,0) -> 0 | O21: =IF(LOWER(I21)=LOWER(Aina!N21),1,0) -> 1 | P21: =IF(LOWER(I21)=LOWER(Kappa!Y23),1,0) -> 1
A22: Thematic Reviews on 'Social Aspects of Digitalisation' (SPC) and 'Digitalisation and Robotisation of Work' (EMCO) - Endorsement of the joint key messages, 14411/18 | B22: Council of the European Union | C22: http://data.consilium.europa.eu/doc/document/ST-14411-2018-INIT/en/pdf | G22: EU | H22: 19/11/2018 | I22: International organisation | M22: =IF(ISNUMBER(SEARCH(",",I22)),"multistakeholders",lower(I22)) -> international organisation | N22: =IF(LOWER(I22)=LOWER(Maria!L22),1,0) -> 1 | O22: =IF(LOWER(I22)=LOWER(Aina!N22),1,0) -> 1 | P22: =IF(LOWER(I22)=LOWER(Kappa!Y24),1,0) -> 1
A23: Standards for AI Governance: International Standards to Enable Global Coordination in AI Research & Development | B23: Future of Humanity Institute, University of Oxford | C23: https://www.fhi.ox.ac.uk/wp-content/uploads/Standards_-FHI-Technical-Report.pdf | G23: international | H23: 04/2019 | I23: Academia | M23: =IF(ISNUMBER(SEARCH(",",I23)),"multistakeholders",lower(I23)) -> academia | N23: =IF(LOWER(I23)=LOWER(Maria!L23),1,0) -> 0 | O23: =IF(LOWER(I23)=LOWER(Aina!N23),1,0) -> 0 | P23: =IF(LOWER(I23)=LOWER(Kappa!Y25),1,0) -> 1
A24: Preparing the future of AI | B24: National Science and Technology Council (US) | C24: https://obamawhitehouse.archives.gov/sites/default/files/whitehouse_files/microsites/ostp/NSTC/preparing_for_the_future_of_ai.pdf | G24: USA | H24: 10/2016 | I24: National authority | M24: =IF(ISNUMBER(SEARCH(",",I24)),"multistakeholders",lower(I24)) -> national authority | N24: =IF(LOWER(I24)=LOWER(Maria!L24),1,0) -> 1 | O24: =IF(LOWER(I24)=LOWER(Aina!N24),1,0) -> 1 | P24: =IF(LOWER(I24)=LOWER(Kappa!Y26),1,0) -> 1
A25: AI Now Report 2016. The Social and Economic Implications of Artificial Intelligence Technologies in the Near-Term | B25: AI Now Institute | C25: https://assets.ctfassets.net/8wprhhvnpfc0/3JOy5k4f1YSCQOi8MCCmA2/97010d04fbc7892662ce8b2469dc1601/AI_Now_2016_Report.pdf | G25: USA | H25: 22/09/2016 | I25: Academia, Civil society | M25: =IF(ISNUMBER(SEARCH(",",I25)),"multistakeholders",lower(I25)) -> multistakeholders | N25: =IF(LOWER(I25)=LOWER(Maria!L25),1,0) -> 0 | O25: =IF(LOWER(I25)=LOWER(Aina!N25),1,0) -> 0 | P25: =IF(LOWER(I25)=LOWER(Kappa!Y27),1,0) -> 0
A26: G20 AI Principles | B26: Ministry of Internal Affairs and Communications | C26: https://www.mofa.go.jp/policy/economy/g20_summit/osaka19/pdf/documents/en/annex_08.pdf | G26: Japan | H26: 2019 | I26: National authority | M26: =IF(ISNUMBER(SEARCH(",",I26)),"multistakeholders",lower(I26)) -> national authority | N26: =IF(LOWER(I26)=LOWER(Maria!L26),1,0) -> 0 | O26: =IF(LOWER(I26)=LOWER(Aina!N26),1,0) -> 0 | P26: =IF(LOWER(I26)=LOWER(Kappa!Y28),1,0) -> 1
A27: Principles for the Governance of AI | B27: The Future Society Science Law and Society (SLS) Initiative | C27: https://thefuturesociety.org/principles-law-and-society-initiative/ | G27: USA | H27: 15/07/2017 | I27: Civil society | M27: =IF(ISNUMBER(SEARCH(",",I27)),"multistakeholders",lower(I27)) -> civil society | N27: =IF(LOWER(I27)=LOWER(Maria!L27),1,0) -> 1 | O27: =IF(LOWER(I27)=LOWER(Aina!N27),1,0) -> 1 | P27: =IF(LOWER(I27)=LOWER(Kappa!Y29),1,0) -> 1
A28: 4 Steps to developing Responsible AI | B28: World Economic Forum (WEF) | C28: https://www.weforum.org/agenda/2019/06/4-steps-to-developing-responsible-ai/ | G28: international | H28: 20/06/2019 | I28: Private sector | M28: =IF(ISNUMBER(SEARCH(",",I28)),"multistakeholders",lower(I28)) -> private sector | N28: =IF(LOWER(I28)=LOWER(Maria!L28),1,0) -> 0 | O28: =IF(LOWER(I28)=LOWER(Aina!N28),1,0) -> 0 | P28: =IF(LOWER(I28)=LOWER(Kappa!Y30),1,0) -> 0
A29: Opinion on AI - The consequences of artificial intelligence on the (digital) single market, production, consumption, employment and society’ | B29: European Economic and Social Committee (EESC) | C29: https://eur-lex.europa.eu/legal-content/EN/TXT/PDF/?uri=CELEX:52016IE5369&from=EN | G29: international | H29: 31/08/2017 | I29: International organisation | M29: =IF(ISNUMBER(SEARCH(",",I29)),"multistakeholders",lower(I29)) -> international organisation | N29: =IF(LOWER(I29)=LOWER(Maria!L29),1,0) -> 0 | O29: =IF(LOWER(I29)=LOWER(Aina!N29),1,0) -> 1 | P29: =IF(LOWER(I29)=LOWER(Kappa!Y31),1,0) -> 1
A30: Human Rights Impact Assessments for AI: Analysis and Recommendations | B30: AccessNow | C30: https://www.accessnow.org/cms/assets/uploads/2022/11/Access-Now-Version-Human-Rights-Implications-of-Algorithmic-Impact-Assessments_-Priority-Recommendations-to-Guide-Effective-Development-and-Use.pdf | G30: USA | H30: 10/2022 | I30: Academia, Civil society | M30: =IF(ISNUMBER(SEARCH(",",I30)),"multistakeholders",lower(I30)) -> multistakeholders | N30: =IF(LOWER(I30)=LOWER(Maria!L30),1,0) -> 0 | O30: =IF(LOWER(I30)=LOWER(Aina!N30),1,0) -> 0 | P30: =IF(LOWER(I30)=LOWER(Kappa!Y32),1,0) -> 0
A31: Report on Artificial intelligence in health care: medical, legal and ethical challenges ahead | B31: Council of Europe (Parliamentary Assembly) | C31: https://pace.coe.int/files/28737/pdf | G31: EU | H31: 01/10/2020 | I31: International organisation | M31: =IF(ISNUMBER(SEARCH(",",I31)),"multistakeholders",lower(I31)) -> international organisation | N31: =IF(LOWER(I31)=LOWER(Maria!L31),1,0) -> 1 | O31: =IF(LOWER(I31)=LOWER(Aina!N31),1,0) -> 1 | P31: =IF(LOWER(I31)=LOWER(Kappa!Y33),1,0) -> 1
A32: Recomendations on the inclusion subSaharan Africa in Global AI Ethics | B32: Research ICT Africa | C32: https://researchictafrica.net/ranitp2019-2-ai-ethics/ | G32: South Africa | H32: 02/2019 | I32: Civil society, Academia | M32: =IF(ISNUMBER(SEARCH(",",I32)),"multistakeholders",lower(I32)) -> multistakeholders | N32: =IF(LOWER(I32)=LOWER(Maria!L32),1,0) -> 0 | O32: =IF(LOWER(I32)=LOWER(Aina!N32),1,0) -> 0 | P32: =IF(LOWER(I32)=LOWER(Kappa!Y34),1,0) -> 0
A33: Our principles | B33: Google | C33: https://blog.google/technology/ai/ai-principles/ | D33: . | E33: . | G33: USA | H33: 2018 | I33: Private sector | M33: =IF(ISNUMBER(SEARCH(",",I33)),"multistakeholders",lower(I33)) -> private sector | N33: =IF(LOWER(I33)=LOWER(Maria!L33),1,0) -> 1 | O33: =IF(LOWER(I33)=LOWER(Aina!N33),1,0) -> 1 | P33: =IF(LOWER(I33)=LOWER(Kappa!Y35),1,0) -> 1
A34: Unfairness by algorithm: Distilling the Harms of automated decision making | B34: Future of Privacy Forum | C34: https://fpf.org/wp-content/uploads/2017/12/FPF-Automated-Decision-Making-Harms-and-Mitigation-Charts.pdf | G34: USA | H34: 12/2017 | I34: Civil society | M34: =IF(ISNUMBER(SEARCH(",",I34)),"multistakeholders",lower(I34)) -> civil society | N34: =IF(LOWER(I34)=LOWER(Maria!L34),1,0) -> 1 | O34: =IF(LOWER(I34)=LOWER(Aina!N34),1,0) -> 1 | P34: =IF(LOWER(I34)=LOWER(Kappa!Y36),1,0) -> 1
A35: Automated Decision-Making Under the GDPR: Practical Cases from Courts and Data Protection Authorities | B35: Future of Privacy Forum | C35: https://fpf.org/wp-content/uploads/2022/05/FPF-ADM-Report-R2-singles.pdf | G35: USA | H35: 05/2022 | I35: Civil society | M35: =IF(ISNUMBER(SEARCH(",",I35)),"multistakeholders",lower(I35)) -> civil society | N35: =IF(LOWER(I35)=LOWER(Maria!L35),1,0) -> 1 | O35: =IF(LOWER(I35)=LOWER(Aina!N35),1,0) -> 1 | P35: =IF(LOWER(I35)=LOWER(Kappa!Y37),1,0) -> 1
A36: Big Data and AI Principles in Engineering | B36: World Federation of Engineering Organizations (WEFO) | C36: http://www.wfeo.org/big-data-and-ai-principles-in-engineering/ | G36: France | H36: 2020 | I36: Private sector | M36: =IF(ISNUMBER(SEARCH(",",I36)),"multistakeholders",lower(I36)) -> private sector | N36: =IF(LOWER(I36)=LOWER(Maria!L36),1,0) -> 0 | O36: =IF(LOWER(I36)=LOWER(Aina!N36),1,0) -> 0 | P36: =IF(LOWER(I36)=LOWER(Kappa!Y38),1,0) -> 0
A37: RFI for AI Services | B37: TBS Canada | C37: https://buyandsell.gc.ca/cds/public/2018/06/28/05baa93c08b6f2d3000855170f831066/ABES.PROD.PW__EE.B017.E33657.EBSU000.PDF | G37: Canada | H37: 28/06/2018 | I37: National authority | K37: Pas trouvé le document | M37: =IF(ISNUMBER(SEARCH(",",I37)),"multistakeholders",lower(I37)) -> national authority | N37: =IF(LOWER(I37)=LOWER(Maria!L37),1,0) -> 1 | O37: =IF(LOWER(I37)=LOWER(Aina!N37),1,0) -> 1 | P37: =IF(LOWER(I37)=LOWER(Kappa!Y39),1,0) -> 1
A38: Beyond pilots: sustainable implementation of AI in public services | B38: European Commission (Joint Research Centre, AI Watch) | C38: https://publications.jrc.ec.europa.eu/repository/bitstream/JRC126665/jrc126665_sustainable_implementation_of_ai_in_public_services_technical-report_v2.pdf | G38: EU | H38: 2021 | I38: International organisation | M38: =IF(ISNUMBER(SEARCH(",",I38)),"multistakeholders",lower(I38)) -> international organisation | N38: =IF(LOWER(I38)=LOWER(Maria!L38),1,0) -> 0 | O38: =IF(LOWER(I38)=LOWER(Aina!N38),1,0) -> 0 | P38: =IF(LOWER(I38)=LOWER(Kappa!Y40),1,0) -> 1
A39: Open letter: Civil society call for the introduction of red lines in the upcoming European Commission proposal on Artificial Intelligence | B39: European Digital Rights (EDRi) | C39: https://edri.org/wp-content/uploads/2021/01/EDRi-open-letter-AI-red-lines.pdf | G39: Belgium | H39: 12/01/2021 | I39: Civil Society | M39: =IF(ISNUMBER(SEARCH(",",I39)),"multistakeholders",lower(I39)) -> civil society | N39: =IF(LOWER(I39)=LOWER(Maria!L39),1,0) -> 0 | O39: =IF(LOWER(I39)=LOWER(Aina!N39),1,0) -> 1 | P39: =IF(LOWER(I39)=LOWER(Kappa!Y41),1,0) -> 1
A40: Governance Principles for a New Generation of Artificial Intelligence: Develop Responsible Artificial Intelligence | B40: National New Generation Artificial Intelligence Governance Expert Committee | C40: https://www.newamerica.org/cybersecurity-initiative/digichina/blog/translation-chinese-expert-group-offers-governance-principles-responsible-ai/ | G40: China | H40: 2019 | I40: National authority | M40: =IF(ISNUMBER(SEARCH(",",I40)),"multistakeholders",lower(I40)) -> national authority | N40: =IF(LOWER(I40)=LOWER(Maria!L40),1,0) -> 0 | O40: =IF(LOWER(I40)=LOWER(Aina!N40),1,0) -> 1 | P40: =IF(LOWER(I40)=LOWER(Kappa!Y42),1,0) -> 1
A41: Principles for Responsible AI | B41: Women leading in AI | C41: https://womenleadinginai.org/wp-content/uploads/2019/02/WLiAI-Report-2019.pdf | D41: Ivana Bartoletti,Allison Gardner,Reema Patel,Emma Gibson,Liz Stocks,Samara Banno,Sanya Sheikh,Rebecca Geach,Holly Rafique | G41: UK | H41: 2019 | I41: Civil Society | M41: =IF(ISNUMBER(SEARCH(",",I41)),"multistakeholders",lower(I41)) -> civil society | N41: =IF(LOWER(I41)=LOWER(Maria!L41),1,0) -> 1 | O41: =IF(LOWER(I41)=LOWER(Aina!N41),1,0) -> 1 | P41: =IF(LOWER(I41)=LOWER(Kappa!Y43),1,0) -> 1
A42: Report with recommendations to the Commission on a framework of ethical aspects of artificial intelligence, robotics and related technologies | B42: European Parliament | C42: https://www.europarl.europa.eu/doceo/document/A-9-2020-0186_EN.pdf | G42: EU | H42: 08/10/2020 | I42: International organisation | M42: =IF(ISNUMBER(SEARCH(",",I42)),"multistakeholders",lower(I42)) -> international organisation | N42: =IF(LOWER(I42)=LOWER(Maria!L42),1,0) -> 1 | O42: =IF(LOWER(I42)=LOWER(Aina!N42),1,0) -> 1 | P42: =IF(LOWER(I42)=LOWER(Kappa!Y44),1,0) -> 1
A43: Responsible AI Policy Framework | B43: ITechLaw | C43: https://www.itechlaw.org/publication/responsible-ai-2021-update/ | G43: USA | H43: 2021 | I43: Civil society | M43: =IF(ISNUMBER(SEARCH(",",I43)),"multistakeholders",lower(I43)) -> civil society | N43: =IF(LOWER(I43)=LOWER(Maria!L43),1,0) -> 1 | O43: =IF(LOWER(I43)=LOWER(Aina!N43),1,0) -> 1 | P43: =IF(LOWER(I43)=LOWER(Kappa!Y45),1,0) -> 1
A44: Four Principles of Explainable Artificial Intelligence | B44: National Institute of Standards and Technology (NIST) (US) | C44: https://nvlpubs.nist.gov/nistpubs/ir/2021/NIST.IR.8312.pdf | G44: USA | H44: 09/2021 | I44: National authority | M44: =IF(ISNUMBER(SEARCH(",",I44)),"multistakeholders",lower(I44)) -> national authority | N44: =IF(LOWER(I44)=LOWER(Maria!L44),1,0) -> 1 | O44: =IF(LOWER(I44)=LOWER(Aina!N44),1,0) -> 1 | P44: =IF(LOWER(I44)=LOWER(Kappa!Y46),1,0) -> 1
A45: The right to privacy in the digital age | B45: United Nations (OHCHR) | C45: https://www.ohchr.org/en/calls-for-input/2021/right-privacy-digital-age-report-2021 | G45: international | H45: 15/09/2021 | I45: International organisation | M45: =IF(ISNUMBER(SEARCH(",",I45)),"multistakeholders",lower(I45)) -> international organisation | N45: =IF(LOWER(I45)=LOWER(Maria!L45),1,0) -> 1 | O45: =IF(LOWER(I45)=LOWER(Aina!N45),1,0) -> 1 | P45: =IF(LOWER(I45)=LOWER(Kappa!Y47),1,0) -> 1
A48: academia
A49: private sector
A50: interational organisation
A51: civil society
A52: national authority

Sheet Maria
A1: Title | B1: Institution | C1: URL | G1: Country | H1: Date | I1: Sector | M1: Matthieu | N1: Aina | O1: Simon
A2: AI Index 2022 | B2: University of Stanford, SRI International, MIT, OpenAI, McKinsey Global Institute, Partnership on AI, Harvard University | C2: https://aiindex.stanford.edu/wp-content/uploads/2022/03/2022-AI-Index-Report_Master.pdf | G2: USA | H2: 2022 | I2: academia | L2: =IF(ISNUMBER(SEARCH(",",I2)),"multistakeholders",lower(I2)) -> academia | M2: =IF(LOWER(L2)=LOWER(Matthieu!M2),1,0) -> 1 | N2: =IF(LOWER(L2)=LOWER(Aina!N2),1,0) -> 0 | O2: =IF(LOWER(L2)=LOWER(Kappa!Y4),1,0) -> 0 | P2: Maria | R2: COUNTA de | S2: SUM de Matthieu | T2: SUM de Aina | U2: SUM de Simon | V2: Matthieu | W2: Aina | X2: Simon
A3: 2030 Digital Compass: the European way for the Digital Decade | B3: European Commission | C3: https://eur-lex.europa.eu/legal-content/en/TXT/?uri=CELEX%3A52021DC0118 | G3: international | H3: 09/03/2021 | I3: international organisation | L3: =IF(ISNUMBER(SEARCH(",",I3)),"multistakeholders",lower(I3)) -> international organisation | M3: =IF(LOWER(L3)=LOWER(Matthieu!M3),1,0) -> 1 | N3: =IF(LOWER(L3)=LOWER(Aina!N3),1,0) -> 1 | O3: =IF(LOWER(L3)=LOWER(Kappa!Y5),1,0) -> 1 | P3: =5/44 -> 0.11363636 | Q3: academia | R3: 5 | S3: 4 | T3: 4 | U3: 4 | V3: =S3/$R3 -> 0.8 | W3: =T3/$R3 -> 0.8 | X3: =U3/$R3 -> 0.8
A4: Global competition and convergence of AI Law | B4: Vrije Universiteit Brussel | C4: https://osf.io/preprints/socarxiv/j36ke/ | G4: Belgium | H4: 2021 | I4: academia | L4: =IF(ISNUMBER(SEARCH(",",I4)),"multistakeholders",lower(I4)) -> academia | M4: =IF(LOWER(L4)=LOWER(Matthieu!M4),1,0) -> 1 | N4: =IF(LOWER(L4)=LOWER(Aina!N4),1,0) -> 1 | O4: =IF(LOWER(L4)=LOWER(Kappa!Y6),1,0) -> 1 | P4: =6/44 -> 0.13636364 | Q4: civil society | R4: 6 | S4: 5 | T4: 6 | U4: 5 | V4: =S4/$R4 -> 0.83333333 | W4: =T4/$R4 -> 1 | X4: =U4/$R4 -> 0.83333333
A5: Technology rules? The advent of new technologies in the justice system | B5: House of Lords, Justice and Home affairs Committee (United Kingdom) | C5: https://publications.parliament.uk/pa/ld5802/ldselect/ldjusthom/180/180.pdf | G5: UK | H5: 30/03/2022 | I5: national authority | L5: =IF(ISNUMBER(SEARCH(",",I5)),"multistakeholders",lower(I5)) -> national authority | M5: =IF(LOWER(L5)=LOWER(Matthieu!M5),1,0) -> 1 | N5: =IF(LOWER(L5)=LOWER(Aina!N5),1,0) -> 1 | O5: =IF(LOWER(L5)=LOWER(Kappa!Y7),1,0) -> 1 | P5: =9/44 -> 0.20454545 | Q5: international organisation | R5: 9 | S5: 8 | T5: 9 | U5: 8 | V5: =S5/$R5 -> 0.88888889 | W5: =T5/$R5 -> 1 | X5: =U5/$R5 -> 0.88888889
A6: Algorithmic discrimination in Europe: Challenges and opportunities for gender equality and non-discrimination law | B6: European Commission (European network of legal experts in gender equality and non-discrimination) | C6: https://op.europa.eu/en/publication-detail/-/publication/082f1dbc-821d-11eb-9ac9-01aa75ed71a1 | G6: EU | H6: 10/2020 | I6: international organisation | L6: =IF(ISNUMBER(SEARCH(",",I6)),"multistakeholders",lower(I6)) -> international organisation | M6: =IF(LOWER(L6)=LOWER(Matthieu!M6),1,0) -> 1 | N6: =IF(LOWER(L6)=LOWER(Aina!N6),1,0) -> 1 | O6: =IF(LOWER(L6)=LOWER(Kappa!Y8),1,0) -> 1 | P6: =18/44 -> 0.40909091 | Q6: multistakeholders | R6: 18 | S6: 4 | T6: 8 | U6: 3 | V6: =S6/$R6 -> 0.22222222 | W6: =T6/$R6 -> 0.44444444 | X6: =U6/$R6 -> 0.16666667
A7: AI Index 2019 | B7: University of Stanford, SRI International, MIT, OpenAI, McKinsey Global Institute, Partnership on AI, Harvard University | C7: https://hai.stanford.edu/sites/default/files/ai_index_2019_report.pdf | G7: USA | H7: 2019 | I7: academia, private sector | L7: =IF(ISNUMBER(SEARCH(",",I7)),"multistakeholders",lower(I7)) -> multistakeholders | M7: =IF(LOWER(L7)=LOWER(Matthieu!M7),1,0) -> 0 | N7: =IF(LOWER(L7)=LOWER(Aina!N7),1,0) -> 1 | O7: =IF(LOWER(L7)=LOWER(Kappa!Y9),1,0) -> 1 | P7: =4/44 -> 0.090909091 | Q7: national authority | R7: 4 | S7: 4 | T7: 4 | U7: 4 | V7: =S7/$R7 -> 1 | W7: =T7/$R7 -> 1 | X7: =U7/$R7 -> 1
A8: Artificial intelligence and the control of COVID-19 | B8: Council of Europe | C8: https://www.coe.int/en/web/artificial-intelligence/ai-and-control-of-covid-19-coronavirus | G8: EU | H8: 2020 | I8: international organisation | L8: =IF(ISNUMBER(SEARCH(",",I8)),"multistakeholders",lower(I8)) -> international organisation | M8: =IF(LOWER(L8)=LOWER(Matthieu!M8),1,0) -> 1 | N8: =IF(LOWER(L8)=LOWER(Aina!N8),1,0) -> 1 | O8: =IF(LOWER(L8)=LOWER(Kappa!Y10),1,0) -> 1 | P8: =2/44 -> 0.045454545 | Q8: private sector | R8: 2 | S8: 2 | T8: 2 | U8: 2 | V8: =S8/$R8 -> 1 | W8: =T8/$R8 -> 1 | X8: =U8/$R8 -> 1
A9: Unified Ethical Frame for Big Data Analysis. IAF Big Data Ethics Initiative, Part A | B9: The Information Accountability Foundation | C9: https://bigdata.fpf.org/wp-content/uploads/2015/11/IAF-Unified-Ethical-Frame-for-Big-Data-Analysis.pdf | G9: UK | H9: 03/2015 | I9: civil society | L9: =IF(ISNUMBER(SEARCH(",",I9)),"multistakeholders",lower(I9)) -> civil society | M9: =IF(LOWER(L9)=LOWER(Matthieu!M9),1,0) -> 0 | N9: =IF(LOWER(L9)=LOWER(Aina!N9),1,0) -> 1 | O9: =IF(LOWER(L9)=LOWER(Kappa!Y11),1,0) -> 0 | Q9: Total général | R9: 44 | S9: 27 | T9: 33 | U9: 26 | V9: =S9/$R9 -> 0.61363636 | W9: =T9/$R9 -> 0.75 | X9: =U9/$R9 -> 0.59090909
A10: Artificial Intelligence | B10: Samsung Research | C10: https://research.samsung.com/artificial-intelligence | G10: South Korea | I10: private sector | L10: =IF(ISNUMBER(SEARCH(",",I10)),"multistakeholders",lower(I10)) -> private sector | M10: =IF(LOWER(L10)=LOWER(Matthieu!M10),1,0) -> 1 | N10: =IF(LOWER(L10)=LOWER(Aina!N10),1,0) -> 1 | O10: =IF(LOWER(L10)=LOWER(Kappa!Y12),1,0) -> 1
A11: The EURON Roboethics Roadmap | B11: The European Robotics Research Network (EURON) | C11: http://www.roboethics.org/index_file/Roboethics%20Roadmap%20Rel.1.2.pdf | G11: EU | H11: 01/2007 | I11: academia | L11: =IF(ISNUMBER(SEARCH(",",I11)),"multistakeholders",lower(I11)) -> academia | M11: =IF(LOWER(L11)=LOWER(Matthieu!M11),1,0) -> 0 | N11: =IF(LOWER(L11)=LOWER(Aina!N11),1,0) -> 1 | O11: =IF(LOWER(L11)=LOWER(Kappa!Y13),1,0) -> 1
A12: Understanding Artificial Intelligence and Safety - A guide for the responsible design and implementation of AI systems in the public sector | B12: The Alan Turing Institute | C12: https://www.turing.ac.uk/sites/default/files/2019-06/understanding_artificial_intelligence_ethics_and_safety.pdf | G12: UK | H12: 2019 | I12: academia, national authority | L12: =IF(ISNUMBER(SEARCH(",",I12)),"multistakeholders",lower(I12)) -> multistakeholders | M12: =IF(LOWER(L12)=LOWER(Matthieu!M12),1,0) -> 0 | N12: =IF(LOWER(L12)=LOWER(Aina!N12),1,0) -> 0 | O12: =IF(LOWER(L12)=LOWER(Kappa!Y14),1,0) -> 1
A13: Digital Ethics: A guide for professionals of the Digital Age | B13: CIGREF/Syntec Numérique | C13: https://www.cigref.fr/wp/wp-content/uploads/2019/02/Cigref-Syntec-Digital-Ethics-Guide-for-Professionals-of-Digital-Age-2018-October-EN.pdf | G13: France | H13: 10/2018 | I13: private sector, civil society | L13: =IF(ISNUMBER(SEARCH(",",I13)),"multistakeholders",lower(I13)) -> multistakeholders | M13: =IF(LOWER(L13)=LOWER(Matthieu!M13),1,0) -> 0 | N13: =IF(LOWER(L13)=LOWER(Aina!N13),1,0) -> 1 | O13: =IF(LOWER(L13)=LOWER(Kappa!Y15),1,0) -> 0
A14: Human Rights, Democracy, and the Rule of Law Assurance Framework for AI Systems: A proposal prepared for the Council of Europe’s Ad hoc Committee on Artificial Intelligence | B14: The Alan Turing Institute | C14: https://rm.coe.int/huderaf-coe-final-1-2752-6741-5300-v-1/1680a3f688 | G14: UK | H14: 2021 | I14: academia, national authority | L14: =IF(ISNUMBER(SEARCH(",",I14)),"multistakeholders",lower(I14)) -> multistakeholders | M14: =IF(LOWER(L14)=LOWER(Matthieu!M14),1,0) -> 0 | N14: =IF(LOWER(L14)=LOWER(Aina!N14),1,0) -> 1 | O14: =IF(LOWER(L14)=LOWER(Kappa!Y16),1,0) -> 1
A15: Study on AI Governance by Human Rights-Centred Design, Deliberation and Oversight | B15: University of Birmingham | C15: https://papers.ssrn.com/sol3/papers.cfm?abstract_id=3435011 | G15: UK | H15: 09/08/2019 | I15: academia | L15: =IF(ISNUMBER(SEARCH(",",I15)),"multistakeholders",lower(I15)) -> academia | M15: =IF(LOWER(L15)=LOWER(Matthieu!M15),1,0) -> 1 | N15: =IF(LOWER(L15)=LOWER(Aina!N15),1,0) -> 1 | O15: =IF(LOWER(L15)=LOWER(Kappa!Y17),1,0) -> 1
A16: European ethical Charter on the use of Artificial Intelligence in judicial systems and their environment | B16: Council of Europe: European Commission for the efficiency of Justice (CEPEJ) | C16: https://rm.coe.int/ethical-charter-en-for-publication-4-december-2018/16808f699c | G16: EU | H16: 04/12/2018 | I16: international organisation | L16: =IF(ISNUMBER(SEARCH(",",I16)),"multistakeholders",lower(I16)) -> international organisation | M16: =IF(LOWER(L16)=LOWER(Matthieu!M16),1,0) -> 1 | N16: =IF(LOWER(L16)=LOWER(Aina!N16),1,0) -> 1 | O16: =IF(LOWER(L16)=LOWER(Kappa!Y18),1,0) -> 1
A17: The Road to a Human-Centred Digital Society | B17: Centre on AI Technology for Humanking (AiTH) at NUS Business School | C17: https://drive.google.com/uc?export=download&id=1aRyqczni56ONA9PVExt2DrrJ1ATGKSu0 | D17: David De Cremer, Devesh Narayanan, Andreas Deppeler, Mahak Nagpal, Jack McGuire, Jess Zhang | E17: National University of Singapore | G17: Singapore | H17: 12/2021 | I17: academia | L17: =IF(ISNUMBER(SEARCH(",",I17)),"multistakeholders",lower(I17)) -> academia | M17: =IF(LOWER(L17)=LOWER(Matthieu!M17),1,0) -> 1 | N17: =IF(LOWER(L17)=LOWER(Aina!N17),1,0) -> 1 | O17: =IF(LOWER(L17)=LOWER(Kappa!Y19),1,0) -> 1
A18: AI Roadmap | B18: AI Council (United Kingdom) | C18: https://assets.publishing.service.gov.uk/media/5ff3bc6e8fa8f53b76ccee23/AI_Council_AI_Roadmap.pdf | G18: UK | H18: 01/2021 | I18: civil society, national authority | L18: =IF(ISNUMBER(SEARCH(",",I18)),"multistakeholders",lower(I18)) -> multistakeholders | M18: =IF(LOWER(L18)=LOWER(Matthieu!M18),1,0) -> 0 | N18: =IF(LOWER(L18)=LOWER(Aina!N18),1,0) -> 0 | O18: =IF(LOWER(L18)=LOWER(Kappa!Y20),1,0) -> 0
A19: Growing the artificial intelligence industry in the UK | B19: Department for Digital, Culture, Media & Sport and Department for Business, Energy & Industrial Strategy (United Kingdom) | C19: https://www.gov.uk/government/publications/growing-the-artificial-intelligence-industry-in-the-uk | G19: UK | H19: 15/10/2017 | I19: academia, private sector, national authority | L19: =IF(ISNUMBER(SEARCH(",",I19)),"multistakeholders",lower(I19)) -> multistakeholders | M19: =IF(LOWER(L19)=LOWER(Matthieu!M19),1,0) -> 0 | N19: =IF(LOWER(L19)=LOWER(Aina!N19),1,0) -> 1 | O19: =IF(LOWER(L19)=LOWER(Kappa!Y21),1,0) -> 0
A20: AI Now 2017 Report | B20: AI Now Institute | C20: https://ainowinstitute.org/wp-content/uploads/2023/04/AI_Now_2017_Report.pdf | G20: USA | H20: 2017 | I20: civil society, academia | L20: =IF(ISNUMBER(SEARCH(",",I20)),"multistakeholders",lower(I20)) -> multistakeholders | M20: =IF(LOWER(L20)=LOWER(Matthieu!M20),1,0) -> 1 | N20: =IF(LOWER(L20)=LOWER(Aina!N20),1,0) -> 0 | O20: =IF(LOWER(L20)=LOWER(Kappa!Y22),1,0) -> 0
A21: Algorithms in Decision Making | B21: Parliament Science and Technology Committee (United Kingdom) | C21: https://publications.parliament.uk/pa/cm201719/cmselect/cmsctech/351/351.pdf | G21: UK | H21: 23/05/2018 | I21: civil society, national authority | L21: =IF(ISNUMBER(SEARCH(",",I21)),"multistakeholders",lower(I21)) -> multistakeholders | M21: =IF(LOWER(L21)=LOWER(Matthieu!M21),1,0) -> 0 | N21: =IF(LOWER(L21)=LOWER(Aina!N21),1,0) -> 0 | O21: =IF(LOWER(L21)=LOWER(Kappa!Y23),1,0) -> 0
A22: Thematic Reviews on 'Social Aspects of Digitalisation' (SPC) and 'Digitalisation and Robotisation of Work' (EMCO) - Endorsement of the joint key messages, 14411/18 | B22: Council of the European Union | C22: http://data.consilium.europa.eu/doc/document/ST-14411-2018-INIT/en/pdf | G22: EU | H22: 19/11/2018 | I22: international organisation | L22: =IF(ISNUMBER(SEARCH(",",I22)),"multistakeholders",lower(I22)) -> international organisation | M22: =IF(LOWER(L22)=LOWER(Matthieu!M22),1,0) -> 1 | N22: =IF(LOWER(L22)=LOWER(Aina!N22),1,0) -> 1 | O22: =IF(LOWER(L22)=LOWER(Kappa!Y24),1,0) -> 1
A23: Standards for AI Governance: International Standards to Enable Global Coordination in AI Research & Development | B23: Future of Humanity Institute, University of Oxford | C23: https://www.fhi.ox.ac.uk/wp-content/uploads/Standards_-FHI-Technical-Report.pdf | G23: international | H23: 04/2019 | I23: civil society, academia | L23: =IF(ISNUMBER(SEARCH(",",I23)),"multistakeholders",lower(I23)) -> multistakeholders | M23: =IF(LOWER(L23)=LOWER(Matthieu!M23),1,0) -> 0 | N23: =IF(LOWER(L23)=LOWER(Aina!N23),1,0) -> 1 | O23: =IF(LOWER(L23)=LOWER(Kappa!Y25),1,0) -> 0
A24: Preparing the future of AI | B24: National Science and Technology Council (US) | C24: https://obamawhitehouse.archives.gov/sites/default/files/whitehouse_files/microsites/ostp/NSTC/preparing_for_the_future_of_ai.pdf | G24: USA | H24: 10/2016 | I24: national authority | L24: =IF(ISNUMBER(SEARCH(",",I24)),"multistakeholders",lower(I24)) -> national authority | M24: =IF(LOWER(L24)=LOWER(Matthieu!M24),1,0) -> 1 | N24: =IF(LOWER(L24)=LOWER(Aina!N24),1,0) -> 1 | O24: =IF(LOWER(L24)=LOWER(Kappa!Y26),1,0) -> 1
A25: AI Now Report 2016. The Social and Economic Implications of Artificial Intelligence Technologies in the Near-Term | B25: AI Now Institute | C25: https://assets.ctfassets.net/8wprhhvnpfc0/3JOy5k4f1YSCQOi8MCCmA2/97010d04fbc7892662ce8b2469dc1601/AI_Now_2016_Report.pdf | G25: USA | H25: 22/09/2016 | I25: national authority, academia | L25: =IF(ISNUMBER(SEARCH(",",I25)),"multistakeholders",lower(I25)) -> multistakeholders | M25: =IF(LOWER(L25)=LOWER(Matthieu!M25),1,0) -> 1 | N25: =IF(LOWER(L25)=LOWER(Aina!N25),1,0) -> 1 | O25: =IF(LOWER(L25)=LOWER(Kappa!Y27),1,0) -> 0
A26: G20 AI Principles | B26: Ministry of Internal Affairs and Communications | C26: https://www.mofa.go.jp/policy/economy/g20_summit/osaka19/pdf/documents/en/annex_08.pdf | G26: Japan | H26: 2019 | I26: international organisation | L26: =IF(ISNUMBER(SEARCH(",",I26)),"multistakeholders",lower(I26)) -> international organisation | M26: =IF(LOWER(L26)=LOWER(Matthieu!M26),1,0) -> 0 | N26: =IF(LOWER(L26)=LOWER(Aina!N26),1,0) -> 1 | O26: =IF(LOWER(L26)=LOWER(Kappa!Y28),1,0) -> 0
A27: Principles for the Governance of AI | B27: The Future Society Science Law and Society (SLS) Initiative | C27: https://thefuturesociety.org/principles-law-and-society-initiative/ | G27: USA | H27: 15/07/2017 | I27: civil society | L27: =IF(ISNUMBER(SEARCH(",",I27)),"multistakeholders",lower(I27)) -> civil society | M27: =IF(LOWER(L27)=LOWER(Matthieu!M27),1,0) -> 1 | N27: =IF(LOWER(L27)=LOWER(Aina!N27),1,0) -> 1 | O27: =IF(LOWER(L27)=LOWER(Kappa!Y29),1,0) -> 1
A28: 4 Steps to developing Responsible AI | B28: World Economic Forum (WEF) | C28: https://www.weforum.org/agenda/2019/06/4-steps-to-developing-responsible-ai/ | G28: international | H28: 20/06/2019 | I28: civil society, international organisation | L28: =IF(ISNUMBER(SEARCH(",",I28)),"multistakeholders",lower(I28)) -> multistakeholders | M28: =IF(LOWER(L28)=LOWER(Matthieu!M28),1,0) -> 0 | N28: =IF(LOWER(L28)=LOWER(Aina!N28),1,0) -> 0 | O28: =IF(LOWER(L28)=LOWER(Kappa!Y30),1,0) -> 0
A29: Opinion on AI - The consequences of artificial intelligence on the (digital) single market, production, consumption, employment and society’ | B29: European Economic and Social Committee (EESC) | C29: https://eur-lex.europa.eu/legal-content/EN/TXT/PDF/?uri=CELEX:52016IE5369&from=EN | G29: international | H29: 31/08/2017 | I29: international organisation, civil society | L29: =IF(ISNUMBER(SEARCH(",",I29)),"multistakeholders",lower(I29)) -> multistakeholders | M29: =IF(LOWER(L29)=LOWER(Matthieu!M29),1,0) -> 0 | N29: =IF(LOWER(L29)=LOWER(Aina!N29),1,0) -> 0 | O29: =IF(LOWER(L29)=LOWER(Kappa!Y31),1,0) -> 0
... A32: Recomendations on the inclusion subSaharan Africa in Global AI Ethics | B32: Research ICT Africa | C32: https://researchictafrica.net/ranitp2019-2-ai-ethics/ | G32: South Africa | H32: 02/2019 | I32: academia, civil society | L32: =IF(ISNUMBER(SEARCH(",",I32)),"multistakeholders",lower(I32)) -> multistakeholders | M32: =IF(LOWER(L32)=LOWER(Matthieu!M32),1,0) -> 1 | N32: =IF(LOWER(L32)=LOWER(Aina!N32),1,0) -> 0 | O32: =IF(LOWER(L32)=LOWER(Kappa!Y34),1,0) -> 0
A33: Our principles | B33: Google | C33: https://blog.google/technology/ai/ai-principles/ | D33: . | E33: . | G33: USA | H33: 2018 | I33: private sector | L33: =IF(ISNUMBER(SEARCH(",",I33)),"multistakeholders",lower(I33)) -> private sector | M33: =IF(LOWER(L33)=LOWER(Matthieu!M33),1,0) -> 1 | N33: =IF(LOWER(L33)=LOWER(Aina!N33),1,0) -> 1 | O33: =IF(LOWER(L33)=LOWER(Kappa!Y35),1,0) -> 1
A34: Unfairness by algorithm: Distilling the Harms of automated decision making | B34: Future of Privacy Forum | C34: https://fpf.org/wp-content/uploads/2017/12/FPF-Automated-Decision-Making-Harms-and-Mitigation-Charts.pdf | G34: USA | H34: 12/2017 | I34: civil society | L34: =IF(ISNUMBER(SEARCH(",",I34)),"multistakeholders",lower(I34)) -> civil society | M34: =IF(LOWER(L34)=LOWER(Matthieu!M34),1,0) -> 1 | N34: =IF(LOWER(L34)=LOWER(Aina!N34),1,0) -> 1 | O34: =IF(LOWER(L34)=LOWER(Kappa!Y36),1,0) -> 1
A35: Automated Decision-Making Under the GDPR: Practical Cases from Courts and Data Protection Authorities | B35: Future of Privacy Forum | C35: https://fpf.org/wp-content/uploads/2022/05/FPF-ADM-Report-R2-singles.pdf | G35: USA | H35: 05/2022 | I35: civil society | L35: =IF(ISNUMBER(SEARCH(",",I35)),"multistakeholders",lower(I35)) -> civil society | M35: =IF(LOWER(L35)=LOWER(Matthieu!M35),1,0) -> 1 | N35: =IF(LOWER(L35)=LOWER(Aina!N35),1,0) -> 1 | O35: =IF(LOWER(L35)=LOWER(Kappa!Y37),1,0) -> 1
A36: Big Data and AI Principles in Engineering | B36: World Federation of Engineering Organizations (WEFO) | C36: http://www.wfeo.org/big-data-and-ai-principles-in-engineering/ | G36: France | H36: 2020 | I36: civil society, private sector | L36: =IF(ISNUMBER(SEARCH(",",I36)),"multistakeholders",lower(I36)) -> multistakeholders | M36: =IF(LOWER(L36)=LOWER(Matthieu!M36),1,0) -> 0 | N36: =IF(LOWER(L36)=LOWER(Aina!N36),1,0) -> 1 | O36: =IF(LOWER(L36)=LOWER(Kappa!Y38),1,0) -> 0
A37: RFI for AI Services | B37: TBS Canada | C37: https://buyandsell.gc.ca/cds/public/2018/06/28/05baa93c08b6f2d3000855170f831066/ABES.PROD.PW__EE.B017.E33657.EBSU000.PDF | G37: Canada | H37: 28/06/2018 | I37: national authority | L37: =IF(ISNUMBER(SEARCH(",",I37)),"multistakeholders",lower(I37)) -> national authority | M37: =IF(LOWER(L37)=LOWER(Matthieu!M37),1,0) -> 1 | N37: =IF(LOWER(L37)=LOWER(Aina!N37),1,0) -> 1 | O37: =IF(LOWER(L37)=LOWER(Kappa!Y39),1,0) -> 1
A38: Beyond pilots: sustainable implementation of AI in public services | B38: European Commission (Joint Research Centre, AI Watch) | C38: https://publications.jrc.ec.europa.eu/repository/bitstream/JRC126665/jrc126665_sustainable_implementation_of_ai_in_public_services_technical-report_v2.pdf | G38: EU | H38: 2021 | I38: international organisation, academia | L38: =IF(ISNUMBER(SEARCH(",",I38)),"multistakeholders",lower(I38)) -> multistakeholders | M38: =IF(LOWER(L38)=LOWER(Matthieu!M38),1,0) -> 0 | N38: =IF(LOWER(L38)=LOWER(Aina!N38),1,0) -> 1 | O38: =IF(LOWER(L38)=LOWER(Kappa!Y40),1,0) -> 0
A39: Open letter: Civil society call for the introduction of red lines in the upcoming European Commission proposal on Artificial Intelligence | B39: European Digital Rights (EDRi) | C39: https://edri.org/wp-content/uploads/2021/01/EDRi-open-letter-AI-red-lines.pdf | G39: Belgium | H39: 12/01/2021 | I39: civil society, academia | L39: =IF(ISNUMBER(SEARCH(",",I39)),"multistakeholders",lower(I39)) -> multistakeholders | M39: =IF(LOWER(L39)=LOWER(Matthieu!M39),1,0) -> 0 | N39: =IF(LOWER(L39)=LOWER(Aina!N39),1,0) -> 0 | O39: =IF(LOWER(L39)=LOWER(Kappa!Y41),1,0) -> 0
A40: Governance Principles for a New Generation of Artificial Intelligence: Develop Responsible Artificial Intelligence | B40: National New Generation Artificial Intelligence Governance Expert Committee | C40: https://www.newamerica.org/cybersecurity-initiative/digichina/blog/translation-chinese-expert-group-offers-governance-principles-responsible-ai/ | G40: China | H40: 2019 | I40: national authority, academia | L40: =IF(ISNUMBER(SEARCH(",",I40)),"multistakeholders",lower(I40)) -> multistakeholders | M40: =IF(LOWER(L40)=LOWER(Matthieu!M40),1,0) -> 0 | N40: =IF(LOWER(L40)=LOWER(Aina!N40),1,0) -> 0 | O40: =IF(LOWER(L40)=LOWER(Kappa!Y42),1,0) -> 0
A41: Principles for Responsible AI | B41: Women leading in AI | C41: https://womenleadinginai.org/wp-content/uploads/2019/02/WLiAI-Report-2019.pdf | D41: Ivana Bartoletti,Allison Gardner,Reema Patel,Emma Gibson,Liz Stocks,Samara Banno,Sanya Sheikh,Rebecca Geach,Holly Rafique | G41: UK | H41: 2019 | I41: civil society | L41: =IF(ISNUMBER(SEARCH(",",I41)),"multistakeholders",lower(I41)) -> civil society | M41: =IF(LOWER(L41)=LOWER(Matthieu!M41),1,0) -> 1 | N41: =IF(LOWER(L41)=LOWER(Aina!N41),1,0) -> 1 | O41: =IF(LOWER(L41)=LOWER(Kappa!Y43),1,0) -> 1
A42: Report with recommendations to the Commission on a framework of ethical aspects of artificial intelligence, robotics and related technologies | B42: European Parliament | C42: https://www.europarl.europa.eu/doceo/document/A-9-2020-0186_EN.pdf | G42: EU | H42: 08/10/2020 | I42: international organisation | L42: =IF(ISNUMBER(SEARCH(",",I42)),"multistakeholders",lower(I42)) -> international organisation | M42: =IF(LOWER(L42)=LOWER(Matthieu!M42),1,0) -> 1 | N42: =IF(LOWER(L42)=LOWER(Aina!N42),1,0) -> 1 | O42: =IF(LOWER(L42)=LOWER(Kappa!Y44),1,0) -> 1
A43: Responsible AI Policy Framework | B43: ITechLaw | C43: https://www.itechlaw.org/publication/responsible-ai-2021-update/ | G43: USA | H43: 2021 | I43: civil society | L43: =IF(ISNUMBER(SEARCH(",",I43)),"multistakeholders",lower(I43)) -> civil society | M43: =IF(LOWER(L43)=LOWER(Matthieu!M43),1,0) -> 1 | N43: =IF(LOWER(L43)=LOWER(Aina!N43),1,0) -> 1 | O43: =IF(LOWER(L43)=LOWER(Kappa!Y45),1,0) -> 1
A44: Four Principles of Explainable Artificial Intelligence | B44: National Institute of Standards and Technology (NIST) (US) | C44: https://nvlpubs.nist.gov/nistpubs/ir/2021/NIST.IR.8312.pdf | G44: USA | H44: 09/2021 | I44: national authority | L44: =IF(ISNUMBER(SEARCH(",",I44)),"multistakeholders",lower(I44)) -> national authority | M44: =IF(LOWER(L44)=LOWER(Matthieu!M44),1,0) -> 1 | N44: =IF(LOWER(L44)=LOWER(Aina!N44),1,0) -> 1 | O44: =IF(LOWER(L44)=LOWER(Kappa!Y46),1,0) -> 1
A45: The right to privacy in the digital age | B45: United Nations (OHCHR) | C45: https://www.ohchr.org/en/calls-for-input/2021/right-privacy-digital-age-report-2021 | G45: international | H45: 15/09/2021 | I45: international organisation | L45: =IF(ISNUMBER(SEARCH(",",I45)),"multistakeholders",lower(I45)) -> international organisation | M45: =IF(LOWER(L45)=LOWER(Matthieu!M45),1,0) -> 1 | N45: =IF(LOWER(L45)=LOWER(Aina!N45),1,0) -> 1 | O45: =IF(LOWER(L45)=LOWER(Kappa!Y47),1,0) -> 1

Sheet Aina
A1: Title | B1: Institution | C1: URL | G1: Country | H1: Date | I1: Sector | J1: unsure? | K1: justification (when unsure / if needed for discussion) | O1: Matthieu | P1: Maria | Q1: Simon
A2: AI Index 2022 | B2: University of Stanford, SRI International, MIT, OpenAI, McKinsey Global Institute, Partnership on AI, Harvard University | C2: https://aiindex.stanford.edu/wp-content/uploads/2022/03/2022-AI-Index-Report_Master.pdf | G2: USA | H2: 2022 | I2: academia, private sector | K2: "The AI Index is an independent initiative at the Stanford Institute for Human-Centered Artificial Intelligence (HAI), led by the AI Index Steering Committee, an interdisciplinary group of experts from across academia and industry" | N2: =IF(ISNUMBER(SEARCH(",",I2)),"multistakeholders",lower(I2)) -> multistakeholders | O2: =IF(LOWER(N2)=LOWER(Matthieu!M2),1,0) -> 0 | P2: =IF(LOWER(N2)=LOWER(Maria!L2),1,0) -> 0 | Q2: =IF(LOWER(N2)=LOWER(Kappa!Y4),1,0) -> 1 | S2: COUNTA de | T2: SUM de Matthieu | U2: SUM de Maria | V2: SUM de Simon | W2: Matthieu | X2: Maria | Y2: Simon
A3: 2030 Digital Compass: the European way for the Digital Decade | B3: European Commission | C3: https://eur-lex.europa.eu/legal-content/en/TXT/?uri=CELEX%3A52021DC0118 | G3: international | H3: 09/03/2021 | I3: international organisation | N3: =IF(ISNUMBER(SEARCH(",",I3)),"multistakeholders",lower(I3)) -> international organisation | O3: =IF(LOWER(N3)=LOWER(Matthieu!M3),1,0) -> 1 | P3: =IF(LOWER(N3)=LOWER(Maria!L3),1,0) -> 1 | Q3: =IF(LOWER(N3)=LOWER(Kappa!Y5),1,0) -> 1 | R3: academia | S3: 6 | T3: 4 | U3: 4 | V3: 4 | W3: =T3/$S3 -> 0.66666667 | X3: =U3/$S3 -> 0.66666667 | Y3: =V3/$S3 -> 0.66666667
A4: Global competition and convergence of AI Law | B4: Vrije Universiteit Brussel | C4: https://osf.io/preprints/socarxiv/j36ke/ | G4: Belgium | H4: 2021 | I4: academia | N4: =IF(ISNUMBER(SEARCH(",",I4)),"multistakeholders",lower(I4)) -> academia | O4: =IF(LOWER(N4)=LOWER(Matthieu!M4),1,0) -> 1 | P4: =IF(LOWER(N4)=LOWER(Maria!L4),1,0) -> 1 | Q4: =IF(LOWER(N4)=LOWER(Kappa!Y6),1,0) -> 1 | R4: civil society | S4: 11 | T4: 7 | U4: 6 | V4: 9 | W4: =T4/$S4 -> 0.63636364 | X4: =U4/$S4 -> 0.54545455 | Y4: =V4/$S4 -> 0.81818182
A5: Technology rules? The advent of new technologies in the justice system | B5: House of Lords, Justice and Home affairs Committee (United Kingdom) | C5: https://publications.parliament.uk/pa/ld5802/ldselect/ldjusthom/180/180.pdf | G5: UK | H5: 30/03/2022 | I5: national authority | N5: =IF(ISNUMBER(SEARCH(",",I5)),"multistakeholders",lower(I5)) -> national authority | O5: =IF(LOWER(N5)=LOWER(Matthieu!M5),1,0) -> 1 | P5: =IF(LOWER(N5)=LOWER(Maria!L5),1,0) -> 1 | Q5: =IF(LOWER(N5)=LOWER(Kappa!Y7),1,0) -> 1 | R5: international organisation | S5: 10 | T5: 9 | U5: 9 | V5: 9 | W5: =T5/$S5 -> 0.9 | X5: =U5/$S5 -> 0.9 | Y5: =V5/$S5 -> 0.9
A6: Algorithmic discrimination in Europe: Challenges and opportunities for gender equality and non-discrimination law | B6: European Commission (European network of legal experts in gender equality and non-discrimination) | C6: https://op.europa.eu/en/publication-detail/-/publication/082f1dbc-821d-11eb-9ac9-01aa75ed71a1 | G6: EU | H6: 10/2020 | I6: international organisation | N6: =IF(ISNUMBER(SEARCH(",",I6)),"multistakeholders",lower(I6)) -> international organisation | O6: =IF(LOWER(N6)=LOWER(Matthieu!M6),1,0) -> 1 | P6: =IF(LOWER(N6)=LOWER(Maria!L6),1,0) -> 1 | Q6: =IF(LOWER(N6)=LOWER(Kappa!Y8),1,0) -> 1 | R6: multistakeholders | S6: 9 | T6: 1 | U6: 8 | V6: 3 | W6: =T6/$S6 -> 0.11111111 | X6: =U6/$S6 -> 0.88888889 | Y6: =V6/$S6 -> 0.33333333
A7: AI Index 2019 | B7: University of Stanford, SRI International, MIT, OpenAI, McKinsey Global Institute, Partnership on AI, Harvard University | C7: https://hai.stanford.edu/sites/default/files/ai_index_2019_report.pdf | G7: USA | H7: 2019 | I7: academia, private sector | K7: SRI, OpenAI... + Stanford, MIT... | N7: =IF(ISNUMBER(SEARCH(",",I7)),"multistakeholders",lower(I7)) -> multistakeholders | O7: =IF(LOWER(N7)=LOWER(Matthieu!M7),1,0) -> 0 | P7: =IF(LOWER(N7)=LOWER(Maria!L7),1,0) -> 1 | Q7: =IF(LOWER(N7)=LOWER(Kappa!Y9),1,0) -> 1 | R7: national authority | S7: 6 | T7: 6 | U7: 4 | V7: 6 | W7: =T7/$S7 -> 1 | X7: =U7/$S7 -> 0.66666667 | Y7: =V7/$S7 -> 1
A8: Artificial intelligence and the control of COVID-19 | B8: Council of Europe | C8: https://www.coe.int/en/web/artificial-intelligence/ai-and-control-of-covid-19-coronavirus | G8: EU | H8: 2020 | I8: international organisation | N8: =IF(ISNUMBER(SEARCH(",",I8)),"multistakeholders",lower(I8)) -> international organisation | O8: =IF(LOWER(N8)=LOWER(Matthieu!M8),1,0) -> 1 | P8: =IF(LOWER(N8)=LOWER(Maria!L8),1,0) -> 1 | Q8: =IF(LOWER(N8)=LOWER(Kappa!Y10),1,0) -> 1 | R8: private sector | S8: 2 | T8: 2 | U8: 2 | V8: 2 | W8: =T8/$S8 -> 1 | X8: =U8/$S8 -> 1 | Y8: =V8/$S8 -> 1
A9: Unified Ethical Frame for Big Data Analysis. IAF Big Data Ethics Initiative, Part A | B9: The Information Accountability Foundation | C9: https://bigdata.fpf.org/wp-content/uploads/2015/11/IAF-Unified-Ethical-Frame-for-Big-Data-Analysis.pdf | G9: UK | H9: 03/2015 | I9: civil society | N9: =IF(ISNUMBER(SEARCH(",",I9)),"multistakeholders",lower(I9)) -> civil society | O9: =IF(LOWER(N9)=LOWER(Matthieu!M9),1,0) -> 0 | P9: =IF(LOWER(N9)=LOWER(Maria!L9),1,0) -> 1 | Q9: =IF(LOWER(N9)=LOWER(Kappa!Y11),1,0) -> 0 | R9: Total général | S9: 44 | T9: 29 | U9: 33 | V9: 33 | W9: =T9/$S9 -> 0.65909091 | X9: =U9/$S9 -> 0.75 | Y9: =V9/$S9 -> 0.75
A10: Artificial Intelligence | B10: Samsung Research | C10: https://research.samsung.com/artificial-intelligence | G10: South Korea | I10: private sector | N10: =IF(ISNUMBER(SEARCH(",",I10)),"multistakeholders",lower(I10)) -> private sector | O10: =IF(LOWER(N10)=LOWER(Matthieu!M10),1,0) -> 1 | P10: =IF(LOWER(N10)=LOWER(Maria!L10),1,0) -> 1 | Q10: =IF(LOWER(N10)=LOWER(Kappa!Y12),1,0) -> 1 | S10: Aina
A11: The EURON Roboethics Roadmap | B11: The European Robotics Research Network (EURON) | C11: http://www.roboethics.org/index_file/Roboethics%20Roadmap%20Rel.1.2.pdf | G11: EU | H11: 01/2007 | I11: academia | J11: VERY UNSURE | K11: (mostly researchers, but funded by EU and wants to promote links with industry) | N11: =IF(ISNUMBER(SEARCH(",",I11)),"multistakeholders",lower(I11)) -> academia | O11: =IF(LOWER(N11)=LOWER(Matthieu!M11),1,0) -> 0 | P11: =IF(LOWER(N11)=LOWER(Maria!L11),1,0) -> 1 | Q11: =IF(LOWER(N11)=LOWER(Kappa!Y13),1,0) -> 1 | S11: =S3/$S$9 -> 0.13636364
A12: Understanding Artificial Intelligence and Safety - A guide for the responsible design and implementation of AI systems in the public sector | B12: The Alan Turing Institute | C12: https://www.turing.ac.uk/sites/default/files/2019-06/understanding_artificial_intelligence_ethics_and_safety.pdf | G12: UK | H12: 2019 | I12: academia | N12: =IF(ISNUMBER(SEARCH(",",I12)),"multistakeholders",lower(I12)) -> academia | O12: =IF(LOWER(N12)=LOWER(Matthieu!M12),1,0) -> 1 | P12: =IF(LOWER(N12)=LOWER(Maria!L12),1,0) -> 0 | Q12: =IF(LOWER(N12)=LOWER(Kappa!Y14),1,0) -> 0 | S12: =S4/$S$9 -> 0.25
A13: Digital Ethics: A guide for professionals of the Digital Age | B13: CIGREF/Syntec Numérique | C13: https://www.cigref.fr/wp/wp-content/uploads/2019/02/Cigref-Syntec-Digital-Ethics-Guide-for-Professionals-of-Digital-Age-2018-October-EN.pdf | G13: France | H13: 10/2018 | I13: private sector, national authority | K13: cigref = "Réseau de grandes entreprises et administration publiques françaises" | N13: =IF(ISNUMBER(SEARCH(",",I13)),"multistakeholders",lower(I13)) -> multistakeholders | O13: =IF(LOWER(N13)=LOWER(Matthieu!M13),1,0) -> 0 | P13: =IF(LOWER(N13)=LOWER(Maria!L13),1,0) -> 1 | Q13: =IF(LOWER(N13)=LOWER(Kappa!Y15),1,0) -> 0 | S13: =S5/$S$9 -> 0.22727273
A14: Human Rights, Democracy, and the Rule of Law Assurance Framework for AI Systems: A proposal prepared for the Council of Europe’s Ad hoc Committee on Artificial Intelligence | B14: The Alan Turing Institute | C14: https://rm.coe.int/huderaf-coe-final-1-2752-6741-5300-v-1/1680a3f688 | G14: UK | H14: 2021 | I14: academia, international organisation | K14: cahai (int org) + alan turing (academia) | N14: =IF(ISNUMBER(SEARCH(",",I14)),"multistakeholders",lower(I14)) -> multistakeholders | O14: =IF(LOWER(N14)=LOWER(Matthieu!M14),1,0) -> 0 | P14: =IF(LOWER(N14)=LOWER(Maria!L14),1,0) -> 1 | Q14: =IF(LOWER(N14)=LOWER(Kappa!Y16),1,0) -> 1 | S14: =S6/$S$9 -> 0.20454545
A15: Study on AI Governance by Human Rights-Centred Design, Deliberation and Oversight | B15: University of Birmingham | C15: https://papers.ssrn.com/sol3/papers.cfm?abstract_id=3435011 | G15: UK | H15: 09/08/2019 | I15: academia | N15: =IF(ISNUMBER(SEARCH(",",I15)),"multistakeholders",lower(I15)) -> academia | O15: =IF(LOWER(N15)=LOWER(Matthieu!M15),1,0) -> 1 | P15: =IF(LOWER(N15)=LOWER(Maria!L15),1,0) -> 1 | Q15: =IF(LOWER(N15)=LOWER(Kappa!Y17),1,0) -> 1 | S15: =S7/$S$9 -> 0.13636364
A16: European ethical Charter on the use of Artificial Intelligence in judicial systems and their environment | B16: Council of Europe: European Commission for the efficiency of Justice (CEPEJ) | C16: https://rm.coe.int/ethical-charter-en-for-publication-4-december-2018/16808f699c | G16: EU | H16: 04/12/2018 | I16: international organisation | N16: =IF(ISNUMBER(SEARCH(",",I16)),"multistakeholders",lower(I16)) -> international organisation | O16: =IF(LOWER(N16)=LOWER(Matthieu!M16),1,0) -> 1 | P16: =IF(LOWER(N16)=LOWER(Maria!L16),1,0) -> 1 | Q16: =IF(LOWER(N16)=LOWER(Kappa!Y18),1,0) -> 1 | S16: =S8/$S$9 -> 0.045454545
A17: The Road to a Human-Centred Digital Society | B17: Centre on AI Technology for Humanking (AiTH) at NUS Business School | C17: https://drive.google.com/uc?export=download&id=1aRyqczni56ONA9PVExt2DrrJ1ATGKSu0 | D17: David De Cremer, Devesh Narayanan, Andreas Deppeler, Mahak Nagpal, Jack McGuire, Jess Zhang | E17: National University of Singapore | G17: Singapore | H17: 12/2021 | I17: academia | N17: =IF(ISNUMBER(SEARCH(",",I17)),"multistakeholders",lower(I17)) -> academia | O17: =IF(LOWER(N17)=LOWER(Matthieu!M17),1,0) -> 1 | P17: =IF(LOWER(N17)=LOWER(Maria!L17),1,0) -> 1 | Q17: =IF(LOWER(N17)=LOWER(Kappa!Y19),1,0) -> 1
A18: AI Roadmap | B18: AI Council (United Kingdom) | C18: https://assets.publishing.service.gov.uk/media/5ff3bc6e8fa8f53b76ccee23/AI_Council_AI_Roadmap.pdf | G18: UK | H18: 01/2021 | I18: civil society | N18: =IF(ISNUMBER(SEARCH(",",I18)),"multistakeholders",lower(I18)) -> civil society | O18: =IF(LOWER(N18)=LOWER(Matthieu!M18),1,0) -> 1 | P18: =IF(LOWER(N18)=LOWER(Maria!L18),1,0) -> 0 | Q18: =IF(LOWER(N18)=LOWER(Kappa!Y20),1,0) -> 0
A19: Growing the artificial intelligence industry in the UK | B19: Department for Digital, Culture, Media & Sport and Department for Business, Energy & Industrial Strategy (United Kingdom) | C19: https://www.gov.uk/government/publications/growing-the-artificial-intelligence-industry-in-the-uk | G19: UK | H19: 15/10/2017 | I19: academia, private sector | K19: "This independent review, carried out by Dame Wendy Hall FRS FREng (Regius Professor of Computer Science, University of Southampton) and Jérôme Pesenti (CEO, BenevelentTech)" | N19: =IF(ISNUMBER(SEARCH(",",I19)),"multistakeholders",lower(I19)) -> multistakeholders | O19: =IF(LOWER(N19)=LOWER(Matthieu!M19),1,0) -> 0 | P19: =IF(LOWER(N19)=LOWER(Maria!L19),1,0) -> 1 | Q19: =IF(LOWER(N19)=LOWER(Kappa!Y21),1,0) -> 0
A20: AI Now 2017 Report | B20: AI Now Institute | C20: https://ainowinstitute.org/wp-content/uploads/2023/04/AI_Now_2017_Report.pdf | G20: USA | H20: 2017 | I20: academia | N20: =IF(ISNUMBER(SEARCH(",",I20)),"multistakeholders",lower(I20)) -> academia | O20: =IF(LOWER(N20)=LOWER(Matthieu!M20),1,0) -> 0 | P20: =IF(LOWER(N20)=LOWER(Maria!L20),1,0) -> 0 | Q20: =IF(LOWER(N20)=LOWER(Kappa!Y22),1,0) -> 0
A21: Algorithms in Decision Making | B21: Parliament Science and Technology Committee (United Kingdom) | C21: https://publications.parliament.uk/pa/cm201719/cmselect/cmsctech/351/351.pdf | G21: UK | H21: 23/05/2018 | I21: national authority | N21: =IF(ISNUMBER(SEARCH(",",I21)),"multistakeholders",lower(I21)) -> national authority | O21: =IF(LOWER(N21)=LOWER(Matthieu!M21),1,0) -> 1 | P21: =IF(LOWER(N21)=LOWER(Maria!L21),1,0) -> 0 | Q21: =IF(LOWER(N21)=LOWER(Kappa!Y23),1,0) -> 1
A22: Thematic Reviews on 'Social Aspects of Digitalisation' (SPC) and 'Digitalisation and Robotisation of Work' (EMCO) - Endorsement of the joint key messages, 14411/18 | B22: Council of the European Union | C22: http://data.consilium.europa.eu/doc/document/ST-14411-2018-INIT/en/pdf | G22: EU | H22: 19/11/2018 | I22: international organisation | N22: =IF(ISNUMBER(SEARCH(",",I22)),"multistakeholders",lower(I22)) -> international organisation | O22: =IF(LOWER(N22)=LOWER(Matthieu!M22),1,0) -> 1 | P22: =IF(LOWER(N22)=LOWER(Maria!L22),1,0) -> 1 | Q22: =IF(LOWER(N22)=LOWER(Kappa!Y24),1,0) -> 1
A23: Standards for AI Governance: International Standards to Enable Global Coordination in AI Research & Development | B23: Future of Humanity Institute, University of Oxford | C23: https://www.fhi.ox.ac.uk/wp-content/uploads/Standards_-FHI-Technical-Report.pdf | G23: international | H23: 04/2019 | I23: academia, civil society | K23: centre for governance of AI = civil society, future of humanity institute = academia | N23: =IF(ISNUMBER(SEARCH(",",I23)),"multistakeholders",lower(I23)) -> multistakeholders | O23: =IF(LOWER(N23)=LOWER(Matthieu!M23),1,0) -> 0 | P23: =IF(LOWER(N23)=LOWER(Maria!L23),1,0) -> 1 | Q23: =IF(LOWER(N23)=LOWER(Kappa!Y25),1,0) -> 0
A24: Preparing the future of AI | B24: National Science and Technology Council (US) | C24: https://obamawhitehouse.archives.gov/sites/default/files/whitehouse_files/microsites/ostp/NSTC/preparing_for_the_future_of_ai.pdf | G24: USA | H24: 10/2016 | I24: national authority | N24: =IF(ISNUMBER(SEARCH(",",I24)),"multistakeholders",lower(I24)) -> national authority | O24: =IF(LOWER(N24)=LOWER(Matthieu!M24),1,0) -> 1 | P24: =IF(LOWER(N24)=LOWER(Maria!L24),1,0) -> 1 | Q24: =IF(LOWER(N24)=LOWER(Kappa!Y26),1,0) -> 1
A25: AI Now Report 2016. The Social and Economic Implications of Artificial Intelligence Technologies in the Near-Term | B25: AI Now Institute | C25: https://assets.ctfassets.net/8wprhhvnpfc0/3JOy5k4f1YSCQOi8MCCmA2/97010d04fbc7892662ce8b2469dc1601/AI_Now_2016_Report.pdf | G25: USA | H25: 22/09/2016 | I25: national authority, academia, private sector | J25: VERY UNSURE | K25: I understood "AI Now" as a research institute within academia and here it is described as a series of events organized by the government (and including people from academia and industry) | N25: =IF(ISNUMBER(SEARCH(",",I25)),"multistakeholders",lower(I25)) -> multistakeholders | O25: =IF(LOWER(N25)=LOWER(Matthieu!M25),1,0) -> 1 | P25: =IF(LOWER(N25)=LOWER(Maria!L25),1,0) -> 1 | Q25: =IF(LOWER(N25)=LOWER(Kappa!Y27),1,0) -> 0
A26: G20 AI Principles | B26: Ministry of Internal Affairs and Communications | C26: https://www.mofa.go.jp/policy/economy/g20_summit/osaka19/pdf/documents/en/annex_08.pdf | G26: Japan | H26: 2019 | I26: international organisation | N26: =IF(ISNUMBER(SEARCH(",",I26)),"multistakeholders",lower(I26)) -> international organisation | O26: =IF(LOWER(N26)=LOWER(Matthieu!M26),1,0) -> 0 | P26: =IF(LOWER(N26)=LOWER(Maria!L26),1,0) -> 1 | Q26: =IF(LOWER(N26)=LOWER(Kappa!Y28),1,0) -> 0
A27: Principles for the Governance of AI | B27: The Future Society Science Law and Society (SLS) Initiative | C27: https://thefuturesociety.org/principles-law-and-society-initiative/ | G27: USA | H27: 15/07/2017 | I27: civil society | N27: =IF(ISNUMBER(SEARCH(",",I27)),"multistakeholders",lower(I27)) -> civil society | O27: =IF(LOWER(N27)=LOWER(Matthieu!M27),1,0) -> 1 | P27: =IF(LOWER(N27)=LOWER(Maria!L27),1,0) -> 1 | Q27: =IF(LOWER(N27)=LOWER(Kappa!Y29),1,0) -> 1
A28: 4 Steps to developing Responsible AI | B28: World Economic Forum (WEF) | C28: https://www.weforum.org/agenda/2019/06/4-steps-to-developing-responsible-ai/ | G28: international | H28: 20/06/2019 | I28: civil society | N28: =IF(ISNUMBER(SEARCH(",",I28)),"multistakeholders",lower(I28)) -> civil society | O28: =IF(LOWER(N28)=LOWER(Matthieu!M28),1,0) -> 0 | P28: =IF(LOWER(N28)=LOWER(Maria!L28),1,0) -> 0 | Q28: =IF(LOWER(N28)=LOWER(Kappa!Y30),1,0) -> 1
A29: Opinion on AI - The consequences of artificial intelligence on the (digital) single market, production, consumption, employment and society’ | B29: European Economic and Social Committee (EESC) | C29: https://eur-lex.europa.eu/legal-content/EN/TXT/PDF/?uri=CELEX:52016IE5369&from=EN | G29: international | H29: 31/08/2017 | I29: international organisation | N29: =IF(ISNUMBER(SEARCH(",",I29)),"multistakeholders",lower(I29)) -> international organisation | O29: =IF(LOWER(N29)=LOWER(Matthieu!M29),1,0) -> 1 | P29: =IF(LOWER(N29)=LOWER(Maria!L29),1,0) -> 0 | Q29: =IF(LOWER(N29)=LOWER(Kappa!Y31),1,0) -> 1
A30: Human Rights Impact Assessments for AI: Analysis and Recommendations | B30: AccessNow | C30: https://www.accessnow.org/cms/assets/uploads/2022/11/Access-Now-Version-Human-Rights-Implications-of-Algorithmic-Impact-Assessments_-Priority-Recommendations-to-Guide-Effective-Development-and-Use.pdf | G30: USA | H30: 10/2022 | I30: civil society | N30: =IF(ISNUMBER(SEARCH(",",I30)),"multistakeholders",lower(I30)) -> civil society | O30: =IF(LOWER(N30)=LOWER(Matthieu!M30),1,0) -> 0 | P30: =IF(LOWER(N30)=LOWER(Maria!L30),1,0) -> 0 | Q30: =IF(LOWER(N30)=LOWER(Kappa!Y32),1,0) -> 1
A31: Report on Artificial intelligence in health care: medical, legal and ethical challenges ahead | B31: Council of Europe (Parliamentary Assembly) | C31: https://pace.coe.int/files/28737/pdf | G31: EU | H31: 01/10/2020 | I31: international organisation | N31: =IF(ISNUMBER(SEARCH(",",I31)),"multistakeholders",lower(I31)) -> international organisation | O31: =IF(LOWER(N31)=LOWER(Matthieu!M31),1,0) -> 1 | P31: =IF(LOWER(N31)=LOWER(Maria!L31),1,0) -> 1 | Q31: =IF(LOWER(N31)=LOWER(Kappa!Y33),1,0) -> 1
A32: Recomendations on the inclusion subSaharan Africa in Global AI Ethics | B32: Research ICT Africa | C32: https://researchictafrica.net/ranitp2019-2-ai-ethics/ | G32: South Africa | H32: 02/2019 | I32: civil society | N32: =IF(ISNUMBER(SEARCH(",",I32)),"multistakeholders",lower(I32)) -> civil society | O32: =IF(LOWER(N32)=LOWER(Matthieu!M32),1,0) -> 0 | P32: =IF(LOWER(N32)=LOWER(Maria!L32),1,0) -> 0 | Q32: =IF(LOWER(N32)=LOWER(Kappa!Y34),1,0) -> 1
A33: Our principles | B33: Google | C33: https://blog.google/technology/ai/ai-principles/ | D33: . | E33: . | G33: USA | H33: 2018 | I33: private sector | N33: =IF(ISNUMBER(SEARCH(",",I33)),"multistakeholders",lower(I33)) -> private sector | O33: =IF(LOWER(N33)=LOWER(Matthieu!M33),1,0) -> 1 | P33: =IF(LOWER(N33)=LOWER(Maria!L33),1,0) -> 1 | Q33: =IF(LOWER(N33)=LOWER(Kappa!Y35),1,0) -> 1
A34: Unfairness by algorithm: Distilling the Harms of automated decision making | B34: Future of Privacy Forum | C34: https://fpf.org/wp-content/uploads/2017/12/FPF-Automated-Decision-Making-Harms-and-Mitigation-Charts.pdf | G34: USA | H34: 12/2017 | I34: civil society | N34: =IF(ISNUMBER(SEARCH(",",I34)),"multistakeholders",lower(I34)) -> civil society | O34: =IF(LOWER(N34)=LOWER(Matthieu!M34),1,0) -> 1 | P34: =IF(LOWER(N34)=LOWER(Maria!L34),1,0) -> 1 | Q34: =IF(LOWER(N34)=LOWER(Kappa!Y36),1,0) -> 1
A35: Automated Decision-Making Under the GDPR: Practical Cases from Courts and Data Protection Authorities | B35: Future of Privacy Forum | C35: https://fpf.org/wp-content/uploads/2022/05/FPF-ADM-Report-R2-singles.pdf | G35: USA | H35: 05/2022 | I35: civil society | N35: =IF(ISNUMBER(SEARCH(",",I35)),"multistakeholders",lower(I35)) -> civil society | O35: =IF(LOWER(N35)=LOWER(Matthieu!M35),1,0) -> 1 | P35: =IF(LOWER(N35)=LOWER(Maria!L35),1,0) -> 1 | Q35: =IF(LOWER(N35)=LOWER(Kappa!Y37),1,0) -> 1
A36: Big Data and AI Principles in Engineering | B36: World Federation of Engineering Organizations (WEFO) | C36: http://www.wfeo.org/big-data-and-ai-principles-in-engineering/ | G36: France | H36: 2020 | I36: civil society, international organisation | K36: "On March, 4th 1968, representatives of 50 scientific and technical associations from all over the world met under the auspices of the United Nations Educational, Scientific and Cultural Organization (UNESCO) in Paris to establish the World Federation of Engineering Organizations (WFEO), whose charter as an international, non-governmental organisation is to unite multidisciplinary engineering associations throughout the world." | N36: =IF(ISNUMBER(SEARCH(",",I36)),"multistakeholders",lower(I36)) -> multistakeholders | O36: =IF(LOWER(N36)=LOWER(Matthieu!M36),1,0) -> 0 | P36: =IF(LOWER(N36)=LOWER(Maria!L36),1,0) -> 1 | Q36: =IF(LOWER(N36)=LOWER(Kappa!Y38),1,0) -> 0
A37: RFI for AI Services | B37: TBS Canada | C37: https://buyandsell.gc.ca/cds/public/2018/06/28/05baa93c08b6f2d3000855170f831066/ABES.PROD.PW__EE.B017.E33657.EBSU000.PDF | G37: Canada | H37: 28/06/2018 | I37: national authority | K37: (notes) RFI=request for information, TBS=Treasury Board of Canada Secretariat, link outdated | N37: =IF(ISNUMBER(SEARCH(",",I37)),"multistakeholders",lower(I37)) -> national authority | O37: =IF(LOWER(N37)=LOWER(Matthieu!M37),1,0) -> 1 | P37: =IF(LOWER(N37)=LOWER(Maria!L37),1,0) -> 1 | Q37: =IF(LOWER(N37)=LOWER(Kappa!Y39),1,0) -> 1
A38: Beyond pilots: sustainable implementation of AI in public services | B38: European Commission (Joint Research Centre, AI Watch) | C38: https://publications.jrc.ec.europa.eu/repository/bitstream/JRC126665/jrc126665_sustainable_implementation_of_ai_in_public_services_technical-report_v2.pdf | G38: EU | H38: 2021 | I38: international organisation, civil society | K38: European comission + JRC ("Scientists at the Joint Research Centre (JRC) carry out research in various fields to provide independent advice to EU policymakers and put science at the heart of European policies.") | N38: =IF(ISNUMBER(SEARCH(",",I38)),"multistakeholders",lower(I38)) -> multistakeholders | O38: =IF(LOWER(N38)=LOWER(Matthieu!M38),1,0) -> 0 | P38: =IF(LOWER(N38)=LOWER(Maria!L38),1,0) -> 1 | Q38: =IF(LOWER(N38)=LOWER(Kappa!Y40),1,0) -> 0
A39: Open letter: Civil society call for the introduction of red lines in the upcoming European Commission proposal on Artificial Intelligence | B39: European Digital Rights (EDRi) | C39: https://edri.org/wp-content/uploads/2021/01/EDRi-open-letter-AI-red-lines.pdf | G39: Belgium | H39: 12/01/2021 | I39: civil society | N39: =IF(ISNUMBER(SEARCH(",",I39)),"multistakeholders",lower(I39)) -> civil society | O39: =IF(LOWER(N39)=LOWER(Matthieu!M39),1,0) -> 1 | P39: =IF(LOWER(N39)=LOWER(Maria!L39),1,0) -> 0 | Q39: =IF(LOWER(N39)=LOWER(Kappa!Y41),1,0) -> 1
A40: Governance Principles for a New Generation of Artificial Intelligence: Develop Responsible Artificial Intelligence | B40: National New Generation Artificial Intelligence Governance Expert Committee | C40: https://www.newamerica.org/cybersecurity-initiative/digichina/blog/translation-chinese-expert-group-offers-governance-principles-responsible-ai/ | G40: China | H40: 2019 | I40: national authority | N40: =IF(ISNUMBER(SEARCH(",",I40)),"multistakeholders",lower(I40)) -> national authority | O40: =IF(LOWER(N40)=LOWER(Matthieu!M40),1,0) -> 1 | P40: =IF(LOWER(N40)=LOWER(Maria!L40),1,0) -> 0 | Q40: =IF(LOWER(N40)=LOWER(Kappa!Y42),1,0) -> 1
A41: Principles for Responsible AI | B41: Women leading in AI | C41: https://womenleadinginai.org/wp-content/uploads/2019/02/WLiAI-Report-2019.pdf | D41: Ivana Bartoletti,Allison Gardner,Reema Patel,Emma Gibson,Liz Stocks,Samara Banno,Sanya Sheikh,Rebecca Geach,Holly Rafique | G41: UK | H41: 2019 | I41: civil society | N41: =IF(ISNUMBER(SEARCH(",",I41)),"multistakeholders",lower(I41)) -> civil society | O41: =IF(LOWER(N41)=LOWER(Matthieu!M41),1,0) -> 1 | P41: =IF(LOWER(N41)=LOWER(Maria!L41),1,0) -> 1 | Q41: =IF(LOWER(N41)=LOWER(Kappa!Y43),1,0) -> 1
A42: Report with recommendations to the Commission on a framework of ethical aspects of artificial intelligence, robotics and related technologies | B42: European Parliament | C42: https://www.europarl.europa.eu/doceo/document/A-9-2020-0186_EN.pdf | G42: EU | H42: 08/10/2020 | I42: international organisation | N42: =IF(ISNUMBER(SEARCH(",",I42)),"multistakeholders",lower(I42)) -> international organisation | O42: =IF(LOWER(N42)=LOWER(Matthieu!M42),1,0) -> 1 | P42: =IF(LOWER(N42)=LOWER(Maria!L42),1,0) -> 1 | Q42: =IF(LOWER(N42)=LOWER(Kappa!Y44),1,0) -> 1
A43: Responsible AI Policy Framework | B43: ITechLaw | C43: https://www.itechlaw.org/publication/responsible-ai-2021-update/ | G43: USA | H43: 2021 | I43: civil society | N43: =IF(ISNUMBER(SEARCH(",",I43)),"multistakeholders",lower(I43)) -> civil society | O43: =IF(LOWER(N43)=LOWER(Matthieu!M43),1,0) -> 1 | P43: =IF(LOWER(N43)=LOWER(Maria!L43),1,0) -> 1 | Q43: =IF(LOWER(N43)=LOWER(Kappa!Y45),1,0) -> 1
A44: Four Principles of Explainable Artificial Intelligence | B44: National Institute of Standards and Technology (NIST) (US) | C44: https://nvlpubs.nist.gov/nistpubs/ir/2021/NIST.IR.8312.pdf | G44: USA | H44: 09/2021 | I44: national authority | N44: =IF(ISNUMBER(SEARCH(",",I44)),"multistakeholders",lower(I44)) -> national authority | O44: =IF(LOWER(N44)=LOWER(Matthieu!M44),1,0) -> 1 | P44: =IF(LOWER(N44)=LOWER(Maria!L44),1,0) -> 1 | Q44: =IF(LOWER(N44)=LOWER(Kappa!Y46),1,0) -> 1
A45: The right to privacy in the digital age | B45: United Nations (OHCHR) | C45: https://www.ohchr.org/en/calls-for-input/2021/right-privacy-digital-age-report-2021 | G45: international | H45: 15/09/2021 | I45: international organisation | N45: =IF(ISNUMBER(SEARCH(",",I45)),"multistakeholders",lower(I45)) -> international organisation | O45: =IF(LOWER(N45)=LOWER(Matthieu!M45),1,0) -> 1 | P45: =IF(LOWER(N45)=LOWER(Maria!L45),1,0) -> 1 | Q45: =IF(LOWER(N45)=LOWER(Kappa!Y47),1,0) -> 1

Sheet Tiphaine
A1: Title | B1: Institution | C1: URL | G1: Country | H1: Date | I1: Sector
A2: AI Index 2022 | B2: University of Stanford, SRI International, MIT, OpenAI, McKinsey Global Institute, Partnership on AI, Harvard University | C2: https://hai.stanford.edu/assets/files/hai_ai_index_report_2025.pdf | G2: USA | H2: 2025 | I2: academia, multistakeholder
A3: 2030 Digital Compass: the European way for the Digital Decade | B3: European Commission | C3: https://eur-lex.europa.eu/resource.html?uri=cellar:12e835e2-81af-11eb-9ac9-01aa75ed71a1.0001.02/DOC_1&format=PDF | G3: international | H3: 09/03/2021 | I3: international organisation
A4: Global competition and convergence of AI Law | B4: Vrije Universiteit Brussel | C4: https://osf.io/preprints/socarxiv/j36ke/ | G4: Belgium | H4: 2021 | I4: academia
A5: Technology rules? The advent of new technologies in the justice system | B5: House of Lords, Justice and Home affairs Committee (United Kingdom) | C5: https://publications.parliament.uk/pa/ld5802/ldselect/ldjusthom/180/180.pdf | G5: UK | H5: 30/03/2022 | I5: national authority
A6: Algorithmic discrimination in Europe: Challenges and opportunities for gender equality and non-discrimination law | B6: European Commission (European network of legal experts in gender equality and non-discrimination) | C6: https://op.europa.eu/en/publication-detail/-/publication/082f1dbc-821d-11eb-9ac9-01aa75ed71a1 | G6: EU | H6: 10/2020 | I6: international organisation
A7: AI Index 2019 | B7: University of Stanford, SRI International, MIT, OpenAI, McKinsey Global Institute, Partnership on AI, Harvard University | C7: https://hai.stanford.edu/sites/default/files/ai_index_2019_report.pdf | G7: USA | H7: 2019 | I7: academia
A8: Artificial intelligence and the control of COVID-19 | B8: Council of Europe | C8: https://www.coe.int/en/web/artificial-intelligence/ai-and-control-of-covid-19-coronavirus | G8: EU | H8: 2020 | I8: international organisation
A9: Unified Ethical Frame for Big Data Analysis. IAF Big Data Ethics Initiative, Part A | B9: The Information Accountability Foundation | C9: https://bigdata.fpf.org/wp-content/uploads/2015/11/IAF-Unified-Ethical-Frame-for-Big-Data-Analysis.pdf | G9: UK | H9: 03/2015 | I9: multistakeholders
A10: Artificial Intelligence | B10: Samsung Research | C10: https://research.samsung.com/artificial-intelligence | G10: South Korea | I10: industry
A11: The EURON Roboethics Roadmap | B11: The European Robotics Research Network (EURON) | C11: http://www.roboethics.org/index_file/Roboethics%20Roadmap%20Rel.1.2.pdf | G11: EU | H11: 01/2007 | I11: academia
A12: Understanding Artificial Intelligence and Safety - A guide for the responsible design and implementation of AI systems in the public sector | B12: The Alan Turing Institute | C12: https://www.turing.ac.uk/sites/default/files/2019-06/understanding_artificial_intelligence_ethics_and_safety.pdf | G12: UK | H12: 2019 | I12: academia
A13: Digital Ethics: A guide for professionals of the Digital Age | B13: CIGREF/Syntec Numérique | C13: https://www.cigref.fr/wp/wp-content/uploads/2019/02/Cigref-Syntec-Digital-Ethics-Guide-for-Professionals-of-Digital-Age-2018-October-EN.pdf | G13: France | H13: 10/2018 | I13: private sector
A14: Human Rights, Democracy, and the Rule of Law Assurance Framework for AI Systems: A proposal prepared for the Council of Europe’s Ad hoc Committee on Artificial Intelligence | B14: The Alan Turing Institute | C14: https://rm.coe.int/huderaf-coe-final-1-2752-6741-5300-v-1/1680a3f688 | G14: UK | H14: 2021 | I14: academia
A15: Study on AI Governance by Human Rights-Centred Design, Deliberation and Oversight | B15: University of Birmingham | C15: https://papers.ssrn.com/sol3/papers.cfm?abstract_id=3435011 | G15: UK | H15: 09/08/2019 | I15: academia
A16: European ethical Charter on the use of Artificial Intelligence in judicial systems and their environment | B16: Council of Europe: European Commission for the efficiency of Justice (CEPEJ) | C16: https://rm.coe.int/ethical-charter-en-for-publication-4-december-2018/16808f699c | G16: EU | H16: 04/12/2018 | I16: international organisation
A17: The Road to a Human-Centred Digital Society | B17: Centre on AI Technology for Humanking (AiTH) at NUS Business School | C17: https://drive.google.com/uc?export=download&id=1aRyqczni56ONA9PVExt2DrrJ1ATGKSu0 | D17: David De Cremer, Devesh Narayanan, Andreas Deppeler, Mahak Nagpal, Jack McGuire, Jess Zhang | E17: National University of Singapore | G17: Singapore | H17: 12/2021
A18: AI Roadmap | B18: AI Council (United Kingdom) | C18: https://assets.publishing.service.gov.uk/media/5ff3bc6e8fa8f53b76ccee23/AI_Council_AI_Roadmap.pdf | G18: UK | H18: 01/2021 | I18: national authority
A19: Growing the artificial intelligence industry in the UK | B19: Department for Digital, Culture, Media & Sport and Department for Business, Energy & Industrial Strategy (United Kingdom) | C19: https://www.gov.uk/government/publications/growing-the-artificial-intelligence-industry-in-the-uk | G19: UK | H19: 15/10/2017
A20: AI Now 2017 Report | B20: AI Now Institute | C20: https://ainowinstitute.org/wp-content/uploads/2023/04/AI_Now_2017_Report.pdf | G20: USA | H20: 2017
A21: Algorithms in Decision Making | B21: Parliament Science and Technology Committee (United Kingdom) | C21: https://publications.parliament.uk/pa/cm201719/cmselect/cmsctech/351/351.pdf | G21: UK | H21: 23/05/2018
A22: Thematic Reviews on 'Social Aspects of Digitalisation' (SPC) and 'Digitalisation and Robotisation of Work' (EMCO) - Endorsement of the joint key messages, 14411/18 | B22: Council of the European Union | C22: http://data.consilium.europa.eu/doc/document/ST-14411-2018-INIT/en/pdf | G22: EU | H22: 19/11/2018 | I22: international organisation
A23: Standards for AI Governance: International Standards to Enable Global Coordination in AI Research & Development | B23: Future of Humanity Institute, University of Oxford | C23: https://www.fhi.ox.ac.uk/wp-content/uploads/Standards_-FHI-Technical-Report.pdf | G23: international | H23: 04/2019
A24: Preparing the future of AI | B24: National Science and Technology Council (US) | C24: https://obamawhitehouse.archives.gov/sites/default/files/whitehouse_files/microsites/ostp/NSTC/preparing_for_the_future_of_ai.pdf | G24: USA | H24: 10/2016
A25: AI Now Report 2016. The Social and Economic Implications of Artificial Intelligence Technologies in the Near-Term | B25: AI Now Institute | C25: https://assets.ctfassets.net/8wprhhvnpfc0/3JOy5k4f1YSCQOi8MCCmA2/97010d04fbc7892662ce8b2469dc1601/AI_Now_2016_Report.pdf | G25: USA | H25: 22/09/2016
A26: G20 AI Principles | B26: Ministry of Internal Affairs and Communications | C26: https://www.mofa.go.jp/policy/economy/g20_summit/osaka19/pdf/documents/en/annex_08.pdf | G26: Japan | H26: 2019
A27: Principles for the Governance of AI | B27: The Future Society Science Law and Society (SLS) Initiative | C27: https://thefuturesociety.org/principles-law-and-society-initiative/ | G27: USA | H27: 15/07/2017
A28: 4 Steps to developing Responsible AI | B28: World Economic Forum (WEF) | C28: https://www.weforum.org/agenda/2019/06/4-steps-to-developing-responsible-ai/ | G28: international | H28: 20/06/2019
A29: Opinion on AI - The consequences of artificial intelligence on the (digital) single market, production, consumption, employment and society’ | B29: European Economic and Social Committee (EESC) | C29: https://eur-lex.europa.eu/legal-content/EN/TXT/PDF/?uri=CELEX:52016IE5369&from=EN | G29: international | H29: 31/08/2017 | I29: international organisation
A30: Human Rights Impact Assessments for AI: Analysis and Recommendations | B30: AccessNow | C30: https://www.accessnow.org/cms/assets/uploads/2022/11/Access-Now-Version-Human-Rights-Implications-of-Algorithmic-Impact-Assessments_-Priority-Recommendations-to-Guide-Effective-Development-and-Use.pdf | G30: USA | H30: 10/2022
A31: Report on Artificial intelligence in health care: medical, legal and ethical challenges ahead | B31: Council of Europe (Parliamentary Assembly) | C31: https://pace.coe.int/files/28737/pdf | G31: EU | H31: 01/10/2020 | I31: international organisation
A32: Recomendations on the inclusion subSaharan Africa in Global AI Ethics | B32: Research ICT Africa | C32: https://researchictafrica.net/ranitp2019-2-ai-ethics/ | G32: South Africa | H32: 02/2019 | I32: civil society
A33: Our principles | B33: Google | C33: https://blog.google/technology/ai/ai-principles/ | D33: . | E33: . | G33: USA | H33: 2018 | I33: industry
A34: Unfairness by algorithm: Distilling the Harms of automated decision making | B34: Future of Privacy Forum | C34: https://fpf.org/wp-content/uploads/2017/12/FPF-Automated-Decision-Making-Harms-and-Mitigation-Charts.pdf | G34: USA | H34: 12/2017 | I34: civil society
A35: Automated Decision-Making Under the GDPR: Practical Cases from Courts and Data Protection Authorities | B35: Future of Privacy Forum | C35: https://fpf.org/wp-content/uploads/2022/05/FPF-ADM-Report-R2-singles.pdf | G35: USA | H35: 05/2022 | I35: civil society
A36: Big Data and AI Principles in Engineering | B36: World Federation of Engineering Organizations (WEFO) | C36: http://www.wfeo.org/big-data-and-ai-principles-in-engineering/ | G36: France | H36: 2020
A37: RFI for AI Services | B37: TBS Canada | C37: https://buyandsell.gc.ca/cds/public/2018/06/28/05baa93c08b6f2d3000855170f831066/ABES.PROD.PW__EE.B017.E33657.EBSU000.PDF | G37: Canada | H37: 28/06/2018
A38: Beyond pilots: sustainable implementation of AI in public services | B38: European Commission (Joint Research Centre, AI Watch) | C38: https://publications.jrc.ec.europa.eu/repository/bitstream/JRC126665/jrc126665_sustainable_implementation_of_ai_in_public_services_technical-report_v2.pdf | G38: EU | H38: 2021 | I38: international organisation
A39: Open letter: Civil society call for the introduction of red lines in the upcoming European Commission proposal on Artificial Intelligence | B39: European Digital Rights (EDRi) | C39: https://edri.org/wp-content/uploads/2021/01/EDRi-open-letter-AI-red-lines.pdf | G39: Belgium | H39: 12/01/2021 | I39: civil society
A40: Governance Principles for a New Generation of Artificial Intelligence: Develop Responsible Artificial Intelligence | B40: National New Generation Artificial Intelligence Governance Expert Committee | C40: https://www.newamerica.org/cybersecurity-initiative/digichina/blog/translation-chinese-expert-group-offers-governance-principles-responsible-ai/ | G40: China | H40: 2019
A41: Principles for Responsible AI | B41: Women leading in AI | C41: https://womenleadinginai.org/wp-content/uploads/2019/02/WLiAI-Report-2019.pdf | D41: Ivana Bartoletti,Allison Gardner,Reema Patel,Emma Gibson,Liz Stocks,Samara Banno,Sanya Sheikh,Rebecca Geach,Holly Rafique | G41: UK | H41: 2019
A42: Report with recommendations to the Commission on a framework of ethical aspects of artificial intelligence, robotics and related technologies | B42: European Parliament | C42: https://www.europarl.europa.eu/doceo/document/A-9-2020-0186_EN.pdf | G42: EU | H42: 08/10/2020 | I42: international organisation
A43: Responsible AI Policy Framework | B43: ITechLaw | C43: https://www.itechlaw.org/publication/responsible-ai-2021-update/ | G43: USA | H43: 2021
A44: Four Principles of Explainable Artificial Intelligence | B44: National Institute of Standards and Technology (NIST) (US) | C44: https://nvlpubs.nist.gov/nistpubs/ir/2021/NIST.IR.8312.pdf | G44: USA | H44: 09/2021 | I44: national authority
A45: The right to privacy in the digital age | B45: United Nations (OHCHR) | C45: https://www.ohchr.org/en/calls-for-input/2021/right-privacy-digital-age-report-2021 | G45: international | H45: 15/09/2021 | I45: international organisation

Sheet Kappa
A1: n annotateurs | B1: 4 | F1: Fleiss Kappa | J1: international organization
A2: n docs | B2: 44 | H2: Matrice M(n,k), avec n le nombre de documents, k le nombre de catégories possibles, dans laquelle M(i,j) correspond au nombre d'annotateurs ayant attribué la catégorie j au doc i. | X2: =IF(ISNUMBER(SEARCH(",",B2)),"multistakeholders",lower(B2)) -> 44
A3: Title | B3: Simon | C3: Matthieu | D3: Maria | E3: Aina | F3: Tiphaine | H3: academia | I3: civil society | J3: international organisation | K3: national authority | L3: private sector | M3: multistakeholders | N3: Accord pour l'item i | X3: =IF(ISNUMBER(SEARCH(",",B3)),"multistakeholders",lower(B3)) -> simon | AB3: COUNTA de
A4: AI Index 2022 | B4: =IF(ISNUMBER(SEARCH(",",VLOOKUP($A4,'List of documents'!A:F,6,0))),"multistakeholders",VLOOKUP($A4,'List of documents'!A:F,6,0)) -> multistakeholders | C4: =IF(ISNUMBER(SEARCH(",",VLOOKUP($A4,Matthieu!$A:$I,9,0))),"multistakeholders",VLOOKUP($A4,Matthieu!$A:$I,9,0)) -> Academia | D4: =IF(ISNUMBER(SEARCH(",",VLOOKUP($A4,Maria!$A:$I,9,0))),"multistakeholders",VLOOKUP($A4,Maria!$A:$I,9,0)) -> academia | E4: =IF(ISNUMBER(SEARCH(",",VLOOKUP($A4,Aina!$A:$I,9,0))),"multistakeholders",VLOOKUP($A4,Aina!$A:$I,9,0)) -> multistakeholders | F4: =IF(ISNUMBER(SEARCH(",",VLOOKUP($A4,Tiphaine!$A:$I,9,0))),"multistakeholders",VLOOKUP($A4,Tiphaine!$A:$I,9,0)) -> multistakeholders | G4: =SUM(H4:M4)=$B$1 -> FALSE | H4: =COUNTIF($B4:$F4,"*"&H$3&"*") -> 2 | I4: =COUNTIF($B4:$F4,"*"&I$3&"*") -> 0 | J4: =COUNTIF($B4:$F4,"*"&J$3&"*") + COUNTIF($B4:$F4,"*"&J$1&"*") -> 0 | K4: =COUNTIF($B4:$F4,"*"&K$3&"*") -> 0 | L4: =COUNTIF($B4:$F4,"*"&L$3&"*") -> 0 | M4: =COUNTIF($B4:$F4,"*"&M$3&"*") -> 3 | N4: =SUMPRODUCT(H4:M4, (H4:M4 - 1)) / ($B$1 * ($B$1-1)) -> 0.66666667 | Q4: accord moyen observé | R4: =AVERAGE(N4:N47) -> 0.96969697 | X4: =IF(ISNUMBER(SEARCH(",",B4)),"multistakeholders",lower(B4)) -> multistakeholders | Y4: =IF(ISNUMBER(SEARCH(">",X4)),LEFT(X4,SEARCH(">",X4)-2),X4) -> multistakeholders | AB4: 0 | AC4: Simon
A5: 2030 Digital Compass: the European way for the Digital Decade | B5: =IF(ISNUMBER(SEARCH(",",VLOOKUP($A5,'List of documents'!A:F,6,0))),"multistakeholders",VLOOKUP($A5,'List of documents'!A:F,6,0)) -> international organisation > EU institution | C5: =IF(ISNUMBER(SEARCH(",",VLOOKUP($A5,Matthieu!$A:$I,9,0))),"multistakeholders",VLOOKUP($A5,Matthieu!$A:$I,9,0)) -> International organisation | D5: =IF(ISNUMBER(SEARCH(",",VLOOKUP($A5,Maria!$A:$I,9,0))),"multistakeholders",VLOOKUP($A5,Maria!$A:$I,9,0)) -> international organisation | E5: =IF(ISNUMBER(SEARCH(",",VLOOKUP($A5,Aina!$A:$I,9,0))),"multistakeholders",VLOOKUP($A5,Aina!$A:$I,9,0)) -> international organisation | F5: =IF(ISNUMBER(SEARCH(",",VLOOKUP($A5,Tiphaine!$A:$I,9,0))),"multistakeholders",VLOOKUP($A5,Tiphaine!$A:$I,9,0)) -> international organisation | G5: =SUM(H5:M5)=$B$1 -> FALSE | H5: =COUNTIF($B5:$F5,"*"&H$3&"*") -> 0 | I5: =COUNTIF($B5:$F5,"*"&I$3&"*") -> 0 | J5: =COUNTIF($B5:$F5,"*"&J$3&"*") + COUNTIF($B5:$F5,"*"&J$1&"*") -> 5 | K5: =COUNTIF($B5:$F5,"*"&K$3&"*") -> 0 | L5: =COUNTIF($B5:$F5,"*"&L$3&"*") -> 0 | M5: =COUNTIF($B5:$F5,"*"&M$3&"*") -> 0 | N5: =SUMPRODUCT(H5:M5, (H5:M5 - 1)) / ($B$1 * ($B$1-1)) -> 1.6666667 | Q5: accord attendu | R5: =SUMPRODUCT(H49:M49,H49:M49) -> 0.24683626 | X5: =IF(ISNUMBER(SEARCH(",",B5)),"multistakeholders",lower(B5)) -> international organisation > eu institution | Y5: =IF(ISNUMBER(SEARCH(">",X5)),LEFT(X5,SEARCH(">",X5)-2),X5) -> international organisation | AA5: academia | AB5: 5 | AC5: =AB5/$AB$11 -> 0.11363636
A6: Global competition and convergence of AI Law | B6: =IF(ISNUMBER(SEARCH(",",VLOOKUP($A6,'List of documents'!A:F,6,0))),"multistakeholders",VLOOKUP($A6,'List of documents'!A:F,6,0)) -> academia | C6: =IF(ISNUMBER(SEARCH(",",VLOOKUP($A6,Matthieu!$A:$I,9,0))),"multistakeholders",VLOOKUP($A6,Matthieu!$A:$I,9,0)) -> Academia | D6: =IF(ISNUMBER(SEARCH(",",VLOOKUP($A6,Maria!$A:$I,9,0))),"multistakeholders",VLOOKUP($A6,Maria!$A:$I,9,0)) -> academia | E6: =IF(ISNUMBER(SEARCH(",",VLOOKUP($A6,Aina!$A:$I,9,0))),"multistakeholders",VLOOKUP($A6,Aina!$A:$I,9,0)) -> academia | F6: =IF(ISNUMBER(SEARCH(",",VLOOKUP($A6,Tiphaine!$A:$I,9,0))),"multistakeholders",VLOOKUP($A6,Tiphaine!$A:$I,9,0)) -> academia | G6: =SUM(H6:M6)=$B$1 -> FALSE | H6: =COUNTIF($B6:$F6,"*"&H$3&"*") -> 5 | I6: =COUNTIF($B6:$F6,"*"&I$3&"*") -> 0 | J6: =COUNTIF($B6:$F6,"*"&J$3&"*") + COUNTIF($B6:$F6,"*"&J$1&"*") -> 0 | K6: =COUNTIF($B6:$F6,"*"&K$3&"*") -> 0 | L6: =COUNTIF($B6:$F6,"*"&L$3&"*") -> 0 | M6: =COUNTIF($B6:$F6,"*"&M$3&"*") -> 0 | N6: =SUMPRODUCT(H6:M6, (H6:M6 - 1)) / ($B$1 * ($B$1-1)) -> 1.6666667 | X6: =IF(ISNUMBER(SEARCH(",",B6)),"multistakeholders",lower(B6)) -> academia | Y6: =IF(ISNUMBER(SEARCH(">",X6)),LEFT(X6,SEARCH(">",X6)-2),X6) -> academia | AA6: civil society | AB6: 13 | AC6: =AB6/$AB$11 -> 0.29545455
A7: Technology rules? The advent of new technologies in the justice system | B7: =IF(ISNUMBER(SEARCH(",",VLOOKUP($A7,'List of documents'!A:F,6,0))),"multistakeholders",VLOOKUP($A7,'List of documents'!A:F,6,0)) -> national authority | C7: =IF(ISNUMBER(SEARCH(",",VLOOKUP($A7,Matthieu!$A:$I,9,0))),"multistakeholders",VLOOKUP($A7,Matthieu!$A:$I,9,0)) -> National authority | D7: =IF(ISNUMBER(SEARCH(",",VLOOKUP($A7,Maria!$A:$I,9,0))),"multistakeholders",VLOOKUP($A7,Maria!$A:$I,9,0)) -> national authority | E7: =IF(ISNUMBER(SEARCH(",",VLOOKUP($A7,Aina!$A:$I,9,0))),"multistakeholders",VLOOKUP($A7,Aina!$A:$I,9,0)) -> national authority | F7: =IF(ISNUMBER(SEARCH(",",VLOOKUP($A7,Tiphaine!$A:$I,9,0))),"multistakeholders",VLOOKUP($A7,Tiphaine!$A:$I,9,0)) -> national authority | G7: =SUM(H7:M7)=$B$1 -> FALSE | H7: =COUNTIF($B7:$F7,"*"&H$3&"*") -> 0 | I7: =COUNTIF($B7:$F7,"*"&I$3&"*") -> 0 | J7: =COUNTIF($B7:$F7,"*"&J$3&"*") + COUNTIF($B7:$F7,"*"&J$1&"*") -> 0 | K7: =COUNTIF($B7:$F7,"*"&K$3&"*") -> 5 | L7: =COUNTIF($B7:$F7,"*"&L$3&"*") -> 0 | M7: =COUNTIF($B7:$F7,"*"&M$3&"*") -> 0 | N7: =SUMPRODUCT(H7:M7, (H7:M7 - 1)) / ($B$1 * ($B$1-1)) -> 1.6666667 | Q7: Kappa | R7: =(R4-R5) / (1-R5) -> 0.95976568 | X7: =IF(ISNUMBER(SEARCH(",",B7)),"multistakeholders",lower(B7)) -> national authority | Y7: =IF(ISNUMBER(SEARCH(">",X7)),LEFT(X7,SEARCH(">",X7)-2),X7) -> national authority | AA7: international organisation | AB7: 11 | AC7: =AB7/$AB$11 -> 0.25
A8: Algorithmic discrimination in Europe: Challenges and opportunities for gender equality and non-discrimination law | B8: =IF(ISNUMBER(SEARCH(",",VLOOKUP($A8,'List of documents'!A:F,6,0))),"multistakeholders",VLOOKUP($A8,'List of documents'!A:F,6,0)) -> international organisation > EU institution | C8: =IF(ISNUMBER(SEARCH(",",VLOOKUP($A8,Matthieu!$A:$I,9,0))),"multistakeholders",VLOOKUP($A8,Matthieu!$A:$I,9,0)) -> International organisation | D8: =IF(ISNUMBER(SEARCH(",",VLOOKUP($A8,Maria!$A:$I,9,0))),"multistakeholders",VLOOKUP($A8,Maria!$A:$I,9,0)) -> international organisation | E8: =IF(ISNUMBER(SEARCH(",",VLOOKUP($A8,Aina!$A:$I,9,0))),"multistakeholders",VLOOKUP($A8,Aina!$A:$I,9,0)) -> international organisation | F8: =IF(ISNUMBER(SEARCH(",",VLOOKUP($A8,Tiphaine!$A:$I,9,0))),"multistakeholders",VLOOKUP($A8,Tiphaine!$A:$I,9,0)) -> international organisation | G8: =SUM(H8:M8)=$B$1 -> FALSE | H8: =COUNTIF($B8:$F8,"*"&H$3&"*") -> 0 | I8: =COUNTIF($B8:$F8,"*"&I$3&"*") -> 0 | J8: =COUNTIF($B8:$F8,"*"&J$3&"*") + COUNTIF($B8:$F8,"*"&J$1&"*") -> 5 | K8: =COUNTIF($B8:$F8,"*"&K$3&"*") -> 0 | L8: =COUNTIF($B8:$F8,"*"&L$3&"*") -> 0 | M8: =COUNTIF($B8:$F8,"*"&M$3&"*") -> 0 | N8: =SUMPRODUCT(H8:M8, (H8:M8 - 1)) / ($B$1 * ($B$1-1)) -> 1.6666667 | X8: =IF(ISNUMBER(SEARCH(",",B8)),"multistakeholders",lower(B8)) -> international organisation > eu institution | Y8: =IF(ISNUMBER(SEARCH(">",X8)),LEFT(X8,SEARCH(">",X8)-2),X8) -> international organisation | AA8: multistakeholders | AB8: 4 | AC8: =AB8/$AB$11 -> 0.090909091
A9: AI Index 2019 | B9: =IF(ISNUMBER(SEARCH(",",VLOOKUP($A9,'List of documents'!A:F,6,0))),"multistakeholders",VLOOKUP($A9,'List of documents'!A:F,6,0)) -> multistakeholders | C9: =IF(ISNUMBER(SEARCH(",",VLOOKUP($A9,Matthieu!$A:$I,9,0))),"multistakeholders",VLOOKUP($A9,Matthieu!$A:$I,9,0)) -> Academia | D9: =IF(ISNUMBER(SEARCH(",",VLOOKUP($A9,Maria!$A:$I,9,0))),"multistakeholders",VLOOKUP($A9,Maria!$A:$I,9,0)) -> multistakeholders | E9: =IF(ISNUMBER(SEARCH(",",VLOOKUP($A9,Aina!$A:$I,9,0))),"multistakeholders",VLOOKUP($A9,Aina!$A:$I,9,0)) -> multistakeholders | F9: =IF(ISNUMBER(SEARCH(",",VLOOKUP($A9,Tiphaine!$A:$I,9,0))),"multistakeholders",VLOOKUP($A9,Tiphaine!$A:$I,9,0)) -> academia | G9: =SUM(H9:M9)=$B$1 -> FALSE | H9: =COUNTIF($B9:$F9,"*"&H$3&"*") -> 2 | I9: =COUNTIF($B9:$F9,"*"&I$3&"*") -> 0 | J9: =COUNTIF($B9:$F9,"*"&J$3&"*") + COUNTIF($B9:$F9,"*"&J$1&"*") -> 0 | K9: =COUNTIF($B9:$F9,"*"&K$3&"*") -> 0 | L9: =COUNTIF($B9:$F9,"*"&L$3&"*") -> 0 | M9: =COUNTIF($B9:$F9,"*"&M$3&"*") -> 3 | N9: =SUMPRODUCT(H9:M9, (H9:M9 - 1)) / ($B$1 * ($B$1-1)) -> 0.66666667 | X9: =IF(ISNUMBER(SEARCH(",",B9)),"multistakeholders",lower(B9)) -> multistakeholders | Y9: =IF(ISNUMBER(SEARCH(">",X9)),LEFT(X9,SEARCH(">",X9)-2),X9) -> multistakeholders | AA9: national authority | AB9: 9 | AC9: =AB9/$AB$11 -> 0.20454545
A10: Artificial intelligence and the control of COVID-19 | B10: =IF(ISNUMBER(SEARCH(",",VLOOKUP($A10,'List of documents'!A:F,6,0))),"multistakeholders",VLOOKUP($A10,'List of documents'!A:F,6,0)) -> international organisation > IGO | C10: =IF(ISNUMBER(SEARCH(",",VLOOKUP($A10,Matthieu!$A:$I,9,0))),"multistakeholders",VLOOKUP($A10,Matthieu!$A:$I,9,0)) -> International organisation | D10: =IF(ISNUMBER(SEARCH(",",VLOOKUP($A10,Maria!$A:$I,9,0))),"multistakeholders",VLOOKUP($A10,Maria!$A:$I,9,0)) -> international organisation | E10: =IF(ISNUMBER(SEARCH(",",VLOOKUP($A10,Aina!$A:$I,9,0))),"multistakeholders",VLOOKUP($A10,Aina!$A:$I,9,0)) -> international organisation | F10: =IF(ISNUMBER(SEARCH(",",VLOOKUP($A10,Tiphaine!$A:$I,9,0))),"multistakeholders",VLOOKUP($A10,Tiphaine!$A:$I,9,0)) -> international organisation | G10: =SUM(H10:M10)=$B$1 -> FALSE | H10: =COUNTIF($B10:$F10,"*"&H$3&"*") -> 0 | I10: =COUNTIF($B10:$F10,"*"&I$3&"*") -> 0 | J10: =COUNTIF($B10:$F10,"*"&J$3&"*") + COUNTIF($B10:$F10,"*"&J$1&"*") -> 5 | K10: =COUNTIF($B10:$F10,"*"&K$3&"*") -> 0 | L10: =COUNTIF($B10:$F10,"*"&L$3&"*") -> 0 | M10: =COUNTIF($B10:$F10,"*"&M$3&"*") -> 0 | N10: =SUMPRODUCT(H10:M10, (H10:M10 - 1)) / ($B$1 * ($B$1-1)) -> 1.6666667 | X10: =IF(ISNUMBER(SEARCH(",",B10)),"multistakeholders",lower(B10)) -> international organisation > igo | Y10: =IF(ISNUMBER(SEARCH(">",X10)),LEFT(X10,SEARCH(">",X10)-2),X10) -> international organisation | AA10: private sector | AB10: 2 | AC10: =AB10/$AB$11 -> 0.045454545
A11: Unified Ethical Frame for Big Data Analysis. IAF Big Data Ethics Initiative, Part A | B11: =IF(ISNUMBER(SEARCH(",",VLOOKUP($A11,'List of documents'!A:F,6,0))),"multistakeholders",VLOOKUP($A11,'List of documents'!A:F,6,0)) -> international organisation > IGO | C11: =IF(ISNUMBER(SEARCH(",",VLOOKUP($A11,Matthieu!$A:$I,9,0))),"multistakeholders",VLOOKUP($A11,Matthieu!$A:$I,9,0)) -> multistakeholders | D11: =IF(ISNUMBER(SEARCH(",",VLOOKUP($A11,Maria!$A:$I,9,0))),"multistakeholders",VLOOKUP($A11,Maria!$A:$I,9,0)) -> civil society | E11: =IF(ISNUMBER(SEARCH(",",VLOOKUP($A11,Aina!$A:$I,9,0))),"multistakeholders",VLOOKUP($A11,Aina!$A:$I,9,0)) -> civil society | F11: =IF(ISNUMBER(SEARCH(",",VLOOKUP($A11,Tiphaine!$A:$I,9,0))),"multistakeholders",VLOOKUP($A11,Tiphaine!$A:$I,9,0)) -> multistakeholders | G11: =SUM(H11:M11)=$B$1 -> FALSE | H11: =COUNTIF($B11:$F11,"*"&H$3&"*") -> 0 | I11: =COUNTIF($B11:$F11,"*"&I$3&"*") -> 2 | J11: =COUNTIF($B11:$F11,"*"&J$3&"*") + COUNTIF($B11:$F11,"*"&J$1&"*") -> 1 | K11: =COUNTIF($B11:$F11,"*"&K$3&"*") -> 0 | L11: =COUNTIF($B11:$F11,"*"&L$3&"*") -> 0 | M11: =COUNTIF($B11:$F11,"*"&M$3&"*") -> 2 | N11: =SUMPRODUCT(H11:M11, (H11:M11 - 1)) / ($B$1 * ($B$1-1)) -> 0.33333333 | X11: =IF(ISNUMBER(SEARCH(",",B11)),"multistakeholders",lower(B11)) -> international organisation > igo | Y11: =IF(ISNUMBER(SEARCH(">",X11)),LEFT(X11,SEARCH(">",X11)-2),X11) -> international organisation | AA11: Total général | AB11: 44
A12: Artificial Intelligence | B12: =IF(ISNUMBER(SEARCH(",",VLOOKUP($A12,'List of documents'!A:F,6,0))),"multistakeholders",VLOOKUP($A12,'List of documents'!A:F,6,0)) -> private sector | C12: =IF(ISNUMBER(SEARCH(",",VLOOKUP($A12,Matthieu!$A:$I,9,0))),"multistakeholders",VLOOKUP($A12,Matthieu!$A:$I,9,0)) -> Private sector | D12: =IF(ISNUMBER(SEARCH(",",VLOOKUP($A12,Maria!$A:$I,9,0))),"multistakeholders",VLOOKUP($A12,Maria!$A:$I,9,0)) -> private sector | E12: =IF(ISNUMBER(SEARCH(",",VLOOKUP($A12,Aina!$A:$I,9,0))),"multistakeholders",VLOOKUP($A12,Aina!$A:$I,9,0)) -> private sector | F12: =IF(ISNUMBER(SEARCH(",",VLOOKUP($A12,Tiphaine!$A:$I,9,0))),"multistakeholders",VLOOKUP($A12,Tiphaine!$A:$I,9,0)) -> industry | G12: =SUM(H12:M12)=$B$1 -> TRUE | H12: =COUNTIF($B12:$F12,"*"&H$3&"*") -> 0 | I12: =COUNTIF($B12:$F12,"*"&I$3&"*") -> 0 | J12: =COUNTIF($B12:$F12,"*"&J$3&"*") + COUNTIF($B12:$F12,"*"&J$1&"*") -> 0 | K12: =COUNTIF($B12:$F12,"*"&K$3&"*") -> 0 | L12: =COUNTIF($B12:$F12,"*"&L$3&"*") -> 4 | M12: =COUNTIF($B12:$F12,"*"&M$3&"*") -> 0 | N12: =SUMPRODUCT(H12:M12, (H12:M12 - 1)) / ($B$1 * ($B$1-1)) -> 1 | X12: =IF(ISNUMBER(SEARCH(",",B12)),"multistakeholders",lower(B12)) -> private sector | Y12: =IF(ISNUMBER(SEARCH(">",X12)),LEFT(X12,SEARCH(">",X12)-2),X12) -> private sector
A13: The EURON Roboethics Roadmap | B13: =IF(ISNUMBER(SEARCH(",",VLOOKUP($A13,'List of documents'!A:F,6,0))),"multistakeholders",VLOOKUP($A13,'List of documents'!A:F,6,0)) -> academia | C13: =IF(ISNUMBER(SEARCH(",",VLOOKUP($A13,Matthieu!$A:$I,9,0))),"multistakeholders",VLOOKUP($A13,Matthieu!$A:$I,9,0)) -> multistakeholders | D13: =IF(ISNUMBER(SEARCH(",",VLOOKUP($A13,Maria!$A:$I,9,0))),"multistakeholders",VLOOKUP($A13,Maria!$A:$I,9,0)) -> academia | E13: =IF(ISNUMBER(SEARCH(",",VLOOKUP($A13,Aina!$A:$I,9,0))),"multistakeholders",VLOOKUP($A13,Aina!$A:$I,9,0)) -> academia | F13: =IF(ISNUMBER(SEARCH(",",VLOOKUP($A13,Tiphaine!$A:$I,9,0))),"multistakeholders",VLOOKUP($A13,Tiphaine!$A:$I,9,0)) -> academia | G13: =SUM(H13:M13)=$B$1 -> FALSE | H13: =COUNTIF($B13:$F13,"*"&H$3&"*") -> 4 | I13: =COUNTIF($B13:$F13,"*"&I$3&"*") -> 0 | J13: =COUNTIF($B13:$F13,"*"&J$3&"*") + COUNTIF($B13:$F13,"*"&J$1&"*") -> 0 | K13: =COUNTIF($B13:$F13,"*"&K$3&"*") -> 0 | L13: =COUNTIF($B13:$F13,"*"&L$3&"*") -> 0 | M13: =COUNTIF($B13:$F13,"*"&M$3&"*") -> 1 | N13: =SUMPRODUCT(H13:M13, (H13:M13 - 1)) / ($B$1 * ($B$1-1)) -> 1 | X13: =IF(ISNUMBER(SEARCH(",",B13)),"multistakeholders",lower(B13)) -> academia | Y13: =IF(ISNUMBER(SEARCH(">",X13)),LEFT(X13,SEARCH(">",X13)-2),X13) -> academia
A14: Understanding Artificial Intelligence and Safety - A guide for the responsible design and implementation of AI systems in the public sector | B14: =IF(ISNUMBER(SEARCH(",",VLOOKUP($A14,'List of documents'!A:F,6,0))),"multistakeholders",VLOOKUP($A14,'List of documents'!A:F,6,0)) -> multistakeholders | C14: =IF(ISNUMBER(SEARCH(",",VLOOKUP($A14,Matthieu!$A:$I,9,0))),"multistakeholders",VLOOKUP($A14,Matthieu!$A:$I,9,0)) -> Academia | D14: =IF(ISNUMBER(SEARCH(",",VLOOKUP($A14,Maria!$A:$I,9,0))),"multistakeholders",VLOOKUP($A14,Maria!$A:$I,9,0)) -> multistakeholders | E14: =IF(ISNUMBER(SEARCH(",",VLOOKUP($A14,Aina!$A:$I,9,0))),"multistakeholders",VLOOKUP($A14,Aina!$A:$I,9,0)) -> academia | F14: =IF(ISNUMBER(SEARCH(",",VLOOKUP($A14,Tiphaine!$A:$I,9,0))),"multistakeholders",VLOOKUP($A14,Tiphaine!$A:$I,9,0)) -> academia | G14: =SUM(H14:M14)=$B$1 -> FALSE | H14: =COUNTIF($B14:$F14,"*"&H$3&"*") -> 3 | I14: =COUNTIF($B14:$F14,"*"&I$3&"*") -> 0 | J14: =COUNTIF($B14:$F14,"*"&J$3&"*") + COUNTIF($B14:$F14,"*"&J$1&"*") -> 0 | K14: =COUNTIF($B14:$F14,"*"&K$3&"*") -> 0 | L14: =COUNTIF($B14:$F14,"*"&L$3&"*") -> 0 | M14: =COUNTIF($B14:$F14,"*"&M$3&"*") -> 2 | N14: =SUMPRODUCT(H14:M14, (H14:M14 - 1)) / ($B$1 * ($B$1-1)) -> 0.66666667 | X14: =IF(ISNUMBER(SEARCH(",",B14)),"multistakeholders",lower(B14)) -> multistakeholders | Y14: =IF(ISNUMBER(SEARCH(">",X14)),LEFT(X14,SEARCH(">",X14)-2),X14) -> multistakeholders
A15: Digital Ethics: A guide for professionals of the Digital Age | B15: =IF(ISNUMBER(SEARCH(",",VLOOKUP($A15,'List of documents'!A:F,6,0))),"multistakeholders",VLOOKUP($A15,'List of documents'!A:F,6,0)) -> civil society > other | C15: =IF(ISNUMBER(SEARCH(",",VLOOKUP($A15,Matthieu!$A:$I,9,0))),"multistakeholders",VLOOKUP($A15,Matthieu!$A:$I,9,0)) -> Private sector | D15: =IF(ISNUMBER(SEARCH(",",VLOOKUP($A15,Maria!$A:$I,9,0))),"multistakeholders",VLOOKUP($A15,Maria!$A:$I,9,0)) -> multistakeholders | E15: =IF(ISNUMBER(SEARCH(",",VLOOKUP($A15,Aina!$A:$I,9,0))),"multistakeholders",VLOOKUP($A15,Aina!$A:$I,9,0)) -> multistakeholders | F15: =IF(ISNUMBER(SEARCH(",",VLOOKUP($A15,Tiphaine!$A:$I,9,0))),"multistakeholders",VLOOKUP($A15,Tiphaine!$A:$I,9,0)) -> private sector | G15: =SUM(H15:M15)=$B$1 -> FALSE | H15: =COUNTIF($B15:$F15,"*"&H$3&"*") -> 0 | I15: =COUNTIF($B15:$F15,"*"&I$3&"*") -> 1 | J15: =COUNTIF($B15:$F15,"*"&J$3&"*") + COUNTIF($B15:$F15,"*"&J$1&"*") -> 0 | K15: =COUNTIF($B15:$F15,"*"&K$3&"*") -> 0 | L15: =COUNTIF($B15:$F15,"*"&L$3&"*") -> 2 | M15: =COUNTIF($B15:$F15,"*"&M$3&"*") -> 2 | N15: =SUMPRODUCT(H15:M15, (H15:M15 - 1)) / ($B$1 * ($B$1-1)) -> 0.33333333 | X15: =IF(ISNUMBER(SEARCH(",",B15)),"multistakeholders",lower(B15)) -> civil society > other | Y15: =IF(ISNUMBER(SEARCH(">",X15)),LEFT(X15,SEARCH(">",X15)-2),X15) -> civil society
A16: Human Rights, Democracy, and the Rule of Law Assurance Framework for AI Systems: A proposal prepared for the Council of Europe’s Ad hoc Committee on Artificial Intelligence | B16: =IF(ISNUMBER(SEARCH(",",VLOOKUP($A16,'List of documents'!A:F,6,0))),"multistakeholders",VLOOKUP($A16,'List of documents'!A:F,6,0)) -> multistakeholders | C16: =IF(ISNUMBER(SEARCH(",",VLOOKUP($A16,Matthieu!$A:$I,9,0))),"multistakeholders",VLOOKUP($A16,Matthieu!$A:$I,9,0)) -> Academia | D16: =IF(ISNUMBER(SEARCH(",",VLOOKUP($A16,Maria!$A:$I,9,0))),"multistakeholders",VLOOKUP($A16,Maria!$A:$I,9,0)) -> multistakeholders | E16: =IF(ISNUMBER(SEARCH(",",VLOOKUP($A16,Aina!$A:$I,9,0))),"multistakeholders",VLOOKUP($A16,Aina!$A:$I,9,0)) -> multistakeholders | F16: =IF(ISNUMBER(SEARCH(",",VLOOKUP($A16,Tiphaine!$A:$I,9,0))),"multistakeholders",VLOOKUP($A16,Tiphaine!$A:$I,9,0)) -> academia | G16: =SUM(H16:M16)=$B$1 -> FALSE | H16: =COUNTIF($B16:$F16,"*"&H$3&"*") -> 2 | I16: =COUNTIF($B16:$F16,"*"&I$3&"*") -> 0 | J16: =COUNTIF($B16:$F16,"*"&J$3&"*") + COUNTIF($B16:$F16,"*"&J$1&"*") -> 0 | K16: =COUNTIF($B16:$F16,"*"&K$3&"*") -> 0 | L16: =COUNTIF($B16:$F16,"*"&L$3&"*") -> 0 | M16: =COUNTIF($B16:$F16,"*"&M$3&"*") -> 3 | N16: =SUMPRODUCT(H16:M16, (H16:M16 - 1)) / ($B$1 * ($B$1-1)) -> 0.66666667 | X16: =IF(ISNUMBER(SEARCH(",",B16)),"multistakeholders",lower(B16)) -> multistakeholders | Y16: =IF(ISNUMBER(SEARCH(">",X16)),LEFT(X16,SEARCH(">",X16)-2),X16) -> multistakeholders
A17: Study on AI Governance by Human Rights-Centred Design, Deliberation and Oversight | B17: =IF(ISNUMBER(SEARCH(",",VLOOKUP($A17,'List of documents'!A:F,6,0))),"multistakeholders",VLOOKUP($A17,'List of documents'!A:F,6,0)) -> academia | C17: =IF(ISNUMBER(SEARCH(",",VLOOKUP($A17,Matthieu!$A:$I,9,0))),"multistakeholders",VLOOKUP($A17,Matthieu!$A:$I,9,0)) -> Academia | D17: =IF(ISNUMBER(SEARCH(",",VLOOKUP($A17,Maria!$A:$I,9,0))),"multistakeholders",VLOOKUP($A17,Maria!$A:$I,9,0)) -> academia | E17: =IF(ISNUMBER(SEARCH(",",VLOOKUP($A17,Aina!$A:$I,9,0))),"multistakeholders",VLOOKUP($A17,Aina!$A:$I,9,0)) -> academia | F17: =IF(ISNUMBER(SEARCH(",",VLOOKUP($A17,Tiphaine!$A:$I,9,0))),"multistakeholders",VLOOKUP($A17,Tiphaine!$A:$I,9,0)) -> academia | G17: =SUM(H17:M17)=$B$1 -> FALSE | H17: =COUNTIF($B17:$F17,"*"&H$3&"*") -> 5 | I17: =COUNTIF($B17:$F17,"*"&I$3&"*") -> 0 | J17: =COUNTIF($B17:$F17,"*"&J$3&"*") + COUNTIF($B17:$F17,"*"&J$1&"*") -> 0 | K17: =COUNTIF($B17:$F17,"*"&K$3&"*") -> 0 | L17: =COUNTIF($B17:$F17,"*"&L$3&"*") -> 0 | M17: =COUNTIF($B17:$F17,"*"&M$3&"*") -> 0 | N17: =SUMPRODUCT(H17:M17, (H17:M17 - 1)) / ($B$1 * ($B$1-1)) -> 1.6666667 | X17: =IF(ISNUMBER(SEARCH(",",B17)),"multistakeholders",lower(B17)) -> academia | Y17: =IF(ISNUMBER(SEARCH(">",X17)),LEFT(X17,SEARCH(">",X17)-2),X17) -> academia
A18: European ethical Charter on the use of Artificial Intelligence in judicial systems and their environment | B18: =IF(ISNUMBER(SEARCH(",",VLOOKUP($A18,'List of documents'!A:F,6,0))),"multistakeholders",VLOOKUP($A18,'List of documents'!A:F,6,0)) -> international organisation > IGO | C18: =IF(ISNUMBER(SEARCH(",",VLOOKUP($A18,Matthieu!$A:$I,9,0))),"multistakeholders",VLOOKUP($A18,Matthieu!$A:$I,9,0)) -> International organisation | D18: =IF(ISNUMBER(SEARCH(",",VLOOKUP($A18,Maria!$A:$I,9,0))),"multistakeholders",VLOOKUP($A18,Maria!$A:$I,9,0)) -> international organisation | E18: =IF(ISNUMBER(SEARCH(",",VLOOKUP($A18,Aina!$A:$I,9,0))),"multistakeholders",VLOOKUP($A18,Aina!$A:$I,9,0)) -> international organisation | F18: =IF(ISNUMBER(SEARCH(",",VLOOKUP($A18,Tiphaine!$A:$I,9,0))),"multistakeholders",VLOOKUP($A18,Tiphaine!$A:$I,9,0)) -> international organisation | G18: =SUM(H18:M18)=$B$1 -> FALSE | H18: =COUNTIF($B18:$F18,"*"&H$3&"*") -> 0 | I18: =COUNTIF($B18:$F18,"*"&I$3&"*") -> 0 | J18: =COUNTIF($B18:$F18,"*"&J$3&"*") + COUNTIF($B18:$F18,"*"&J$1&"*") -> 5 | K18: =COUNTIF($B18:$F18,"*"&K$3&"*") -> 0 | L18: =COUNTIF($B18:$F18,"*"&L$3&"*") -> 0 | M18: =COUNTIF($B18:$F18,"*"&M$3&"*") -> 0 | N18: =SUMPRODUCT(H18:M18, (H18:M18 - 1)) / ($B$1 * ($B$1-1)) -> 1.6666667 | Q18: academia | X18: =IF(ISNUMBER(SEARCH(",",B18)),"multistakeholders",lower(B18)) -> international organisation > igo | Y18: =IF(ISNUMBER(SEARCH(">",X18)),LEFT(X18,SEARCH(">",X18)-2),X18) -> international organisation
A19: The Road to a Human-Centred Digital Society | B19: =IF(ISNUMBER(SEARCH(",",VLOOKUP($A19,'List of documents'!A:F,6,0))),"multistakeholders",VLOOKUP($A19,'List of documents'!A:F,6,0)) -> academia | C19: =IF(ISNUMBER(SEARCH(",",VLOOKUP($A19,Matthieu!$A:$I,9,0))),"multistakeholders",VLOOKUP($A19,Matthieu!$A:$I,9,0)) -> Academia | D19: =IF(ISNUMBER(SEARCH(",",VLOOKUP($A19,Maria!$A:$I,9,0))),"multistakeholders",VLOOKUP($A19,Maria!$A:$I,9,0)) -> academia | E19: =IF(ISNUMBER(SEARCH(",",VLOOKUP($A19,Aina!$A:$I,9,0))),"multistakeholders",VLOOKUP($A19,Aina!$A:$I,9,0)) -> academia | F19: =IF(ISNUMBER(SEARCH(",",VLOOKUP($A19,Tiphaine!$A:$I,9,0))),"multistakeholders",VLOOKUP($A19,Tiphaine!$A:$I,9,0)) | G19: =SUM(H19:M19)=$B$1 -> TRUE | H19: =COUNTIF($B19:$F19,"*"&H$3&"*") -> 4 | I19: =COUNTIF($B19:$F19,"*"&I$3&"*") -> 0 | J19: =COUNTIF($B19:$F19,"*"&J$3&"*") + COUNTIF($B19:$F19,"*"&J$1&"*") -> 0 | K19: =COUNTIF($B19:$F19,"*"&K$3&"*") -> 0 | L19: =COUNTIF($B19:$F19,"*"&L$3&"*") -> 0 | M19: =COUNTIF($B19:$F19,"*"&M$3&"*") -> 0 | N19: =SUMPRODUCT(H19:M19, (H19:M19 - 1)) / ($B$1 * ($B$1-1)) -> 1 | Q19: civil society | X19: =IF(ISNUMBER(SEARCH(",",B19)),"multistakeholders",lower(B19)) -> academia | Y19: =IF(ISNUMBER(SEARCH(">",X19)),LEFT(X19,SEARCH(">",X19)-2),X19) -> academia
A20: AI Roadmap | B20: =IF(ISNUMBER(SEARCH(",",VLOOKUP($A20,'List of documents'!A:F,6,0))),"multistakeholders",VLOOKUP($A20,'List of documents'!A:F,6,0)) -> national authority | C20: =IF(ISNUMBER(SEARCH(",",VLOOKUP($A20,Matthieu!$A:$I,9,0))),"multistakeholders",VLOOKUP($A20,Matthieu!$A:$I,9,0)) -> Civil society | D20: =IF(ISNUMBER(SEARCH(",",VLOOKUP($A20,Maria!$A:$I,9,0))),"multistakeholders",VLOOKUP($A20,Maria!$A:$I,9,0)) -> multistakeholders | E20: =IF(ISNUMBER(SEARCH(",",VLOOKUP($A20,Aina!$A:$I,9,0))),"multistakeholders",VLOOKUP($A20,Aina!$A:$I,9,0)) -> civil society | F20: =IF(ISNUMBER(SEARCH(",",VLOOKUP($A20,Tiphaine!$A:$I,9,0))),"multistakeholders",VLOOKUP($A20,Tiphaine!$A:$I,9,0)) -> national authority | G20: =SUM(H20:M20)=$B$1 -> FALSE | H20: =COUNTIF($B20:$F20,"*"&H$3&"*") -> 0 | I20: =COUNTIF($B20:$F20,"*"&I$3&"*") -> 2 | J20: =COUNTIF($B20:$F20,"*"&J$3&"*") + COUNTIF($B20:$F20,"*"&J$1&"*") -> 0 | K20: =COUNTIF($B20:$F20,"*"&K$3&"*") -> 2 | L20: =COUNTIF($B20:$F20,"*"&L$3&"*") -> 0 | M20: =COUNTIF($B20:$F20,"*"&M$3&"*") -> 1 | N20: =SUMPRODUCT(H20:M20, (H20:M20 - 1)) / ($B$1 * ($B$1-1)) -> 0.33333333 | Q20: international organisation | X20: =IF(ISNUMBER(SEARCH(",",B20)),"multistakeholders",lower(B20)) -> national authority | Y20: =IF(ISNUMBER(SEARCH(">",X20)),LEFT(X20,SEARCH(">",X20)-2),X20) -> national authority
A21: Growing the artificial intelligence industry in the UK | B21: =IF(ISNUMBER(SEARCH(",",VLOOKUP($A21,'List of documents'!A:F,6,0))),"multistakeholders",VLOOKUP($A21,'List of documents'!A:F,6,0)) -> national authority | C21: =IF(ISNUMBER(SEARCH(",",VLOOKUP($A21,Matthieu!$A:$I,9,0))),"multistakeholders",VLOOKUP($A21,Matthieu!$A:$I,9,0)) -> National authority | D21: =IF(ISNUMBER(SEARCH(",",VLOOKUP($A21,Maria!$A:$I,9,0))),"multistakeholders",VLOOKUP($A21,Maria!$A:$I,9,0)) -> multistakeholders | E21: =IF(ISNUMBER(SEARCH(",",VLOOKUP($A21,Aina!$A:$I,9,0))),"multistakeholders",VLOOKUP($A21,Aina!$A:$I,9,0)) -> multistakeholders | F21: =IF(ISNUMBER(SEARCH(",",VLOOKUP($A21,Tiphaine!$A:$I,9,0))),"multistakeholders",VLOOKUP($A21,Tiphaine!$A:$I,9,0)) | G21: =SUM(H21:M21)=$B$1 -> TRUE | H21: =COUNTIF($B21:$F21,"*"&H$3&"*") -> 0 | I21: =COUNTIF($B21:$F21,"*"&I$3&"*") -> 0 | J21: =COUNTIF($B21:$F21,"*"&J$3&"*") + COUNTIF($B21:$F21,"*"&J$1&"*") -> 0 | K21: =COUNTIF($B21:$F21,"*"&K$3&"*") -> 2 | L21: =COUNTIF($B21:$F21,"*"&L$3&"*") -> 0 | M21: =COUNTIF($B21:$F21,"*"&M$3&"*") -> 2 | N21: =SUMPRODUCT(H21:M21, (H21:M21 - 1)) / ($B$1 * ($B$1-1)) -> 0.33333333 | Q21: multistakeholders | X21: =IF(ISNUMBER(SEARCH(",",B21)),"multistakeholders",lower(B21)) -> national authority | Y21: =IF(ISNUMBER(SEARCH(">",X21)),LEFT(X21,SEARCH(">",X21)-2),X21) -> national authority
A22: AI Now 2017 Report | B22: =IF(ISNUMBER(SEARCH(",",VLOOKUP($A22,'List of documents'!A:F,6,0))),"multistakeholders",VLOOKUP($A22,'List of documents'!A:F,6,0)) -> civil society > NGO | C22: =IF(ISNUMBER(SEARCH(",",VLOOKUP($A22,Matthieu!$A:$I,9,0))),"multistakeholders",VLOOKUP($A22,Matthieu!$A:$I,9,0)) -> multistakeholders | D22: =IF(ISNUMBER(SEARCH(",",VLOOKUP($A22,Maria!$A:$I,9,0))),"multistakeholders",VLOOKUP($A22,Maria!$A:$I,9,0)) -> multistakeholders | E22: =IF(ISNUMBER(SEARCH(",",VLOOKUP($A22,Aina!$A:$I,9,0))),"multistakeholders",VLOOKUP($A22,Aina!$A:$I,9,0)) -> academia | F22: =IF(ISNUMBER(SEARCH(",",VLOOKUP($A22,Tiphaine!$A:$I,9,0))),"multistakeholders",VLOOKUP($A22,Tiphaine!$A:$I,9,0)) | G22: =SUM(H22:M22)=$B$1 -> TRUE | H22: =COUNTIF($B22:$F22,"*"&H$3&"*") -> 1 | I22: =COUNTIF($B22:$F22,"*"&I$3&"*") -> 1 | J22: =COUNTIF($B22:$F22,"*"&J$3&"*") + COUNTIF($B22:$F22,"*"&J$1&"*") -> 0 | K22: =COUNTIF($B22:$F22,"*"&K$3&"*") -> 0 | L22: =COUNTIF($B22:$F22,"*"&L$3&"*") -> 0 | M22: =COUNTIF($B22:$F22,"*"&M$3&"*") -> 2 | N22: =SUMPRODUCT(H22:M22, (H22:M22 - 1)) / ($B$1 * ($B$1-1)) -> 0.16666667 | Q22: national authority | X22: =IF(ISNUMBER(SEARCH(",",B22)),"multistakeholders",lower(B22)) -> civil society > ngo | Y22: =IF(ISNUMBER(SEARCH(">",X22)),LEFT(X22,SEARCH(">",X22)-2),X22) -> civil society
A23: Algorithms in Decision Making | B23: =IF(ISNUMBER(SEARCH(",",VLOOKUP($A23,'List of documents'!A:F,6,0))),"multistakeholders",VLOOKUP($A23,'List of documents'!A:F,6,0)) -> national authority | C23: =IF(ISNUMBER(SEARCH(",",VLOOKUP($A23,Matthieu!$A:$I,9,0))),"multistakeholders",VLOOKUP($A23,Matthieu!$A:$I,9,0)) -> National authority | D23: =IF(ISNUMBER(SEARCH(",",VLOOKUP($A23,Maria!$A:$I,9,0))),"multistakeholders",VLOOKUP($A23,Maria!$A:$I,9,0)) -> multistakeholders | E23: =IF(ISNUMBER(SEARCH(",",VLOOKUP($A23,Aina!$A:$I,9,0))),"multistakeholders",VLOOKUP($A23,Aina!$A:$I,9,0)) -> national authority | F23: =IF(ISNUMBER(SEARCH(",",VLOOKUP($A23,Tiphaine!$A:$I,9,0))),"multistakeholders",VLOOKUP($A23,Tiphaine!$A:$I,9,0)) | G23: =SUM(H23:M23)=$B$1 -> TRUE | H23: =COUNTIF($B23:$F23,"*"&H$3&"*") -> 0 | I23: =COUNTIF($B23:$F23,"*"&I$3&"*") -> 0 | J23: =COUNTIF($B23:$F23,"*"&J$3&"*") + COUNTIF($B23:$F23,"*"&J$1&"*") -> 0 | K23: =COUNTIF($B23:$F23,"*"&K$3&"*") -> 3 | L23: =COUNTIF($B23:$F23,"*"&L$3&"*") -> 0 | M23: =COUNTIF($B23:$F23,"*"&M$3&"*") -> 1 | N23: =SUMPRODUCT(H23:M23, (H23:M23 - 1)) / ($B$1 * ($B$1-1)) -> 0.5 | Q23: private sector | X23: =IF(ISNUMBER(SEARCH(",",B23)),"multistakeholders",lower(B23)) -> national authority | Y23: =IF(ISNUMBER(SEARCH(">",X23)),LEFT(X23,SEARCH(">",X23)-2),X23) -> national authority
A24: Thematic Reviews on 'Social Aspects of Digitalisation' (SPC) and 'Digitalisation and Robotisation of Work' (EMCO) - Endorsement of the joint key messages, 14411/18 | B24: =IF(ISNUMBER(SEARCH(",",VLOOKUP($A24,'List of documents'!A:F,6,0))),"multistakeholders",VLOOKUP($A24,'List of documents'!A:F,6,0)) -> international organisation > EU institution | C24: =IF(ISNUMBER(SEARCH(",",VLOOKUP($A24,Matthieu!$A:$I,9,0))),"multistakeholders",VLOOKUP($A24,Matthieu!$A:$I,9,0)) -> International organisation | D24: =IF(ISNUMBER(SEARCH(",",VLOOKUP($A24,Maria!$A:$I,9,0))),"multistakeholders",VLOOKUP($A24,Maria!$A:$I,9,0)) -> international organisation | E24: =IF(ISNUMBER(SEARCH(",",VLOOKUP($A24,Aina!$A:$I,9,0))),"multistakeholders",VLOOKUP($A24,Aina!$A:$I,9,0)) -> international organisation | F24: =IF(ISNUMBER(SEARCH(",",VLOOKUP($A24,Tiphaine!$A:$I,9,0))),"multistakeholders",VLOOKUP($A24,Tiphaine!$A:$I,9,0)) -> international organisation | G24: =SUM(H24:M24)=$B$1 -> FALSE | H24: =COUNTIF($B24:$F24,"*"&H$3&"*") -> 0 | I24: =COUNTIF($B24:$F24,"*"&I$3&"*") -> 0 | J24: =COUNTIF($B24:$F24,"*"&J$3&"*") + COUNTIF($B24:$F24,"*"&J$1&"*") -> 5 | K24: =COUNTIF($B24:$F24,"*"&K$3&"*") -> 0 | L24: =COUNTIF($B24:$F24,"*"&L$3&"*") -> 0 | M24: =COUNTIF($B24:$F24,"*"&M$3&"*") -> 0 | N24: =SUMPRODUCT(H24:M24, (H24:M24 - 1)) / ($B$1 * ($B$1-1)) -> 1.6666667 | X24: =IF(ISNUMBER(SEARCH(",",B24)),"multistakeholders",lower(B24)) -> international organisation > eu institution | Y24: =IF(ISNUMBER(SEARCH(">",X24)),LEFT(X24,SEARCH(">",X24)-2),X24) -> international organisation
A25: Standards for AI Governance: International Standards to Enable Global Coordination in AI Research & Development | B25: =IF(ISNUMBER(SEARCH(",",VLOOKUP($A25,'List of documents'!A:F,6,0))),"multistakeholders",VLOOKUP($A25,'List of documents'!A:F,6,0)) -> academia | C25: =IF(ISNUMBER(SEARCH(",",VLOOKUP($A25,Matthieu!$A:$I,9,0))),"multistakeholders",VLOOKUP($A25,Matthieu!$A:$I,9,0)) -> Academia | D25: =IF(ISNUMBER(SEARCH(",",VLOOKUP($A25,Maria!$A:$I,9,0))),"multistakeholders",VLOOKUP($A25,Maria!$A:$I,9,0)) -> multistakeholders | E25: =IF(ISNUMBER(SEARCH(",",VLOOKUP($A25,Aina!$A:$I,9,0))),"multistakeholders",VLOOKUP($A25,Aina!$A:$I,9,0)) -> multistakeholders | F25: =IF(ISNUMBER(SEARCH(",",VLOOKUP($A25,Tiphaine!$A:$I,9,0))),"multistakeholders",VLOOKUP($A25,Tiphaine!$A:$I,9,0)) | G25: =SUM(H25:M25)=$B$1 -> TRUE | H25: =COUNTIF($B25:$F25,"*"&H$3&"*") -> 2 | I25: =COUNTIF($B25:$F25,"*"&I$3&"*") -> 0 | J25: =COUNTIF($B25:$F25,"*"&J$3&"*") + COUNTIF($B25:$F25,"*"&J$1&"*") -> 0 | K25: =COUNTIF($B25:$F25,"*"&K$3&"*") -> 0 | L25: =COUNTIF($B25:$F25,"*"&L$3&"*") -> 0 | M25: =COUNTIF($B25:$F25,"*"&M$3&"*") -> 2 | N25: =SUMPRODUCT(H25:M25, (H25:M25 - 1)) / ($B$1 * ($B$1-1)) -> 0.33333333 | X25: =IF(ISNUMBER(SEARCH(",",B25)),"multistakeholders",lower(B25)) -> academia | Y25: =IF(ISNUMBER(SEARCH(">",X25)),LEFT(X25,SEARCH(">",X25)-2),X25) -> academia
A26: Preparing the future of AI | B26: =IF(ISNUMBER(SEARCH(",",VLOOKUP($A26,'List of documents'!A:F,6,0))),"multistakeholders",VLOOKUP($A26,'List of documents'!A:F,6,0)) -> national authority | C26: =IF(ISNUMBER(SEARCH(",",VLOOKUP($A26,Matthieu!$A:$I,9,0))),"multistakeholders",VLOOKUP($A26,Matthieu!$A:$I,9,0)) -> National authority | D26: =IF(ISNUMBER(SEARCH(",",VLOOKUP($A26,Maria!$A:$I,9,0))),"multistakeholders",VLOOKUP($A26,Maria!$A:$I,9,0)) -> national authority | E26: =IF(ISNUMBER(SEARCH(",",VLOOKUP($A26,Aina!$A:$I,9,0))),"multistakeholders",VLOOKUP($A26,Aina!$A:$I,9,0)) -> national authority | F26: =IF(ISNUMBER(SEARCH(",",VLOOKUP($A26,Tiphaine!$A:$I,9,0))),"multistakeholders",VLOOKUP($A26,Tiphaine!$A:$I,9,0)) | G26: =SUM(H26:M26)=$B$1 -> TRUE | H26: =COUNTIF($B26:$F26,"*"&H$3&"*") -> 0 | I26: =COUNTIF($B26:$F26,"*"&I$3&"*") -> 0 | J26: =COUNTIF($B26:$F26,"*"&J$3&"*") + COUNTIF($B26:$F26,"*"&J$1&"*") -> 0 | K26: =COUNTIF($B26:$F26,"*"&K$3&"*") -> 4 | L26: =COUNTIF($B26:$F26,"*"&L$3&"*") -> 0 | M26: =COUNTIF($B26:$F26,"*"&M$3&"*") -> 0 | N26: =SUMPRODUCT(H26:M26, (H26:M26 - 1)) / ($B$1 * ($B$1-1)) -> 1 | X26: =IF(ISNUMBER(SEARCH(",",B26)),"multistakeholders",lower(B26)) -> national authority | Y26: =IF(ISNUMBER(SEARCH(">",X26)),LEFT(X26,SEARCH(">",X26)-2),X26) -> national authority
A27: AI Now Report 2016. The Social and Economic Implications of Artificial Intelligence Technologies in the Near-Term | B27: =IF(ISNUMBER(SEARCH(",",VLOOKUP($A27,'List of documents'!A:F,6,0))),"multistakeholders",VLOOKUP($A27,'List of documents'!A:F,6,0)) -> civil society > NGO | C27: =IF(ISNUMBER(SEARCH(",",VLOOKUP($A27,Matthieu!$A:$I,9,0))),"multistakeholders",VLOOKUP($A27,Matthieu!$A:$I,9,0)) -> multistakeholders | D27: =IF(ISNUMBER(SEARCH(",",VLOOKUP($A27,Maria!$A:$I,9,0))),"multistakeholders",VLOOKUP($A27,Maria!$A:$I,9,0)) -> multistakeholders | E27: =IF(ISNUMBER(SEARCH(",",VLOOKUP($A27,Aina!$A:$I,9,0))),"multistakeholders",VLOOKUP($A27,Aina!$A:$I,9,0)) -> multistakeholders | F27: =IF(ISNUMBER(SEARCH(",",VLOOKUP($A27,Tiphaine!$A:$I,9,0))),"multistakeholders",VLOOKUP($A27,Tiphaine!$A:$I,9,0)) | G27: =SUM(H27:M27)=$B$1 -> TRUE | H27: =COUNTIF($B27:$F27,"*"&H$3&"*") -> 0 | I27: =COUNTIF($B27:$F27,"*"&I$3&"*") -> 1 | J27: =COUNTIF($B27:$F27,"*"&J$3&"*") + COUNTIF($B27:$F27,"*"&J$1&"*") -> 0 | K27: =COUNTIF($B27:$F27,"*"&K$3&"*") -> 0 | L27: =COUNTIF($B27:$F27,"*"&L$3&"*") -> 0 | M27: =COUNTIF($B27:$F27,"*"&M$3&"*") -> 3 | N27: =SUMPRODUCT(H27:M27, (H27:M27 - 1)) / ($B$1 * ($B$1-1)) -> 0.5 | X27: =IF(ISNUMBER(SEARCH(",",B27)),"multistakeholders",lower(B27)) -> civil society > ngo | Y27: =IF(ISNUMBER(SEARCH(">",X27)),LEFT(X27,SEARCH(">",X27)-2),X27) -> civil society
A28: G20 AI Principles | B28: =IF(ISNUMBER(SEARCH(",",VLOOKUP($A28,'List of documents'!A:F,6,0))),"multistakeholders",VLOOKUP($A28,'List of documents'!A:F,6,0)) -> national authority | C28: =IF(ISNUMBER(SEARCH(",",VLOOKUP($A28,Matthieu!$A:$I,9,0))),"multistakeholders",VLOOKUP($A28,Matthieu!$A:$I,9,0)) -> National authority | D28: =IF(ISNUMBER(SEARCH(",",VLOOKUP($A28,Maria!$A:$I,9,0))),"multistakeholders",VLOOKUP($A28,Maria!$A:$I,9,0)) -> international organisation | E28: =IF(ISNUMBER(SEARCH(",",VLOOKUP($A28,Aina!$A:$I,9,0))),"multistakeholders",VLOOKUP($A28,Aina!$A:$I,9,0)) -> international organisation | F28: =IF(ISNUMBER(SEARCH(",",VLOOKUP($A28,Tiphaine!$A:$I,9,0))),"multistakeholders",VLOOKUP($A28,Tiphaine!$A:$I,9,0)) | G28: =SUM(H28:M28)=$B$1 -> TRUE | H28: =COUNTIF($B28:$F28,"*"&H$3&"*") -> 0 | I28: =COUNTIF($B28:$F28,"*"&I$3&"*") -> 0 | J28: =COUNTIF($B28:$F28,"*"&J$3&"*") + COUNTIF($B28:$F28,"*"&J$1&"*") -> 2 | K28: =COUNTIF($B28:$F28,"*"&K$3&"*") -> 2 | L28: =COUNTIF($B28:$F28,"*"&L$3&"*") -> 0 | M28: =COUNTIF($B28:$F28,"*"&M$3&"*") -> 0 | N28: =SUMPRODUCT(H28:M28, (H28:M28 - 1)) / ($B$1 * ($B$1-1)) -> 0.33333333 | X28: =IF(ISNUMBER(SEARCH(",",B28)),"multistakeholders",lower(B28)) -> national authority | Y28: =IF(ISNUMBER(SEARCH(">",X28)),LEFT(X28,SEARCH(">",X28)-2),X28) -> national authority
A29: Principles for the Governance of AI | B29: =IF(ISNUMBER(SEARCH(",",VLOOKUP($A29,'List of documents'!A:F,6,0))),"multistakeholders",VLOOKUP($A29,'List of documents'!A:F,6,0)) -> civil society | C29: =IF(ISNUMBER(SEARCH(",",VLOOKUP($A29,Matthieu!$A:$I,9,0))),"multistakeholders",VLOOKUP($A29,Matthieu!$A:$I,9,0)) -> Civil society | D29: =IF(ISNUMBER(SEARCH(",",VLOOKUP($A29,Maria!$A:$I,9,0))),"multistakeholders",VLOOKUP($A29,Maria!$A:$I,9,0)) -> civil society | E29: =IF(ISNUMBER(SEARCH(",",VLOOKUP($A29,Aina!$A:$I,9,0))),"multistakeholders",VLOOKUP($A29,Aina!$A:$I,9,0)) -> civil society | F29: =IF(ISNUMBER(SEARCH(",",VLOOKUP($A29,Tiphaine!$A:$I,9,0))),"multistakeholders",VLOOKUP($A29,Tiphaine!$A:$I,9,0)) | G29: =SUM(H29:M29)=$B$1 -> TRUE | H29: =COUNTIF($B29:$F29,"*"&H$3&"*") -> 0 | I29: =COUNTIF($B29:$F29,"*"&I$3&"*") -> 4 | J29: =COUNTIF($B29:$F29,"*"&J$3&"*") + COUNTIF($B29:$F29,"*"&J$1&"*") -> 0 | K29: =COUNTIF($B29:$F29,"*"&K$3&"*") -> 0 | L29: =COUNTIF($B29:$F29,"*"&L$3&"*") -> 0 | M29: =COUNTIF($B29:$F29,"*"&M$3&"*") -> 0 | N29: =SUMPRODUCT(H29:M29, (H29:M29 - 1)) / ($B$1 * ($B$1-1)) -> 1 | X29: =IF(ISNUMBER(SEARCH(",",B29)),"multistakeholders",lower(B29)) -> civil society | Y29: =IF(ISNUMBER(SEARCH(">",X29)),LEFT(X29,SEARCH(">",X29)-2),X29) -> civil society
A30: 4 Steps to developing Responsible AI | B30: =IF(ISNUMBER(SEARCH(",",VLOOKUP($A30,'List of documents'!A:F,6,0))),"multistakeholders",VLOOKUP($A30,'List of documents'!A:F,6,0)) -> civil society > NGO | C30: =IF(ISNUMBER(SEARCH(",",VLOOKUP($A30,Matthieu!$A:$I,9,0))),"multistakeholders",VLOOKUP($A30,Matthieu!$A:$I,9,0)) -> Private sector | D30: =IF(ISNUMBER(SEARCH(",",VLOOKUP($A30,Maria!$A:$I,9,0))),"multistakeholders",VLOOKUP($A30,Maria!$A:$I,9,0)) -> multistakeholders | E30: =IF(ISNUMBER(SEARCH(",",VLOOKUP($A30,Aina!$A:$I,9,0))),"multistakeholders",VLOOKUP($A30,Aina!$A:$I,9,0)) -> civil society | F30: =IF(ISNUMBER(SEARCH(",",VLOOKUP($A30,Tiphaine!$A:$I,9,0))),"multistakeholders",VLOOKUP($A30,Tiphaine!$A:$I,9,0)) | G30: =SUM(H30:M30)=$B$1 -> TRUE | H30: =COUNTIF($B30:$F30,"*"&H$3&"*") -> 0 | I30: =COUNTIF($B30:$F30,"*"&I$3&"*") -> 2 | J30: =COUNTIF($B30:$F30,"*"&J$3&"*") + COUNTIF($B30:$F30,"*"&J$1&"*") -> 0 | K30: =COUNTIF($B30:$F30,"*"&K$3&"*") -> 0 | L30: =COUNTIF($B30:$F30,"*"&L$3&"*") -> 1 | M30: =COUNTIF($B30:$F30,"*"&M$3&"*") -> 1 | N30: =SUMPRODUCT(H30:M30, (H30:M30 - 1)) / ($B$1 * ($B$1-1)) -> 0.16666667 | X30: =IF(ISNUMBER(SEARCH(",",B30)),"multistakeholders",lower(B30)) -> civil society > ngo | Y30: =IF(ISNUMBER(SEARCH(">",X30)),LEFT(X30,SEARCH(">",X30)-2),X30) -> civil society
A31: Opinion on AI - The consequences of artificial intelligence on the (digital) single market, production, consumption, employment and society’ | B31: =IF(ISNUMBER(SEARCH(",",VLOOKUP($A31,'List of documents'!A:F,6,0))),"multistakeholders",VLOOKUP($A31,'List of documents'!A:F,6,0)) -> international organisation > EU institution | C31: =IF(ISNUMBER(SEARCH(",",VLOOKUP($A31,Matthieu!$A:$I,9,0))),"multistakeholders",VLOOKUP($A31,Matthieu!$A:$I,9,0)) -> International organisation | D31: =IF(ISNUMBER(SEARCH(",",VLOOKUP($A31,Maria!$A:$I,9,0))),"multistakeholders",VLOOKUP($A31,Maria!$A:$I,9,0)) -> multistakeholders | E31: =IF(ISNUMBER(SEARCH(",",VLOOKUP($A31,Aina!$A:$I,9,0))),"multistakeholders",VLOOKUP($A31,Aina!$A:$I,9,0)) -> international organisation | F31: =IF(ISNUMBER(SEARCH(",",VLOOKUP($A31,Tiphaine!$A:$I,9,0))),"multistakeholders",VLOOKUP($A31,Tiphaine!$A:$I,9,0)) -> international organisation | G31: =SUM(H31:M31)=$B$1 -> FALSE | H31: =COUNTIF($B31:$F31,"*"&H$3&"*") -> 0 | I31: =COUNTIF($B31:$F31,"*"&I$3&"*") -> 0 | J31: =COUNTIF($B31:$F31,"*"&J$3&"*") + COUNTIF($B31:$F31,"*"&J$1&"*") -> 4 | K31: =COUNTIF($B31:$F31,"*"&K$3&"*") -> 0 | L31: =COUNTIF($B31:$F31,"*"&L$3&"*") -> 0 | M31: =COUNTIF($B31:$F31,"*"&M$3&"*") -> 1 | N31: =SUMPRODUCT(H31:M31, (H31:M31 - 1)) / ($B$1 * ($B$1-1)) -> 1 | X31: =IF(ISNUMBER(SEARCH(",",B31)),"multistakeholders",lower(B31)) -> international organisation > eu institution | Y31: =IF(ISNUMBER(SEARCH(">",X31)),LEFT(X31,SEARCH(">",X31)-2),X31) -> international organisation
A32: Human Rights Impact Assessments for AI: Analysis and Recommendations | B32: =IF(ISNUMBER(SEARCH(",",VLOOKUP($A32,'List of documents'!A:F,6,0))),"multistakeholders",VLOOKUP($A32,'List of documents'!A:F,6,0)) -> civil society > NGO | C32: =IF(ISNUMBER(SEARCH(",",VLOOKUP($A32,Matthieu!$A:$I,9,0))),"multistakeholders",VLOOKUP($A32,Matthieu!$A:$I,9,0)) -> multistakeholders | D32: =IF(ISNUMBER(SEARCH(",",VLOOKUP($A32,Maria!$A:$I,9,0))),"multistakeholders",VLOOKUP($A32,Maria!$A:$I,9,0)) -> multistakeholders | E32: =IF(ISNUMBER(SEARCH(",",VLOOKUP($A32,Aina!$A:$I,9,0))),"multistakeholders",VLOOKUP($A32,Aina!$A:$I,9,0)) -> civil society | F32: =IF(ISNUMBER(SEARCH(",",VLOOKUP($A32,Tiphaine!$A:$I,9,0))),"multistakeholders",VLOOKUP($A32,Tiphaine!$A:$I,9,0)) | G32: =SUM(H32:M32)=$B$1 -> TRUE | H32: =COUNTIF($B32:$F32,"*"&H$3&"*") -> 0 | I32: =COUNTIF($B32:$F32,"*"&I$3&"*") -> 2 | J32: =COUNTIF($B32:$F32,"*"&J$3&"*") + COUNTIF($B32:$F32,"*"&J$1&"*") -> 0 | K32: =COUNTIF($B32:$F32,"*"&K$3&"*") -> 0 | L32: =COUNTIF($B32:$F32,"*"&L$3&"*") -> 0 | M32: =COUNTIF($B32:$F32,"*"&M$3&"*") -> 2 | N32: =SUMPRODUCT(H32:M32, (H32:M32 - 1)) / ($B$1 * ($B$1-1)) -> 0.33333333 | X32: =IF(ISNUMBER(SEARCH(",",B32)),"multistakeholders",lower(B32)) -> civil society > ngo | Y32: =IF(ISNUMBER(SEARCH(">",X32)),LEFT(X32,SEARCH(">",X32)-2),X32) -> civil society
A33: Report on Artificial intelligence in health care: medical, legal and ethical challenges ahead | B33: =IF(ISNUMBER(SEARCH(",",VLOOKUP($A33,'List of documents'!A:F,6,0))),"multistakeholders",VLOOKUP($A33,'List of documents'!A:F,6,0)) -> international organisation > IGO | C33: =IF(ISNUMBER(SEARCH(",",VLOOKUP($A33,Matthieu!$A:$I,9,0))),"multistakeholders",VLOOKUP($A33,Matthieu!$A:$I,9,0)) -> International organisation | D33: =IF(ISNUMBER(SEARCH(",",VLOOKUP($A33,Maria!$A:$I,9,0))),"multistakeholders",VLOOKUP($A33,Maria!$A:$I,9,0)) -> international organisation | E33: =IF(ISNUMBER(SEARCH(",",VLOOKUP($A33,Aina!$A:$I,9,0))),"multistakeholders",VLOOKUP($A33,Aina!$A:$I,9,0)) -> international organisation | F33: =IF(ISNUMBER(SEARCH(",",VLOOKUP($A33,Tiphaine!$A:$I,9,0))),"multistakeholders",VLOOKUP($A33,Tiphaine!$A:$I,9,0)) -> international organisation | G33: =SUM(H33:M33)=$B$1 -> FALSE | H33: =COUNTIF($B33:$F33,"*"&H$3&"*") -> 0 | I33: =COUNTIF($B33:$F33,"*"&I$3&"*") -> 0 | J33: =COUNTIF($B33:$F33,"*"&J$3&"*") + COUNTIF($B33:$F33,"*"&J$1&"*") -> 5 | K33: =COUNTIF($B33:$F33,"*"&K$3&"*") -> 0 | L33: =COUNTIF($B33:$F33,"*"&L$3&"*") -> 0 | M33: =COUNTIF($B33:$F33,"*"&M$3&"*") -> 0 | N33: =SUMPRODUCT(H33:M33, (H33:M33 - 1)) / ($B$1 * ($B$1-1)) -> 1.6666667 | X33: =IF(ISNUMBER(SEARCH(",",B33)),"multistakeholders",lower(B33)) -> international organisation > igo | Y33: =IF(ISNUMBER(SEARCH(">",X33)),LEFT(X33,SEARCH(">",X33)-2),X33) -> international organisation
A34: Recomendations on the inclusion subSaharan Africa in Global AI Ethics | B34: =IF(ISNUMBER(SEARCH(",",VLOOKUP($A34,'List of documents'!A:F,6,0))),"multistakeholders",VLOOKUP($A34,'List of documents'!A:F,6,0)) -> civil society > other | C34: =IF(ISNUMBER(SEARCH(",",VLOOKUP($A34,Matthieu!$A:$I,9,0))),"multistakeholders",VLOOKUP($A34,Matthieu!$A:$I,9,0)) -> multistakeholders | D34: =IF(ISNUMBER(SEARCH(",",VLOOKUP($A34,Maria!$A:$I,9,0))),"multistakeholders",VLOOKUP($A34,Maria!$A:$I,9,0)) -> multistakeholders | E34: =IF(ISNUMBER(SEARCH(",",VLOOKUP($A34,Aina!$A:$I,9,0))),"multistakeholders",VLOOKUP($A34,Aina!$A:$I,9,0)) -> civil society | F34: =IF(ISNUMBER(SEARCH(",",VLOOKUP($A34,Tiphaine!$A:$I,9,0))),"multistakeholders",VLOOKUP($A34,Tiphaine!$A:$I,9,0)) -> civil society | G34: =SUM(H34:M34)=$B$1 -> FALSE | H34: =COUNTIF($B34:$F34,"*"&H$3&"*") -> 0 | I34: =COUNTIF($B34:$F34,"*"&I$3&"*") -> 3 | J34: =COUNTIF($B34:$F34,"*"&J$3&"*") + COUNTIF($B34:$F34,"*"&J$1&"*") -> 0 | K34: =COUNTIF($B34:$F34,"*"&K$3&"*") -> 0 | L34: =COUNTIF($B34:$F34,"*"&L$3&"*") -> 0 | M34: =COUNTIF($B34:$F34,"*"&M$3&"*") -> 2 | N34: =SUMPRODUCT(H34:M34, (H34:M34 - 1)) / ($B$1 * ($B$1-1)) -> 0.66666667 | X34: =IF(ISNUMBER(SEARCH(",",B34)),"multistakeholders",lower(B34)) -> civil society > other | Y34: =IF(ISNUMBER(SEARCH(">",X34)),LEFT(X34,SEARCH(">",X34)-2),X34) -> civil society
A35: Our principles | B35: =IF(ISNUMBER(SEARCH(",",VLOOKUP($A35,'List of documents'!A:F,6,0))),"multistakeholders",VLOOKUP($A35,'List of documents'!A:F,6,0)) -> private sector | C35: =IF(ISNUMBER(SEARCH(",",VLOOKUP($A35,Matthieu!$A:$I,9,0))),"multistakeholders",VLOOKUP($A35,Matthieu!$A:$I,9,0)) -> Private sector | D35: =IF(ISNUMBER(SEARCH(",",VLOOKUP($A35,Maria!$A:$I,9,0))),"multistakeholders",VLOOKUP($A35,Maria!$A:$I,9,0)) -> private sector | E35: =IF(ISNUMBER(SEARCH(",",VLOOKUP($A35,Aina!$A:$I,9,0))),"multistakeholders",VLOOKUP($A35,Aina!$A:$I,9,0)) -> private sector | F35: =IF(ISNUMBER(SEARCH(",",VLOOKUP($A35,Tiphaine!$A:$I,9,0))),"multistakeholders",VLOOKUP($A35,Tiphaine!$A:$I,9,0)) -> industry | G35: =SUM(H35:M35)=$B$1 -> TRUE | H35: =COUNTIF($B35:$F35,"*"&H$3&"*") -> 0 | I35: =COUNTIF($B35:$F35,"*"&I$3&"*") -> 0 | J35: =COUNTIF($B35:$F35,"*"&J$3&"*") + COUNTIF($B35:$F35,"*"&J$1&"*") -> 0 | K35: =COUNTIF($B35:$F35,"*"&K$3&"*") -> 0 | L35: =COUNTIF($B35:$F35,"*"&L$3&"*") -> 4 | M35: =COUNTIF($B35:$F35,"*"&M$3&"*") -> 0 | N35: =SUMPRODUCT(H35:M35, (H35:M35 - 1)) / ($B$1 * ($B$1-1)) -> 1 | X35: =IF(ISNUMBER(SEARCH(",",B35)),"multistakeholders",lower(B35)) -> private sector | Y35: =IF(ISNUMBER(SEARCH(">",X35)),LEFT(X35,SEARCH(">",X35)-2),X35) -> private sector
... A47: The right to privacy in the digital age | B47: =IF(ISNUMBER(SEARCH(",",VLOOKUP($A47,'List of documents'!A:F,6,0))),"multistakeholders",VLOOKUP($A47,'List of documents'!A:F,6,0)) -> international organisation > IGO | C47: =IF(ISNUMBER(SEARCH(",",VLOOKUP($A47,Matthieu!$A:$I,9,0))),"multistakeholders",VLOOKUP($A47,Matthieu!$A:$I,9,0)) -> International organisation | D47: =IF(ISNUMBER(SEARCH(",",VLOOKUP($A47,Maria!$A:$I,9,0))),"multistakeholders",VLOOKUP($A47,Maria!$A:$I,9,0)) -> international organisation | E47: =IF(ISNUMBER(SEARCH(",",VLOOKUP($A47,Aina!$A:$I,9,0))),"multistakeholders",VLOOKUP($A47,Aina!$A:$I,9,0)) -> international organisation | F47: =IF(ISNUMBER(SEARCH(",",VLOOKUP($A47,Tiphaine!$A:$I,9,0))),"multistakeholders",VLOOKUP($A47,Tiphaine!$A:$I,9,0)) -> international organisation | G47: =SUM(H47:M47)=$B$1 -> FALSE | H47: =COUNTIF($B47:$F47,"*"&H$3&"*") -> 0 | I47: =COUNTIF($B47:$F47,"*"&I$3&"*") -> 0 | J47: =COUNTIF($B47:$F47,"*"&J$3&"*") + COUNTIF($B47:$F47,"*"&J$1&"*") -> 5 | K47: =COUNTIF($B47:$F47,"*"&K$3&"*") -> 0 | L47: =COUNTIF($B47:$F47,"*"&L$3&"*") -> 0 | M47: =COUNTIF($B47:$F47,"*"&M$3&"*") -> 0 | N47: =SUMPRODUCT(H47:M47, (H47:M47 - 1)) / ($B$1 * ($B$1-1)) -> 1.6666667 | X47: =IF(ISNUMBER(SEARCH(",",B47)),"multistakeholders",lower(B47)) -> international organisation > igo | Y47: =IF(ISNUMBER(SEARCH(">",X47)),LEFT(X47,SEARCH(">",X47)-2),X47) -> international organisation
X48: =IF(ISNUMBER(SEARCH(",",B48)),"multistakeholders",lower(B48))
G49: Proportions par catégorie | H49: =SUM(H4:H47) / ($B$1*$B$2) -> 0.17045455 | I49: =SUM(I4:I47) / ($B$1*$B$2) -> 0.23295455 | J49: =SUM(J4:J47) / ($B$1*$B$2) -> 0.28409091 | K49: =SUM(K4:K47) / ($B$1*$B$2) -> 0.17045455 | L49: =SUM(L4:L47) / ($B$1*$B$2) -> 0.068181818 | M49: =SUM(M4:M47) / ($B$1*$B$2) -> 0.22159091 | X49: =IF(ISNUMBER(SEARCH(",",B49)),"multistakeholders",lower(B49))
G50: check | H50: =sum(H49:M49)=1 -> FALSE | X50: =IF(ISNUMBER(SEARCH(",",B50)),"multistakeholders",lower(B50))
X51: =IF(ISNUMBER(SEARCH(",",B51)),"multistakeholders",lower(B51))
X52: =IF(ISNUMBER(SEARCH(",",B52)),"multistakeholders",lower(B52))
X53: =IF(ISNUMBER(SEARCH(",",B53)),"multistakeholders",lower(B53))
X54: =IF(ISNUMBER(SEARCH(",",B54)),"multistakeholders",lower(B54))
X55: =IF(ISNUMBER(SEARCH(",",B55)),"multistakeholders",lower(B55))
X56: =IF(ISNUMBER(SEARCH(",",B56)),"multistakeholders",lower(B56))
X57: =IF(ISNUMBER(SEARCH(",",B57)),"multistakeholders",lower(B57))
X58: =IF(ISNUMBER(SEARCH(",",B58)),"multistakeholders",lower(B58))
X59: =IF(ISNUMBER(SEARCH(",",B59)),"multistakeholders",lower(B59))
X60: =IF(ISNUMBER(SEARCH(",",B60)),"multistakeholders",lower(B60))
X61: =IF(ISNUMBER(SEARCH(",",B61)),"multistakeholders",lower(B61))
X62: =IF(ISNUMBER(SEARCH(",",B62)),"multistakeholders",lower(B62))
... X79: =IF(ISNUMBER(SEARCH(",",B79)),"multistakeholders",lower(B79))

Sheet Statistics
A1: Documents in the list
H2: Number of documents to classify / pers = 181
B3: Crawled | C3: Not crawled | D3: Not included | E3: Total
A4: Gornet-Viard | B4: {=SUM(IF('List of documents'!$K:$K=Statistics!B$3,1,0))} -> 0 | C4: {=SUM(IF('List of documents'!$K:$K=Statistics!C$3,1,0))} -> 0 | D4: {=SUM(IF('List of documents'!$K:$K=Statistics!D$3,1,0))} -> 294 | E4: =SUM(B4:D4) -> 294
A5: Jobin | B5: {=SUM(IF('List of documents'!$K:$K=Statistics!B$3,IF('List of documents'!$N:$N=1,1,0)))} -> 0 | C5: {=SUM(IF('List of documents'!$K:$K=Statistics!C$3,IF('List of documents'!$N:$N=1,1,0)))} -> 0 | D5: {=SUM(IF('List of documents'!$K:$K=Statistics!D$3,IF('List of documents'!$N:$N=1,1,0)))} -> 9 | E5: =SUM(B5:D5) -> 9 | N5: =J5/M5 -> #DIV/0!
A6: Fjeld | B6: {=SUM(IF('List of documents'!$K:$K=Statistics!B$3,IF('List of documents'!$O:$O=1,1,0)))} -> 0 | C6: {=SUM(IF('List of documents'!$K:$K=Statistics!C$3,IF('List of documents'!$O:$O=1,1,0)))} -> 0 | D6: {=SUM(IF('List of documents'!$K:$K=Statistics!D$3,IF('List of documents'!$O:$O=1,1,0)))} -> 5 | E6: =SUM(B6:D6) -> 5 | N6: =J6/M6 -> #DIV/0!
A7: Tidjon | B7: {=SUM(IF('List of documents'!$K:$K=Statistics!B$3,IF('List of documents'!$P:$P=1,1,0)))} -> 0 | C7: {=SUM(IF('List of documents'!$K:$K=Statistics!C$3,IF('List of documents'!$P:$P=1,1,0)))} -> 0 | D7: {=SUM(IF('List of documents'!$K:$K=Statistics!D$3,IF('List of documents'!$P:$P=1,1,0)))} -> 14 | E7: =SUM(B7:D7) -> 14 | N7: =J7/M7 -> #DIV/0!
A8: CE | B8: {=SUM(IF('List of documents'!$K:$K=Statistics!B$3,IF('List of documents'!$W:$W=1,1,0)))} -> 0 | C8: {=SUM(IF('List of documents'!$K:$K=Statistics!C$3,IF('List of documents'!$W:$W=1,1,0)))} -> 0 | D8: {=SUM(IF('List of documents'!$K:$K=Statistics!D$3,IF('List of documents'!$W:$W=1,1,0)))} -> 235 | E8: =SUM(B8:D8) -> 235 | N8: =J8/M8 -> #DIV/0!
N9: =J9/M9 -> #DIV/0!
A10: Documents in commun (Excel Sheet) | N10: =J10/M10 -> #DIV/0!
B12: Gornet-Viard | C12: Jobin | D12: Fjeld | E12: Tidjon | F12: CE
A13: Gornet-Viard | B13: =E4 -> 294 | C13: =C14 -> 9 | D13: =D15 -> 5 | E13: =E16 -> 14 | F13: =F17 -> 235
A14: Jobin | C14: =E5 -> 9 | D14: {=SUM(IF('List of documents'!$N:$N=1,IF('List of documents'!$O:$O=1,1,0)))} -> 20 | E14: {=SUM(IF('List of documents'!$N:$N=1,IF('List of documents'!$P:$P=1,1,0)))} -> 3 | F14: {=SUM(IF('List of documents'!$N:$N=1,IF('List of documents'!$W:$W=1,1,0)))} -> 69
A15: Fjeld | D15: =E6 -> 5 | E15: {=SUM(IF('List of documents'!$O:$O=1,IF('List of documents'!$P:$P=1,1,0)))} -> 2 | F15: {=SUM(IF('List of documents'!$O:$O=1,IF('List of documents'!$W:$W=1,1,0)))} -> 31
A16: Tidjon | E16: =E7 -> 14 | F16: {=SUM(IF('List of documents'!$P:$P=1,IF('List of documents'!$W:$W=1,1,0)))} -> 8
A17: CE | F17: =E8 -> 235
A19: Documents in commun (Crawled)
B21: Gornet-Viard | C21: Jobin | D21: Fjeld | E21: Tidjon | F21: CE
A22: Gornet-Viard | B22: =B4 -> 0 | C22: =B5 -> 0 | D22: =B6 -> 0 | E22: =B7 -> 0 | F22: =B8 -> 0
A23: Jobin | C23: =C14 -> 9 | D23: =D14 -> 20 | E23: =E14 -> 3 | F23: =F14 -> 69
A24: Fjeld | D24: =D15 -> 5 | E24: =E15 -> 2 | F24: =F15 -> 31
A25: Tidjon | E25: =E16 -> 14 | F25: =F16 -> 8
A26: CE | E26: =E17 | F26: =F17 -> 235
A28: Affiliation
A31: Gornet-Viard
A32: Jobin
A33: Fjeld
A34: Tidjon
A35: CE
A37: Countries
A40: Gornet-Viard
A41: Jobin
A42: Fjeld
A43: Tidjon
A44: CE
... A53: CE

Sheet Simon
A1: URL | B1: INDEX | C1: TOCHECK | D1: Status | E1: Tiphaine | F1: Maria | G1: Simon | H1: Tiphaine | I1: Maria | J1: Simon/Tiphaine | K1: Simon/Maria | L1: Tiphaine/Maria | M1: Aggreement
A2: https://www.accenture.com/t20160629T012639Z__w__/us-en/_acnmedia/PDF-24/Accenture-Universal-Principles-Data-Ethics.pdf new URL https://fr.scribd.com/document/450122018/Accenture-Universal-Principles-Data-Ethics# | B2: 0 | E2: =VLOOKUP(A2,'List of documents'!C:K,9,0) -> not included | F2: =VLOOKUP(A2,'Annotation-old-Maria'!A:D,4,0) | G2: =IF(LOWER(D2)="included",1,0) -> 0 | H2: =IF(LOWER(E2)="included",1,0) -> 0 | I2: =IF(LOWER(F2)="included",1,0) -> 0
A3: https://www.accessnow.org/cms/assets/uploads/2018/11/AI-and-Human-Rights.pdf | B3: 1 | C3: 1 | D3: included | E3: =VLOOKUP(A3,'List of documents'!C:K,9,0) -> included | F3: =VLOOKUP(A3,'Annotation-old-Maria'!A:D,4,0) -> Included | G3: =IF(LOWER(D3)="included",1,0) -> 1 | H3: =IF(LOWER(E3)="included",1,0) -> 1 | I3: =IF(LOWER(F3)="included",1,0) -> 1 | J3: =IF(G3=H3,1,0) -> 1 | K3: =IF(G3=I3,1,0) -> 1 | L3: =IF(H3=I3,1,0) -> 1 | M3: =sum(J3:L3)/3 -> 1 | O3: Inter reliability Agreement
A4: https://www.torontodeclaration.org/declaration-text/english/ | B4: 2 | C4: 1 | D4: included | E4: =VLOOKUP(A4,'List of documents'!C:K,9,0) -> included | F4: =VLOOKUP(A4,'Annotation-old-Maria'!A:D,4,0) -> Included | G4: =IF(LOWER(D4)="included",1,0) -> 1 | H4: =IF(LOWER(E4)="included",1,0) -> 1 | I4: =IF(LOWER(F4)="included",1,0) -> 1 | J4: =IF(G4=H4,1,0) -> 1 | K4: =IF(G4=I4,1,0) -> 1 | L4: =IF(H4=I4,1,0) -> 1 | M4: =sum(J4:L4)/3 -> 1 | O4: =AVERAGE(M3:M205) * 100 -> 85.714286
A5: https://www.accessnow.org/wp-content/uploads/2020/12/Europes-approach-to-AI-strategy-is-evolving.pdf | B5: 3 | E5: =VLOOKUP(A5,'List of documents'!C:K,9,0) -> included | F5: =VLOOKUP(A5,'Annotation-old-Maria'!A:D,4,0) | G5: =IF(LOWER(D5)="included",1,0) -> 0 | H5: =IF(LOWER(E5)="included",1,0) -> 1 | I5: =IF(LOWER(F5)="included",1,0) -> 0
A6: https://www.accessnow.org/cms/assets/uploads/2022/11/Access-Now-Version-Human-Rights-Implications-of-Algorithmic-Impact-Assessments_-Priority-Recommendations-to-Guide-Effective-Development-and-Use.pdf | B6: 4 | E6: =VLOOKUP(A6,'List of documents'!C:K,9,0) -> included | F6: =VLOOKUP(A6,'Annotation-old-Maria'!A:D,4,0) | G6: =IF(LOWER(D6)="included",1,0) -> 0 | H6: =IF(LOWER(E6)="included",1,0) -> 1 | I6: =IF(LOWER(F6)="included",1,0) -> 0
A7: accessnow.org/wp-content/uploads/2018/11/mapping_regulatory_proposals_for_AI_in_EU.pdf | B7: 5 | C7: 1 | D7: included | E7: =VLOOKUP(A7,'List of documents'!C:K,9,0) -> not included | F7: =VLOOKUP(A7,'Annotation-old-Maria'!A:D,4,0) -> Included | G7: =IF(LOWER(D7)="included",1,0) -> 1 | H7: =IF(LOWER(E7)="included",1,0) -> 0 | I7: =IF(LOWER(F7)="included",1,0) -> 1 | J7: =IF(G7=H7,1,0) -> 0 | K7: =IF(G7=I7,1,0) -> 1 | L7: =IF(H7=I7,1,0) -> 0 | M7: =sum(J7:L7)/3 -> 0.33333333
A8: https://www.adalovelaceinstitute.org/wp-content/uploads/2022/03/Expert-opinion-Lilian-Edwards-Regulating-AI-in-Europe.pdf | B8: 6 | E8: =VLOOKUP(A8,'List of documents'!C:K,9,0) -> included | F8: =VLOOKUP(A8,'Annotation-old-Maria'!A:D,4,0) | G8: =IF(LOWER(D8)="included",1,0) -> 0 | H8: =IF(LOWER(E8)="included",1,0) -> 1 | I8: =IF(LOWER(F8)="included",1,0) -> 0
A9: https://www.ethicscanvas.org/index.html | B9: 7 | E9: =VLOOKUP(A9,'List of documents'!C:K,9,0) -> not included | F9: =VLOOKUP(A9,'Annotation-old-Maria'!A:D,4,0) | G9: =IF(LOWER(D9)="included",1,0) -> 0 | H9: =IF(LOWER(E9)="included",1,0) -> 0 | I9: =IF(LOWER(F9)="included",1,0) -> 0
A10: http://www.adel-label.com/adel/ | B10: 8 | C10: 1 | D10: not included | E10: =VLOOKUP(A10,'List of documents'!C:K,9,0) -> not included | F10: =VLOOKUP(A10,'Annotation-old-Maria'!A:D,4,0) -> Not included | G10: =IF(LOWER(D10)="included",1,0) -> 0 | H10: =IF(LOWER(E10)="included",1,0) -> 0 | I10: =IF(LOWER(F10)="included",1,0) -> 0 | J10: =IF(G10=H10,1,0) -> 1 | K10: =IF(G10=I10,1,0) -> 1 | L10: =IF(H10=I10,1,0) -> 1 | M10: =sum(J10:L10)/3 -> 1
A11: https://www.adobe.com/about-adobe/aiethics.html | B11: 9 | E11: =VLOOKUP(A11,'List of documents'!C:K,9,0) -> included | F11: =VLOOKUP(A11,'Annotation-old-Maria'!A:D,4,0) | G11: =IF(LOWER(D11)="included",1,0) -> 0 | H11: =IF(LOWER(E11)="included",1,0) -> 1 | I11: =IF(LOWER(F11)="included",1,0) -> 0
A12: https://www8.cao.go.jp/cstp/tyousakai/ai/summary/aisociety_en.pdf | B12: 10 | C12: 1 | D12: not included | E12: =VLOOKUP(A12,'List of documents'!C:K,9,0) -> included | F12: =VLOOKUP(A12,'Annotation-old-Maria'!A:D,4,0) -> Not included | G12: =IF(LOWER(D12)="included",1,0) -> 0 | H12: =IF(LOWER(E12)="included",1,0) -> 1 | I12: =IF(LOWER(F12)="included",1,0) -> 0 | J12: =IF(G12=H12,1,0) -> 0 | K12: =IF(G12=I12,1,0) -> 1 | L12: =IF(H12=I12,1,0) -> 0 | M12: =sum(J12:L12)/3 -> 0.33333333
A13: https://ai-white-paper.readthedocs.io/en/latest/ | B13: 11 | E13: =VLOOKUP(A13,'List of documents'!C:K,9,0) -> included | F13: =VLOOKUP(A13,'Annotation-old-Maria'!A:D,4,0) | G13: =IF(LOWER(D13)="included",1,0) -> 0 | H13: =IF(LOWER(E13)="included",1,0) -> 1 | I13: =IF(LOWER(F13)="included",1,0) -> 0
A14: https://assets.publishing.service.gov.uk/media/5ff3bc6e8fa8f53b76ccee23/AI_Council_AI_Roadmap.pdf | B14: 12 | C14: 1 | D14: included | E14: =VLOOKUP(A14,'List of documents'!C:K,9,0) -> included | F14: =VLOOKUP(A14,'Annotation-old-Maria'!A:D,4,0) -> Included | G14: =IF(LOWER(D14)="included",1,0) -> 1 | H14: =IF(LOWER(E14)="included",1,0) -> 1 | I14: =IF(LOWER(F14)="included",1,0) -> 1 | J14: =IF(G14=H14,1,0) -> 1 | K14: =IF(G14=I14,1,0) -> 1 | L14: =IF(H14=I14,1,0) -> 1 | M14: =sum(J14:L14)/3 -> 1
A15: https://data.govt.nz/assets/data-ethics/algorithm/Trustworthy-AI-in-Aotearoa-March-2020.pdf | B15: 13 | E15: =VLOOKUP(A15,'List of documents'!C:K,9,0) -> included | F15: =VLOOKUP(A15,'Annotation-old-Maria'!A:D,4,0) | G15: =IF(LOWER(D15)="included",1,0) -> 0 | H15: =IF(LOWER(E15)="included",1,0) -> 1 | I15: =IF(LOWER(F15)="included",1,0) -> 0
A16: https://ainowinstitute.org/wp-content/uploads/2023/04/AI_Now_2017_Report.pdf | B16: 14 | E16: =VLOOKUP(A16,'List of documents'!C:K,9,0) -> included | F16: =VLOOKUP(A16,'Annotation-old-Maria'!A:D,4,0) | G16: =IF(LOWER(D16)="included",1,0) -> 0 | H16: =IF(LOWER(E16)="included",1,0) -> 1 | I16: =IF(LOWER(F16)="included",1,0) -> 0
A17: https://ainowinstitute.org/wp-content/uploads/2023/04/AI_Now_2018_Report.pdf | B17: 15 | E17: =VLOOKUP(A17,'List of documents'!C:K,9,0) -> included | F17: =VLOOKUP(A17,'Annotation-old-Maria'!A:D,4,0) | G17: =IF(LOWER(D17)="included",1,0) -> 0 | H17: =IF(LOWER(E17)="included",1,0) -> 1 | I17: =IF(LOWER(F17)="included",1,0) -> 0
A18: https://ainowinstitute.org/wp-content/uploads/2023/04/AI-Now-2023-Landscape-Report-FINAL.pdf | B18: 16 | C18: 1 | D18: included | E18: =VLOOKUP(A18,'List of documents'!C:K,9,0) -> included | F18: =VLOOKUP(A18,'Annotation-old-Maria'!A:D,4,0) -> Included | G18: =IF(LOWER(D18)="included",1,0) -> 1 | H18: =IF(LOWER(E18)="included",1,0) -> 1 | I18: =IF(LOWER(F18)="included",1,0) -> 1 | J18: =IF(G18=H18,1,0) -> 1 | K18: =IF(G18=I18,1,0) -> 1 | L18: =IF(H18=I18,1,0) -> 1 | M18: =sum(J18:L18)/3 -> 1
A19: https://ainowinstitute.org/wp-content/uploads/2023/04/AI_Now_2019_Report.pdf | B19: 17 | C19: 1 | D19: included | E19: =VLOOKUP(A19,'List of documents'!C:K,9,0) -> included | F19: =VLOOKUP(A19,'Annotation-old-Maria'!A:D,4,0) -> Included | G19: =IF(LOWER(D19)="included",1,0) -> 1 | H19: =IF(LOWER(E19)="included",1,0) -> 1 | I19: =IF(LOWER(F19)="included",1,0) -> 1 | J19: =IF(G19=H19,1,0) -> 1 | K19: =IF(G19=I19,1,0) -> 1 | L19: =IF(H19=I19,1,0) -> 1 | M19: =sum(J19:L19)/3 -> 1
A20: https://artificialintelligencenow.com/media/documents/AINowSummaryReport_3_RpmwKHu.pdf | B20: 18 | E20: =VLOOKUP(A20,'List of documents'!C:K,9,0) -> #N/A | F20: =VLOOKUP(A20,'Annotation-old-Maria'!A:D,4,0) | G20: =IF(LOWER(D20)="included",1,0) -> 0 | H20: =IF(LOWER(E20)="included",1,0) -> #N/A | I20: =IF(LOWER(F20)="included",1,0) -> 0
A21: https://airecht.nl/s/Artificial-Intelligence-Impact-Assessment-English.pdf | B21: 19 | C21: 1 | D21: included | E21: =VLOOKUP(A21,'List of documents'!C:K,9,0) -> included | F21: =VLOOKUP(A21,'Annotation-old-Maria'!A:D,4,0) -> Included | G21: =IF(LOWER(D21)="included",1,0) -> 1 | H21: =IF(LOWER(E21)="included",1,0) -> 1 | I21: =IF(LOWER(F21)="included",1,0) -> 1 | J21: =IF(G21=H21,1,0) -> 1 | K21: =IF(G21=I21,1,0) -> 1 | L21: =IF(H21=I21,1,0) -> 1 | M21: =sum(J21:L21)/3 -> 1 | O21: Output from SPSS
A22: https://www.ai4belgium.be/wp-content/uploads/2019/04/report_en.pdf | B22: 20 | E22: =VLOOKUP(A22,'List of documents'!C:K,9,0) -> included | F22: =VLOOKUP(A22,'Annotation-old-Maria'!A:D,4,0) | G22: =IF(LOWER(D22)="included",1,0) -> 0 | H22: =IF(LOWER(E22)="included",1,0) -> 1 | I22: =IF(LOWER(F22)="included",1,0) -> 0
A23: https://link.springer.com/content/pdf/10.1007/s11023-018-9482-5.pdf | B23: 21 | C23: 1 | D23: included | E23: =VLOOKUP(A23,'List of documents'!C:K,9,0) -> included | F23: =VLOOKUP(A23,'Annotation-old-Maria'!A:D,4,0) -> Included | G23: =IF(LOWER(D23)="included",1,0) -> 1 | H23: =IF(LOWER(E23)="included",1,0) -> 1 | I23: =IF(LOWER(F23)="included",1,0) -> 1 | J23: =IF(G23=H23,1,0) -> 1 | K23: =IF(G23=I23,1,0) -> 1 | L23: =IF(H23=I23,1,0) -> 1 | M23: =sum(J23:L23)/3 -> 1
A24: https://www.ai-ethics-impact.org/resource/blob/1961130/c6db9894ee73aefa489d6249f5ee2b9f/aieig---report---download-hb-data.pdf | B24: 22 | C24: 1 | D24: included | E24: =VLOOKUP(A24,'List of documents'!C:K,9,0) -> included | F24: =VLOOKUP(A24,'Annotation-old-Maria'!A:D,4,0) -> Included | G24: =IF(LOWER(D24)="included",1,0) -> 1 | H24: =IF(LOWER(E24)="included",1,0) -> 1 | I24: =IF(LOWER(F24)="included",1,0) -> 1 | J24: =IF(G24=H24,1,0) -> 1 | K24: =IF(G24=I24,1,0) -> 1 | L24: =IF(H24=I24,1,0) -> 1 | M24: =sum(J24:L24)/3 -> 1
A25: https://www.aisoma.de/wp-content/uploads/2021/01/Overview-of-National-AI-Strategies.pdf | B25: 23 | C25: 1 | D25: not included | E25: =VLOOKUP(A25,'List of documents'!C:K,9,0) -> not included | F25: =VLOOKUP(A25,'Annotation-old-Maria'!A:D,4,0) -> Not included | G25: =IF(LOWER(D25)="included",1,0) -> 0 | H25: =IF(LOWER(E25)="included",1,0) -> 0 | I25: =IF(LOWER(F25)="included",1,0) -> 0 | J25: =IF(G25=H25,1,0) -> 1 | K25: =IF(G25=I25,1,0) -> 1 | L25: =IF(H25=I25,1,0) -> 1 | M25: =sum(J25:L25)/3 -> 1
A26: https://aisp.upenn.edu/wp-content/uploads/2022/07/AISP-Toolkit_5.27.20.pdf | B26: 24 | E26: =VLOOKUP(A26,'List of documents'!C:K,9,0) -> not included | F26: =VLOOKUP(A26,'Annotation-old-Maria'!A:D,4,0) | G26: =IF(LOWER(D26)="included",1,0) -> 0 | H26: =IF(LOWER(E26)="included",1,0) -> 0 | I26: =IF(LOWER(F26)="included",1,0) -> 0
A27: https://algorithmwatch.org/wp-content/uploads/2017/06/AlgorithmWatch_Working-Paper_No_2_Ethics_ADM.pdf | B27: 25 | C27: 1 | D27: included | E27: =VLOOKUP(A27,'List of documents'!C:K,9,0) -> included | F27: =VLOOKUP(A27,'Annotation-old-Maria'!A:D,4,0) -> Not included | G27: =IF(LOWER(D27)="included",1,0) -> 1 | H27: =IF(LOWER(E27)="included",1,0) -> 1 | I27: =IF(LOWER(F27)="included",1,0) -> 0 | J27: =IF(G27=H27,1,0) -> 1 | K27: =IF(G27=I27,1,0) -> 0 | L27: =IF(H27=I27,1,0) -> 0 | M27: =sum(J27:L27)/3 -> 0.33333333
A28: https://algorithmwatch.org/wp-content/uploads/2019/01/Automating_Society_Report_2019.pdf | B28: 26 | E28: =VLOOKUP(A28,'List of documents'!C:K,9,0) -> included | F28: =VLOOKUP(A28,'Annotation-old-Maria'!A:D,4,0) | G28: =IF(LOWER(D28)="included",1,0) -> 0 | H28: =IF(LOWER(E28)="included",1,0) -> 1 | I28: =IF(LOWER(F28)="included",1,0) -> 0
A29: https://alltechishuman.org/ai-human-rights-report | B29: 27 | E29: =VLOOKUP(A29,'List of documents'!C:K,9,0) -> not included | F29: =VLOOKUP(A29,'Annotation-old-Maria'!A:D,4,0) | G29: =IF(LOWER(D29)="included",1,0) -> 0 | H29: =IF(LOWER(E29)="included",1,0) -> 0 | I29: =IF(LOWER(F29)="included",1,0) -> 0
A30: https://allai.nl/wp-content/uploads/2021/08/EU-Proposal-for-Artificial-Intelligence-Act-Analysis-and-Recommendations.pdf | B30: 28 | E30: =VLOOKUP(A30,'List of documents'!C:K,9,0) -> included | F30: =VLOOKUP(A30,'Annotation-old-Maria'!A:D,4,0) | G30: =IF(LOWER(D30)="included",1,0) -> 0 | H30: =IF(LOWER(E30)="included",1,0) -> 1 | I30: =IF(LOWER(F30)="included",1,0) -> 0
A31: https://www.nytimes.com/2017/09/01/opinion/artificial-intelligence-regulations-rules.html | B31: 29 | C31: 1 | D31: not included | E31: =VLOOKUP(A31,'List of documents'!C:K,9,0) -> not included | F31: =VLOOKUP(A31,'Annotation-old-Maria'!A:D,4,0) -> Included | G31: =IF(LOWER(D31)="included",1,0) -> 0 | H31: =IF(LOWER(E31)="included",1,0) -> 0 | I31: =IF(LOWER(F31)="included",1,0) -> 1 | J31: =IF(G31=H31,1,0) -> 1 | K31: =IF(G31=I31,1,0) -> 0 | L31: =IF(H31=I31,1,0) -> 0 | M31: =sum(J31:L31)/3 -> 0.33333333
A32: https://www.adp.com/-/media/adp/redesign2018/pdf/data-privacy/ai-ethics-statement.pdf?rev=f155df771fea4850b310f17ca407f3f1&hash=73364D9FB41931A7C1887B976538BE5C | B32: 30 | C32: 1 | D32: included | E32: =VLOOKUP(A32,'List of documents'!C:K,9,0) -> included | F32: =VLOOKUP(A32,'Annotation-old-Maria'!A:D,4,0) -> Included | G32: =IF(LOWER(D32)="included",1,0) -> 1 | H32: =IF(LOWER(E32)="included",1,0) -> 1 | I32: =IF(LOWER(F32)="included",1,0) -> 1 | J32: =IF(G32=H32,1,0) -> 1 | K32: =IF(G32=I32,1,0) -> 1 | L32: =IF(H32=I32,1,0) -> 1 | M32: =sum(J32:L32)/3 -> 1
A33: https://www.acr.org/-/media/ACR/Files/Informatics/Ethics-of-AI-in-Radiology-European-and-North-American-Multisociety-Statement--6-13-2019.pdf | B33: 31 | C33: 1 | D33: included | E33: included | F33: =VLOOKUP(A33,'Annotation-old-Maria'!A:D,4,0) -> Included | G33: =IF(LOWER(D33)="included",1,0) -> 1 | H33: =IF(LOWER(E33)="included",1,0) -> 1 | I33: =IF(LOWER(F33)="included",1,0) -> 1 | J33: =IF(G33=H33,1,0) -> 1 | K33: =IF(G33=I33,1,0) -> 1 | L33: =IF(H33=I33,1,0) -> 1 | M33: =sum(J33:L33)/3 -> 1
A34: https://policysearch.ama-assn.org/policyfinder/detail/augmented%20intelligence?uri=%2FAMADoc%2FHOD.xml-H-480.940.xml | B34: 32 | E34: =VLOOKUP(A34,'List of documents'!C:K,9,0) -> included | F34: =VLOOKUP(A34,'Annotation-old-Maria'!A:D,4,0) | G34: =IF(LOWER(D34)="included",1,0) -> 0 | H34: =IF(LOWER(E34)="included",1,0) -> 1 | I34: =IF(LOWER(F34)="included",1,0) -> 0
A35: https://rm.coe.int/feasability-study-en-cepej-2020-15/1680a0adf4 | B35: 33 | E35: =VLOOKUP(A35,'List of documents'!C:K,9,0) -> included | F35: =VLOOKUP(A35,'Annotation-old-Maria'!A:D,4,0) | G35: =IF(LOWER(D35)="included",1,0) -> 0 | H35: =IF(LOWER(E35)="included",1,0) -> 1 | I35: =IF(LOWER(F35)="included",1,0) -> 0
A36: https://rm.coe.int/prems-092922-gbr-2517-ai-and-education-txt-16x24-web/1680a956e3 | B36: 34 | E36: =VLOOKUP(A36,'List of documents'!C:K,9,0) -> included | F36: =VLOOKUP(A36,'Annotation-old-Maria'!A:D,4,0) | G36: =IF(LOWER(D36)="included",1,0) -> 0 | H36: =IF(LOWER(E36)="included",1,0) -> 1 | I36: =IF(LOWER(F36)="included",1,0) -> 0
A37: https://rm.coe.int/eurimages-entering-the-new-paradigm-051219/1680995331 | B37: 35 | E37: =VLOOKUP(A37,'List of documents'!C:K,9,0) -> included | F37: =VLOOKUP(A37,'Annotation-old-Maria'!A:D,4,0) | G37: =IF(LOWER(D37)="included",1,0) -> 0 | H37: =IF(LOWER(E37)="included",1,0) -> 1 | I37: =IF(LOWER(F37)="included",1,0) -> 0
A38: https://rm.coe.int/iris-special-2-2020en-artificial-intelligence-in-the-audiovisual-secto/1680a11e0b | B38: 36 | E38: =VLOOKUP(A38,'List of documents'!C:K,9,0) -> included | F38: =VLOOKUP(A38,'Annotation-old-Maria'!A:D,4,0) | G38: =IF(LOWER(D38)="included",1,0) -> 0 | H38: =IF(LOWER(E38)="included",1,0) -> 1 | I38: =IF(LOWER(F38)="included",1,0) -> 0
A39: https://rm.coe.int/responsability-and-ai-en/168097d9c5 | B39: 37 | E39: =VLOOKUP(A39,'List of documents'!C:K,9,0) -> included | F39: =VLOOKUP(A39,'Annotation-old-Maria'!A:D,4,0) | G39: =IF(LOWER(D39)="included",1,0) -> 0 | H39: =IF(LOWER(E39)="included",1,0) -> 1 | I39: =IF(LOWER(F39)="included",1,0) -> 0
A40: https://rm.coe.int/algorithms-and-human-rights-en-rev/16807956b5 | B40: 38 | E40: =VLOOKUP(A40,'List of documents'!C:K,9,0) -> included | F40: =VLOOKUP(A40,'Annotation-old-Maria'!A:D,4,0) | G40: =IF(LOWER(D40)="included",1,0) -> 0 | H40: =IF(LOWER(E40)="included",1,0) -> 1 | I40: =IF(LOWER(F40)="included",1,0) -> 0
A41: https://rm.coe.int/publication-content-prioritisation-report/1680a07a57 | B41: 39 | E41: =VLOOKUP(A41,'List of documents'!C:K,9,0) -> maybe | F41: =VLOOKUP(A41,'Annotation-old-Maria'!A:D,4,0) | G41: =IF(LOWER(D41)="included",1,0) -> 0 | H41: =IF(LOWER(E41)="included",1,0) -> 0 | I41: =IF(LOWER(F41)="included",1,0) -> 0
A42: https://pace.coe.int/en/files/21694/html | B42: 40 | E42: =VLOOKUP(A42,'List of documents'!C:K,9,0) -> not included | F42: =VLOOKUP(A42,'Annotation-old-Maria'!A:D,4,0) | G42: =IF(LOWER(D42)="included",1,0) -> 0 | H42: =IF(LOWER(E42)="included",1,0) -> 0 | I42: =IF(LOWER(F42)="included",1,0) -> 0
A43: http://assembly.coe.int/nw/xml/XRef/Xref-XML2HTML-EN.asp?fileid=28598&lang=en | B43: 41 | C43: 1 | D43: not included | E43: =VLOOKUP(A43,'List of documents'!C:K,9,0) -> not included | F43: =VLOOKUP(A43,'Annotation-old-Maria'!A:D,4,0) -> Not included | G43: =IF(LOWER(D43)="included",1,0) -> 0 | H43: =IF(LOWER(E43)="included",1,0) -> 0 | I43: =IF(LOWER(F43)="included",1,0) -> 0 | J43: =IF(G43=H43,1,0) -> 1 | K43: =IF(G43=I43,1,0) -> 1 | L43: =IF(H43=I43,1,0) -> 1 | M43: =sum(J43:L43)/3 -> 1
A44: https://pace.coe.int/files/28722/pdf | B44: 42 | E44: =VLOOKUP(A44,'List of documents'!C:K,9,0) -> not included | F44: =VLOOKUP(A44,'Annotation-old-Maria'!A:D,4,0) | G44: =IF(LOWER(D44)="included",1,0) -> 0 | H44: =IF(LOWER(E44)="included",1,0) -> 0 | I44: =IF(LOWER(F44)="included",1,0) -> 0
A45: https://pace.coe.int/files/28738/pdf | B45: 43 | C45: 1 | D45: included | E45: =VLOOKUP(A45,'List of documents'!C:K,9,0) -> not included | F45: =VLOOKUP(A45,'Annotation-old-Maria'!A:D,4,0) -> Included | G45: =IF(LOWER(D45)="included",1,0) -> 1 | H45: =IF(LOWER(E45)="included",1,0) -> 0 | I45: =IF(LOWER(F45)="included",1,0) -> 1 | J45: =IF(G45=H45,1,0) -> 0 | K45: =IF(G45=I45,1,0) -> 1 | L45: =IF(H45=I45,1,0) -> 0 | M45: =sum(J45:L45)/3 -> 0.33333333
A46: https://pace.coe.int/files/28737/pdf | B46: 44 | C46: 1 | D46: included | E46: =VLOOKUP(A46,'List of documents'!C:K,9,0) -> included | F46: =VLOOKUP(A46,'Annotation-old-Maria'!A:D,4,0) -> Included | G46: =IF(LOWER(D46)="included",1,0) -> 1 | H46: =IF(LOWER(E46)="included",1,0) -> 1 | I46: =IF(LOWER(F46)="included",1,0) -> 1 | J46: =IF(G46=H46,1,0) -> 1 | K46: =IF(G46=I46,1,0) -> 1 | L46: =IF(H46=I46,1,0) -> 1 | M46: =sum(J46:L46)/3 -> 1
A47: https://pace.coe.int/files/28723/pdf | B47: 45 | E47: =VLOOKUP(A47,'List of documents'!C:K,9,0) -> included | F47: =VLOOKUP(A47,'Annotation-old-Maria'!A:D,4,0) | G47: =IF(LOWER(D47)="included",1,0) -> 0 | H47: =IF(LOWER(E47)="included",1,0) -> 1 | I47: =IF(LOWER(F47)="included",1,0) -> 0
A48: https://pace.coe.int/files/28721/pdf | B48: 46 | E48: =VLOOKUP(A48,'List of documents'!C:K,9,0) -> included | F48: =VLOOKUP(A48,'Annotation-old-Maria'!A:D,4,0) | G48: =IF(LOWER(D48)="included",1,0) -> 0 | H48: =IF(LOWER(E48)="included",1,0) -> 1 | I48: =IF(LOWER(F48)="included",1,0) -> 0
A49: https://pace.coe.int/files/28715/pdf | B49: 47 | E49: =VLOOKUP(A49,'List of documents'!C:K,9,0) -> included | F49: =VLOOKUP(A49,'Annotation-old-Maria'!A:D,4,0) | G49: =IF(LOWER(D49)="included",1,0) -> 0 | H49: =IF(LOWER(E49)="included",1,0) -> 1 | I49: =IF(LOWER(F49)="included",1,0) -> 0
A50: https://pace.coe.int/files/28742/pdf | B50: 48 | C50: 1 | D50: included | E50: =VLOOKUP(A50,'List of documents'!C:K,9,0) -> included | F50: =VLOOKUP(A50,'Annotation-old-Maria'!A:D,4,0) -> Included | G50: =IF(LOWER(D50)="included",1,0) -> 1 | H50: =IF(LOWER(E50)="included",1,0) -> 1 | I50: =IF(LOWER(F50)="included",1,0) -> 1 | J50: =IF(G50=H50,1,0) -> 1 | K50: =IF(G50=I50,1,0) -> 1 | L50: =IF(H50=I50,1,0) -> 1 | M50: =sum(J50:L50)/3 -> 1
A51: https://rm.coe.int/ai-report-bil-final/16809f9a88 | B51: 49 | E51: =VLOOKUP(A51,'List of documents'!C:K,9,0) -> included | F51: =VLOOKUP(A51,'Annotation-old-Maria'!A:D,4,0) | G51: =IF(LOWER(D51)="included",1,0) -> 0 | H51: =IF(LOWER(E51)="included",1,0) -> 1 | I51: =IF(LOWER(F51)="included",1,0) -> 0
A52: https://rm.coe.int/e-relevance-of-culture-in-the-age-of-ai-expert-seminar-on-culture-crea/168091e688 | B52: 50 | E52: =VLOOKUP(A52,'List of documents'!C:K,9,0) -> included | F52: =VLOOKUP(A52,'Annotation-old-Maria'!A:D,4,0) | G52: =IF(LOWER(D52)="included",1,0) -> 0 | H52: =IF(LOWER(E52)="included",1,0) -> 1 | I52: =IF(LOWER(F52)="included",1,0) -> 0
A53: http://www.consilium.europa.eu/media/21620/19-euco-final-conclusions-en.pdf | B53: 51 | C53: 1 | D53: not included | E53: =VLOOKUP(A53,'List of documents'!C:K,9,0) -> not included | F53: =VLOOKUP(A53,'Annotation-old-Maria'!A:D,4,0) -> Not included | G53: =IF(LOWER(D53)="included",1,0) -> 0 | H53: =IF(LOWER(E53)="included",1,0) -> 0 | I53: =IF(LOWER(F53)="included",1,0) -> 0 | J53: =IF(G53=H53,1,0) -> 1 | K53: =IF(G53=I53,1,0) -> 1 | L53: =IF(H53=I53,1,0) -> 1 | M53: =sum(J53:L53)/3 -> 1
A54: https://www.consilium.europa.eu/media/37363/gender-equality_text-adopted.pdf | B54: 52 | E54: =VLOOKUP(A54,'List of documents'!C:K,9,0) -> not included | F54: =VLOOKUP(A54,'Annotation-old-Maria'!A:D,4,0) | G54: =IF(LOWER(D54)="included",1,0) -> 0 | H54: =IF(LOWER(E54)="included",1,0) -> 0 | I54: =IF(LOWER(F54)="included",1,0) -> 0
A55: https://www.consilium.europa.eu/media/46496/st11481-en20.pdf | B55: 53 | E55: =VLOOKUP(A55,'List of documents'!C:K,9,0) -> not included | F55: =VLOOKUP(A55,'Annotation-old-Maria'!A:D,4,0) | G55: =IF(LOWER(D55)="included",1,0) -> 0 | H55: =IF(LOWER(E55)="included",1,0) -> 0 | I55: =IF(LOWER(F55)="included",1,0) -> 0
A56: http://data.consilium.europa.eu/doc/document/ST-14411-2018-INIT/en/pdf | B56: 54 | E56: =VLOOKUP(A56,'List of documents'!C:K,9,0) -> included | F56: =VLOOKUP(A56,'Annotation-old-Maria'!A:D,4,0) | G56: =IF(LOWER(D56)="included",1,0) -> 0 | H56: =IF(LOWER(E56)="included",1,0) -> 1 | I56: =IF(LOWER(F56)="included",1,0) -> 0
A57: https://www.courdecassation.fr/files/files/Publications/Divers/Rapport%20open%20data/Rapport_La_Diffusion_des_donn%C3%A9es_d%C3%A9cisionnelles_et_la_jurisprudence.pdf | B57: 55 | C57: 1 | D57: not included | E57: =VLOOKUP(A57,'List of documents'!C:K,9,0) -> not included | F57: =VLOOKUP(A57,'Annotation-old-Maria'!A:D,4,0) -> Not included | G57: =IF(LOWER(D57)="included",1,0) -> 0 | H57: =IF(LOWER(E57)="included",1,0) -> 0 | I57: =IF(LOWER(F57)="included",1,0) -> 0 | J57: =IF(G57=H57,1,0) -> 1 | K57: =IF(G57=I57,1,0) -> 1 | L57: =IF(H57=I57,1,0) -> 1 | M57: =sum(J57:L57)/3 -> 1
A58: https://www.ajcact.org | B58: 56 | C58: 1 | D58: not included | E58: =VLOOKUP(A58,'List of documents'!C:K,9,0) -> not included | F58: =VLOOKUP(A58,'Annotation-old-Maria'!A:D,4,0) -> Not included | G58: =IF(LOWER(D58)="included",1,0) -> 0 | H58: =IF(LOWER(E58)="included",1,0) -> 0 | I58: =IF(LOWER(F58)="included",1,0) -> 0 | J58: =IF(G58=H58,1,0) -> 1 | K58: =IF(G58=I58,1,0) -> 1 | L58: =IF(H58=I58,1,0) -> 1 | M58: =sum(J58:L58)/3 -> 1
A59: https://www.bmi.bund.de/SharedDocs/downloads/EN/themen/it-digital-policy/recommendations-data-ethics-commission.pdf;jsessionid=F3332ECDBF9E5FFDB93910C64986F0D9.2_cid295?__blob=publicationFile&v=4 | B59: 57 | C59: 1 | D59: included | E59: =VLOOKUP(A59,'List of documents'!C:K,9,0) -> included | F59: =VLOOKUP(A59,'Annotation-old-Maria'!A:D,4,0) -> Included | G59: =IF(LOWER(D59)="included",1,0) -> 1 | H59: =IF(LOWER(E59)="included",1,0) -> 1 | I59: =IF(LOWER(F59)="included",1,0) -> 1 | J59: =IF(G59=H59,1,0) -> 1 | K59: =IF(G59=I59,1,0) -> 1 | L59: =IF(H59=I59,1,0) -> 1 | M59: =sum(J59:L59)/3 -> 1
